Workbook
Name AMAZONAS: Listas!$T$1090:$V$1100
Name ANTIOQUIA: Listas!$T$2:$V$126
Name ARAUCA: Listas!$T$1049:$V$1055
Name ARCHIPIELAGO_DE_SAN_ANDRES: Listas!$T$1088:$V$1089
Name ATLÁNTICO: Listas!$T$127:$V$149
Name BOGOTA: Listas!$T$150:$V$150
Name BOLÍVAR: Listas!$T$151:$V$196
Name BOYACÁ: Listas!$T$197:$V$319
Name CALDAS: Listas!$T$320:$V$346
Name CAQUETÁ: Listas!$T$347:$V$362
Name CASANARE: Listas!$T$1056:$V$1074
Name CAUCA: Listas!$T$363:$V$404
Name CESAR: Listas!$T$405:$V$429
Name CHOCÓ: Listas!$T$576:$V$605
Name CÓRDOBA: Listas!$T$430:$V$459
Name CUNDINAMARCA: Listas!$T$460:$V$575
Name GUAINÍA: Listas!$T$1101:$V$1108
Name GUAVIARE: Listas!$T$1109:$V$1112
Name HUILA: Listas!$T$606:$V$642
Name LA_GUAJIRA: Listas!$T$643:$V$657
Name LST_ACTIVIDAD_ECONOMICA: Listas!#REF!
Name LST_ASIGNATURA: Listas!$E$2:$E$4
Name LST_ESTADO_CONVENIO: Listas!$H$2:$H$12
Name LST_FACULTAD: Listas!$G$2:$G$18
Name LST_MUNICIPIO: Listas!$T$2:$T$1041
Name LST_SECTOR_ECONOMICO: Listas!$J$2:$J$5
Name LST_SEXO: Listas!$K$2:$K$5
Name LST_TEMATICAS: Listas!$D$2:$D$28
Name LST_TIPO_DE_ACTIVIDAD: Listas!$C$2:$C$5
Name LST_TIPO_DE_ACTOR: Listas!$A$2:$A$11
Name LST_TIPO_DE_PROYECTO: Listas!$B$2:$B$6
Name LST_TIPO_ID: Listas!$I$2:$I$7
Name MAGDALENA: Listas!$T$658:$V$687
Name META: Listas!$T$688:$V$716
Name NARIÑO: Listas!$T$717:$V$781
Name NORTE_DE_SANTANDER: Listas!$T$781:$V$820
Name PUTUMAYO: Listas!$T$1075:$V$1087
Name QUINDÍO: Listas!$T$821:$V$832
Name RISARALDA: Listas!$T$833:$V$846
Name SANTANDER: Listas!$T$847:$V$933
Name SUCRE: Listas!$T$934:$V$959
Name TIPOREL: Listas!$L$2:$L$4
Name TOLIMA: Listas!$T$960:$V$1006
Name VALLE_DEL_CAUCA: Listas!$T$1007:$V$1048
Name VAUPÉS: Listas!$T$1113:$V$1118
Name VICHADA: Listas!$T$1119:$V$1122

Sheet INICIO
B2: BASE DE DATOS HISTÓRICA DE PROYECTOS
B3: Hoja de inicio | Mapa de navegación y guía rápida de uso
B5: OBJETIVO DEL ARCHIVO
B6: Centralizar, organizar y dar seguimiento a la información histórica de proyectos, actores, entidades aliadas, indicadores, metas y avances de la facultad.
B8: MAPA DE NAVEGACIÓN
B9: Hoja / módulo | C9: Descripción | D9: Cuándo usarla | E9: Campo clave
B10: Actores | C10: Registra las personas vinculadas a los proyectos y sus datos de identificación, contacto, rol y relación académica. | D10: Agregar o consultar participantes, docentes, estudiantes u otros actores asociados a un proyecto. | E10: numero_documento
B11: Proyectos | C11: Consolida la información principal de cada proyecto: código, semestre, título, tipo, objetivos, temática, fechas, responsable y estado. | D11: Crear, revisar o actualizar la ficha general de cada proyecto. | E11: codigo_proyecto
B12: Entidades | C12: Directorio maestro de organizaciones externas, con NIT o código interno, sector, CIIU, contacto, ubicación y convenio. | D12: Registrar aliados antes de asociarlos a proyectos. | E12: codigo_entidad / NIT
B13: Proyecto_Socios | C13: Relaciona cada proyecto con sus entidades aliadas y define el tipo de vínculo o participación de cada socio. | D13: Vincular uno o varios socios a un proyecto específico. | E13: codigo_proyecto + codigo_entidad
B14: Metas_Indicador | C14: Define las metas asociadas a cada proyecto e indicador, incluyendo periodicidad, tipo de indicador y valor objetivo. | D14: Establecer la línea base y la meta contra la cual se medirá el avance. | E14: codigo_meta
B15: Seguimiento_Indicador | C15: Registra los avances de los indicadores por periodo y calcula el cumplimiento frente a la meta definida. | D15: Actualizar resultados, evidencias de avance y porcentaje de cumplimiento. | E15: codigo_meta + periodo
B16: Bateria_Indicadores | C16: Catálogo maestro de indicadores disponibles para seleccionar familias, subfamilias, descripciones y tipos. | D16: Consultar o ampliar el banco de indicadores disponibles para los proyectos. | E16: codigo_indicador
B17: Listas | C17: Tablas de referencia técnica para alimentar validaciones y listas desplegables del sistema | D17: Mantener opciones de selección como tipos, estados, sectores, municipios y periodicidades. | E17: categorías de validación
B18: TablasODS | C18: Catálogo de ODS, nombres y metas relacionadas para clasificar proyectos e indicadores según la Agenda 2030. | D18: Mapear proyectos e indicadores con Objetivos de Desarrollo Sostenible y metas ODS. | E18: ODS / meta ODS

Sheet Actores
A1: numero_documento | B1: tipo_documento | C1: semestre_periodo | D1: tipo_actor | E1: nombres_apellidos | F1: fecha_nacimiento | G1: sexo | H1: correo_electronico | I1: telefono | J1: direccion | K1: carrera_programa | L1: facultad | M1: asignatura | N1: codigo_proyecto | O1: titulo_proyecto | P1: informe_final(link) | Q1: observaciones
A2: 1013676963 | B2: CC | C2: 2019-10 | D2: Practicante | E2: MARÍA JOSE CASTILLO MORENO | F2: 35733 | G2: F | H2: maria_castillo@javeriana.edu.co | I2: 310/613-5065 | K2: Ingeniería de Sistemas | L2: Ingeniería | M2: PSU | N2: 1910NULOS-2410 | O2: =IFERROR(IF(Tbla_actores[[#This Row],[codigo_proyecto]]="","",_xlfn.XLOOKUP(Tbla_actores[[#This Row],[codigo_proyecto]],Proyectos!$A:$A,Proyectos!$C:$C)),"") -> NULOS
A3: 1032494985 | B3: CC | C3: 2019-10 | D3: Practicante | E3: MIGUEL ÁNGEL GUTIÉRREZ IBAGUE | F3: 35768 | G3: M | H3: miguel_gutierrez@javeriana.edu.co | I3: 310/810-8579 | K3: Ingeniería de Sistemas | L3: Ingeniería | M3: PSU | N3: 1910NULOS-2410 | O3: =IFERROR(IF(Tbla_actores[[#This Row],[codigo_proyecto]]="","",_xlfn.XLOOKUP(Tbla_actores[[#This Row],[codigo_proyecto]],Proyectos!$A:$A,Proyectos!$C:$C)),"") -> NULOS
A4: 1010228428 | B4: CC | C4: 2019-10 | D4: Practicante | E4: DANIELA LÓPEZ BARAHONA | F4: 35247 | G4: F | H4: lo-daniela@javeriana.edu.co | I4: 316/452-6691 | K4: Ingeniería de Sistemas | L4: Ingeniería | M4: PSU | N4: 1910NULOS-2410 | O4: =IFERROR(IF(Tbla_actores[[#This Row],[codigo_proyecto]]="","",_xlfn.XLOOKUP(Tbla_actores[[#This Row],[codigo_proyecto]],Proyectos!$A:$A,Proyectos!$C:$C)),"") -> NULOS
A5: 1032493211 | B5: CC | C5: 2019-10 | D5: Practicante | E5: DAVID ALEJANDRO MOLANO VÁSQUEZ | F5: 35682 | G5: M | H5: david-molano@javeriana.edu.co | I5: 304/587-1500 | K5: Ingeniería de Sistemas | L5: Ingeniería | M5: PSU | N5: 1910NULOS-2410 | O5: =IFERROR(IF(Tbla_actores[[#This Row],[codigo_proyecto]]="","",_xlfn.XLOOKUP(Tbla_actores[[#This Row],[codigo_proyecto]],Proyectos!$A:$A,Proyectos!$C:$C)),"") -> NULOS
A6: 1018502251 | B6: CC | C6: 2019-10 | D6: Practicante | E6: Murillo Castillo,Johan Sebastian | F6: 35799 | G6: M | H6: johanmurillo@javeriana.edu.co | I6: 305/791-8469 | K6: Ingeniería de Sistemas | L6: Ingeniería | M6: PSU | N6: 1910NULOS-2410 | O6: =IFERROR(IF(Tbla_actores[[#This Row],[codigo_proyecto]]="","",_xlfn.XLOOKUP(Tbla_actores[[#This Row],[codigo_proyecto]],Proyectos!$A:$A,Proyectos!$C:$C)),"") -> NULOS
A7: 1032477898 | B7: CC | C7: 2019-10 | D7: Practicante | E7: KANEKO BOJACA,RIE | F7: 35019 | G7: F | H7: rkaneko@javeriana.edu.co | I7: 321/356-0042 | K7: Ingeniería de Sistemas | L7: Ingeniería | M7: PSU | N7: 1910NULOS-2410 | O7: =IFERROR(IF(Tbla_actores[[#This Row],[codigo_proyecto]]="","",_xlfn.XLOOKUP(Tbla_actores[[#This Row],[codigo_proyecto]],Proyectos!$A:$A,Proyectos!$C:$C)),"") -> NULOS
A8: 1016103807 | B8: CC | C8: 2019-10 | D8: Practicante | E8: SANDOVAL ACOSTA,IVAN DARIO | F8: 35924 | G8: M | H8: sandoval.i@javeriana.edu.co | I8: 310/372-0631 | K8: Ingeniería de Sistemas | L8: Ingeniería | M8: PSU | N8: 1910NULOS-2410 | O8: =IFERROR(IF(Tbla_actores[[#This Row],[codigo_proyecto]]="","",_xlfn.XLOOKUP(Tbla_actores[[#This Row],[codigo_proyecto]],Proyectos!$A:$A,Proyectos!$C:$C)),"") -> NULOS
A9: 1014289963 | B9: CC | C9: 2019-10 | D9: Practicante | E9: MARIÑO GUERRA,ANDRES FELIPE | F9: 35621 | G9: M | H9: marinoandres@javeriana.edu.co | I9: 301/632-5339 | K9: Ingeniería de Sistemas | L9: Ingeniería | M9: PSU | N9: 1910NULOS-2410 | O9: =IFERROR(IF(Tbla_actores[[#This Row],[codigo_proyecto]]="","",_xlfn.XLOOKUP(Tbla_actores[[#This Row],[codigo_proyecto]],Proyectos!$A:$A,Proyectos!$C:$C)),"") -> NULOS
A10: 1013680915 | B10: CC | C10: 2019-10 | D10: Practicante | E10: Torres Rodríguez,Oscar Daniel | F10: 36042 | G10: M | H10: oscar_torres@javeriana.edu.co | I10: 320/553-6492 | K10: Ingeniería de Sistemas | L10: Ingeniería | M10: PSU | N10: 1910NULOS-2410 | O10: =IFERROR(IF(Tbla_actores[[#This Row],[codigo_proyecto]]="","",_xlfn.XLOOKUP(Tbla_actores[[#This Row],[codigo_proyecto]],Proyectos!$A:$A,Proyectos!$C:$C)),"") -> NULOS
A11: 1014285017 | B11: CC | C11: 2019-10 | D11: Practicante | E11: AMANDA CAROLINA SOTO VALENCIA | F11: 35448 | G11: F | H11: amandasoto@javeriana.edu.co | I11: 316/696-5901 | K11: Ingeniería de Sistemas | L11: Ingeniería | M11: PSU | N11: 1910NULOS-2410 | O11: =IFERROR(IF(Tbla_actores[[#This Row],[codigo_proyecto]]="","",_xlfn.XLOOKUP(Tbla_actores[[#This Row],[codigo_proyecto]],Proyectos!$A:$A,Proyectos!$C:$C)),"") -> NULOS
A12: 1018513462 | B12: CC | C12: 2019-10 | D12: Practicante | E12: JUAN SEBASTIÁN GONZÁLEZ MORENO | F12: 36431 | G12: M | H12: gonzalezju@javeriana.edu.co | I12: 747-3508 | K12: Ingeniería de Sistemas | L12: Ingeniería | M12: PSU | N12: 1910NULOS-2410 | O12: =IFERROR(IF(Tbla_actores[[#This Row],[codigo_proyecto]]="","",_xlfn.XLOOKUP(Tbla_actores[[#This Row],[codigo_proyecto]],Proyectos!$A:$A,Proyectos!$C:$C)),"") -> NULOS
A13: 1018497844 | B13: CC | C13: 2019-10 | D13: Practicante | E13: JUAN DAVID GAMA PEÑA | F13: 35705 | G13: M | H13: gamaj@javeriana.edu.co | I13: 312/330-2066 | K13: Ingeniería de Sistemas | L13: Ingeniería | M13: PSU | N13: 1910NULOS-2410 | O13: =IFERROR(IF(Tbla_actores[[#This Row],[codigo_proyecto]]="","",_xlfn.XLOOKUP(Tbla_actores[[#This Row],[codigo_proyecto]],Proyectos!$A:$A,Proyectos!$C:$C)),"") -> NULOS
... A453: 1010237594 | B453: CC | C453: 2019-30 | D453: Practicante | E453: RIVERA ARIZA,DANIEL FELIPE | F453: 35816 | G453: M | H453: daniel-rivera@javeriana.edu.co | I453: 322/390-3190 | K453: Ingeniería Civil | L453: Ingeniería | M453: PSU | N453: 1910NULOS-2410 | O453: =IFERROR(IF(Tbla_actores[[#This Row],[codigo_proyecto]]="","",_xlfn.XLOOKUP(Tbla_actores[[#This Row],[codigo_proyecto]],Proyectos!$A:$A,Proyectos!$C:$C)),"") -> NULOS
A454: 1026594289 | B454: CC | C454: 2020-10 | D454: Practicante | E454: Diego Mateus | F454: NO ENCONTRADO | G454: NO ENCONTRADO | H454: NO ENCONTRADO | I454: NO ENCONTRADO | K454: Ingeniería de Sistemas | L454: Ingeniería | M454: NO ENCONTRADO | N454: 1910NULOS-2410 | O454: =IFERROR(IF(Tbla_actores[[#This Row],[codigo_proyecto]]="","",_xlfn.XLOOKUP(Tbla_actores[[#This Row],[codigo_proyecto]],Proyectos!$A:$A,Proyectos!$C:$C)),"") -> NULOS
A455: 1020810281 | B455: CC | C455: 2020-10 | D455: Practicante | E455: ARCINIEGAS BASTIDAS,RODOLFO ALEJANDRO | F455: 34999 | G455: M | H455: rarciniegas@javeriana.edu.co | I455: 319/524-3098 | K455: Ingeniería de Sistemas | L455: Ingeniería | M455: PSU | N455: 1910NULOS-2410 | O455: =IFERROR(IF(Tbla_actores[[#This Row],[codigo_proyecto]]="","",_xlfn.XLOOKUP(Tbla_actores[[#This Row],[codigo_proyecto]],Proyectos!$A:$A,Proyectos!$C:$C)),"") -> NULOS
A456: 1072715070 | B456: CC | C456: 2020-10 | D456: Practicante | E456: HAMILTON SMITH SANTA CRUZ,DANIEL | F456: 35699 | G456: M | H456: d_hamiltonsmith@javeriana.edu.co | I456: 318/644-8414 | K456: Ingeniería de Sistemas | L456: Ingeniería | M456: PSU | N456: 1910NULOS-2410 | O456: =IFERROR(IF(Tbla_actores[[#This Row],[codigo_proyecto]]="","",_xlfn.XLOOKUP(Tbla_actores[[#This Row],[codigo_proyecto]],Proyectos!$A:$A,Proyectos!$C:$C)),"") -> NULOS
A457: 1116448237 | B457: CC | C457: 2020-10 | D457: Practicante | E457: CHAVEZ ALCALDE,SANDRA ISABEL | F457: 35960 | G457: F | H457: sandra.chavez@javeriana.edu.co | I457: 310/837-8039 | K457: Ingeniería de Sistemas | L457: Ingeniería | M457: PSU | N457: 1910NULOS-2410 | O457: =IFERROR(IF(Tbla_actores[[#This Row],[codigo_proyecto]]="","",_xlfn.XLOOKUP(Tbla_actores[[#This Row],[codigo_proyecto]],Proyectos!$A:$A,Proyectos!$C:$C)),"") -> NULOS
A458: 1018484838 | B458: CC | C458: 2020-10 | D458: Practicante | E458: Juan Linares | F458: 35170 | G458: M | H458: linares.juan@javeriana.edu.co | I458: 300/620-9099 | K458: Ingeniería de Sistemas | L458: Ingeniería | M458: PSU | N458: 1910NULOS-2410 | O458: =IFERROR(IF(Tbla_actores[[#This Row],[codigo_proyecto]]="","",_xlfn.XLOOKUP(Tbla_actores[[#This Row],[codigo_proyecto]],Proyectos!$A:$A,Proyectos!$C:$C)),"") -> NULOS
A459: 1019142697 | B459: CC | C459: 2020-10 | D459: Practicante | E459: William Baquero | F459: 35914 | G459: M | H459: w.baquero@javeriana.edu.co | I459: 320/489-7354 | K459: Ingeniería de Sistemas | L459: Ingeniería | M459: PSU | N459: 1910NULOS-2410 | O459: =IFERROR(IF(Tbla_actores[[#This Row],[codigo_proyecto]]="","",_xlfn.XLOOKUP(Tbla_actores[[#This Row],[codigo_proyecto]],Proyectos!$A:$A,Proyectos!$C:$C)),"") -> NULOS
A460: 1030682895 | B460: CC | C460: 2020-10 | D460: Practicante | E460: Juan Castañeda | F460: 35733 | G460: M | H460: castaneda_j@javeriana.edu.co | I460: 301/675-6383 | K460: Ingeniería de Sistemas | L460: Ingeniería | M460: PSU | N460: 1910NULOS-2410 | O460: =IFERROR(IF(Tbla_actores[[#This Row],[codigo_proyecto]]="","",_xlfn.XLOOKUP(Tbla_actores[[#This Row],[codigo_proyecto]],Proyectos!$A:$A,Proyectos!$C:$C)),"") -> NULOS
A461: 1098815582 | B461: CC | C461: 2020-10 | D461: Practicante | E461: Mara Garcés | F461: 36181 | G461: F | H461: maria_garces@javeriana.edu.co | I461: 317/428-4320 | K461: Ingeniería de Sistemas | L461: Ingeniería | M461: PSU | N461: 1910NULOS-2410 | O461: =IFERROR(IF(Tbla_actores[[#This Row],[codigo_proyecto]]="","",_xlfn.XLOOKUP(Tbla_actores[[#This Row],[codigo_proyecto]],Proyectos!$A:$A,Proyectos!$C:$C)),"") -> NULOS
A462: 1032498978 | B462: CC | C462: 2020-10 | D462: Practicante | E462: Juan Leon | F462: 35989 | G462: M | H462: juleon@javeriana.edu.co | I462: 320/409-4111 | K462: Ingeniería de Sistemas | L462: Ingeniería | M462: PSU | N462: 1910NULOS-2410 | O462: =IFERROR(IF(Tbla_actores[[#This Row],[codigo_proyecto]]="","",_xlfn.XLOOKUP(Tbla_actores[[#This Row],[codigo_proyecto]],Proyectos!$A:$A,Proyectos!$C:$C)),"") -> NULOS
A463: 1001171919 | B463: CC | C463: 2020-10 | D463: Practicante | E463: Briam Agudelo | F463: 35986 | G463: M | H463: briam-agudelo@javeriana.edu.co | I463: 365-0289 | K463: Ingeniería de Sistemas | L463: Ingeniería | M463: PSU | N463: 1910NULOS-2410 | O463: =IFERROR(IF(Tbla_actores[[#This Row],[codigo_proyecto]]="","",_xlfn.XLOOKUP(Tbla_actores[[#This Row],[codigo_proyecto]],Proyectos!$A:$A,Proyectos!$C:$C)),"") -> NULOS
A464: 1033815546 | B464: CC | C464: 2020-10 | D464: Practicante | E464: Diego Barajas | F464: 36271 | G464: M | H464: barajas-d@javeriana.edu.co | I464: 320/288-3351 | K464: Ingeniería de Sistemas | L464: Ingeniería | M464: PSU | N464: 1910NULOS-2410 | O464: =IFERROR(IF(Tbla_actores[[#This Row],[codigo_proyecto]]="","",_xlfn.XLOOKUP(Tbla_actores[[#This Row],[codigo_proyecto]],Proyectos!$A:$A,Proyectos!$C:$C)),"") -> NULOS
A465: 1010065358 | B465: CC | C465: 2020-10 | D465: Practicante | E465: Sergio Posada | F465: 36312 | G465: M | H465: sergio_posada@javeriana.edu.co | I465: 320/941-0506 | K465: Ingeniería de Sistemas | L465: Ingeniería | M465: PSU | N465: 1910NULOS-2410 | O465: =IFERROR(IF(Tbla_actores[[#This Row],[codigo_proyecto]]="","",_xlfn.XLOOKUP(Tbla_actores[[#This Row],[codigo_proyecto]],Proyectos!$A:$A,Proyectos!$C:$C)),"") -> NULOS
A466: 1019147850 | B466: CC | C466: 2020-10 | D466: Practicante | E466: CERVANTES PINEDA,NICOLAS ANDRES | F466: 36256 | G466: M | H466: nicolas.cervantes@javeriana.edu.co | I466: 314/298-9463 | K466: Ingeniería de Sistemas | L466: Ingeniería | M466: PSU | N466: 1910NULOS-2410 | O466: =IFERROR(IF(Tbla_actores[[#This Row],[codigo_proyecto]]="","",_xlfn.XLOOKUP(Tbla_actores[[#This Row],[codigo_proyecto]],Proyectos!$A:$A,Proyectos!$C:$C)),"") -> NULOS
... A469: 1023970683 | B469: CC | C469: 2020-10 | D469: Practicante | E469: CRUZ LOPEZ,BRANDONN ANDRES | F469: 36006 | G469: M | H469: brandonn_cruz@javeriana.edu.co | I469: 314/385-7656 | K469: Ingeniería de Sistemas | L469: Ingeniería | M469: PSU | N469: 1910NULOS-2410 | O469: =IFERROR(IF(Tbla_actores[[#This Row],[codigo_proyecto]]="","",_xlfn.XLOOKUP(Tbla_actores[[#This Row],[codigo_proyecto]],Proyectos!$A:$A,Proyectos!$C:$C)),"") -> NULOS
A470: 1006956287 | B470: CC | C470: 2020-10 | D470: Practicante | E470: Kevin Pelaez | F470: NO ENCONTRADO | G470: NO ENCONTRADO | H470: NO ENCONTRADO | I470: NO ENCONTRADO | K470: Ingeniería de Sistemas | L470: Ingeniería | M470: NO ENCONTRADO | N470: 1910NULOS-2410 | O470: =IFERROR(IF(Tbla_actores[[#This Row],[codigo_proyecto]]="","",_xlfn.XLOOKUP(Tbla_actores[[#This Row],[codigo_proyecto]],Proyectos!$A:$A,Proyectos!$C:$C)),"") -> NULOS
A471: 1013684063 | B471: CC | C471: 2020-10 | D471: Practicante | E471: Jonathan Molina | F471: 36055 | G471: M | H471: molina_jonathan@javeriana.edu.co | I471: 319/257-4131 | K471: Ingeniería de Sistemas | L471: Ingeniería | M471: PSU | N471: 1910NULOS-2410 | O471: =IFERROR(IF(Tbla_actores[[#This Row],[codigo_proyecto]]="","",_xlfn.XLOOKUP(Tbla_actores[[#This Row],[codigo_proyecto]],Proyectos!$A:$A,Proyectos!$C:$C)),"") -> NULOS
A472: 1000061573 | B472: CC | C472: 2020-10 | D472: Practicante | E472: Karol Yate | F472: 36776 | G472: F | H472: yatek@javeriana.edu.co | I472: 301/366-0141 | K472: Ingeniería de Sistemas | L472: Ingeniería | M472: PSU | N472: 1910NULOS-2410 | O472: =IFERROR(IF(Tbla_actores[[#This Row],[codigo_proyecto]]="","",_xlfn.XLOOKUP(Tbla_actores[[#This Row],[codigo_proyecto]],Proyectos!$A:$A,Proyectos!$C:$C)),"") -> NULOS
A473: 1018482319 | B473: CC | C473: 2020-10 | D473: Practicante | E473: MAYORGA CORTES,ALEJANDRO | F473: 35086 | G473: M | H473: alejandromayorga@javeriana.edu.co | I473: 321/336-6403 | K473: Ingeniería Electrónica | L473: Ingeniería | M473: PSU | N473: 1910NULOS-2410 | O473: =IFERROR(IF(Tbla_actores[[#This Row],[codigo_proyecto]]="","",_xlfn.XLOOKUP(Tbla_actores[[#This Row],[codigo_proyecto]],Proyectos!$A:$A,Proyectos!$C:$C)),"") -> NULOS
A474: 1020832382 | B474: CC | C474: 2020-10 | D474: Practicante | E474: GARCIA MORALES,BRAYAN RICARDO | F474: 35882 | G474: M | H474: brayan-garcia@javeriana.edu.co | I474: 305/705-3548 | K474: Ingeniería de Sistemas | L474: Ingeniería | M474: PSU | N474: 1910NULOS-2410 | O474: =IFERROR(IF(Tbla_actores[[#This Row],[codigo_proyecto]]="","",_xlfn.XLOOKUP(Tbla_actores[[#This Row],[codigo_proyecto]],Proyectos!$A:$A,Proyectos!$C:$C)),"") -> NULOS
A475: 1098808861 | B475: CC | C475: 2020-10 | D475: Practicante | E475: VERA QUINTERO,LEYDER FABIAN | F475: 35968 | G475: M | H475: vera_l@javeriana.edu.co | I475: 318/618-1915 | K475: Ingeniería de Sistemas | L475: Ingeniería | M475: PSU | N475: 1910NULOS-2410 | O475: =IFERROR(IF(Tbla_actores[[#This Row],[codigo_proyecto]]="","",_xlfn.XLOOKUP(Tbla_actores[[#This Row],[codigo_proyecto]],Proyectos!$A:$A,Proyectos!$C:$C)),"") -> NULOS
A476: 1020811084 | B476: CC | C476: 2020-10 | D476: Practicante | E476: FERNANDEZ ULLOA,DANIEL | F476: 35030 | G476: M | H476: fernandezdaniel@javeriana.edu.co | I476: 310/310-6722 | K476: Ingeniería de Sistemas | L476: Ingeniería | M476: PSU | N476: 1910NULOS-2410 | O476: =IFERROR(IF(Tbla_actores[[#This Row],[codigo_proyecto]]="","",_xlfn.XLOOKUP(Tbla_actores[[#This Row],[codigo_proyecto]],Proyectos!$A:$A,Proyectos!$C:$C)),"") -> NULOS
A477: 1018510763 | B477: CC | C477: 2020-10 | D477: Practicante | E477: PULIDO AVILA,PABLO ALEJANDRO | F477: 36284 | G477: M | H477: pablo.pulido@javeriana.edu.co | I477: 316/690-5604 | K477: Ingeniería de Sistemas | L477: Ingeniería | M477: PSU | N477: 1910NULOS-2410 | O477: =IFERROR(IF(Tbla_actores[[#This Row],[codigo_proyecto]]="","",_xlfn.XLOOKUP(Tbla_actores[[#This Row],[codigo_proyecto]],Proyectos!$A:$A,Proyectos!$C:$C)),"") -> NULOS
A478: 1019143905 | B478: CC | C478: 2020-10 | D478: Practicante | E478: VILLATE OBANDO,NATALIA | F478: 36073 | G478: F | H478: n-villate@javeriana.edu.co | I478: 315/348-8503 | K478: Ingeniería de Sistemas | L478: Ingeniería | M478: PSU | N478: 1910NULOS-2410 | O478: =IFERROR(IF(Tbla_actores[[#This Row],[codigo_proyecto]]="","",_xlfn.XLOOKUP(Tbla_actores[[#This Row],[codigo_proyecto]],Proyectos!$A:$A,Proyectos!$C:$C)),"") -> NULOS
A479: 1019142423 | B479: CC | C479: 2020-10 | D479: Practicante | E479: HARRY ANDRES AVILA ECHEVERRIA | F479: 36032 | G479: M | H479: harryavila@javeriana.edu.co | I479: 321/456-8565 | K479: Ingeniería Industrial | L479: Ingeniería | M479: CDIO-3 | N479: 1910NULOS-2410 | O479: =IFERROR(IF(Tbla_actores[[#This Row],[codigo_proyecto]]="","",_xlfn.XLOOKUP(Tbla_actores[[#This Row],[codigo_proyecto]],Proyectos!$A:$A,Proyectos!$C:$C)),"") -> NULOS
A480: 1023082150 | B480: CC | C480: 2020-10 | D480: Practicante | E480: MARIA CAMILA CAÑON VARGAS | F480: 36043 | G480: F | H480: canonmaria@javeriana.edu.co | I480: 320/856-7504 | K480: Ingeniería Industrial | L480: Ingeniería | M480: CDIO-3 | N480: 1910NULOS-2410 | O480: =IFERROR(IF(Tbla_actores[[#This Row],[codigo_proyecto]]="","",_xlfn.XLOOKUP(Tbla_actores[[#This Row],[codigo_proyecto]],Proyectos!$A:$A,Proyectos!$C:$C)),"") -> NULOS
A481: 1072714201 | B481: CC | C481: 2020-10 | D481: Practicante | E481: JORGE ALBERTO GÓMEZ VIGOYA | F481: 35562 | G481: M | H481: jo.gomez@javeriana.edu.co | I481: 885-9323 | K481: Ingeniería Industrial | L481: Ingeniería | M481: CDIO-3 | N481: 1910NULOS-2410 | O481: =IFERROR(IF(Tbla_actores[[#This Row],[codigo_proyecto]]="","",_xlfn.XLOOKUP(Tbla_actores[[#This Row],[codigo_proyecto]],Proyectos!$A:$A,Proyectos!$C:$C)),"") -> NULOS
A482: 1032490379 | B482: CC | C482: 2020-10 | D482: Practicante | E482: CAMARGO LOPEZ,DANIEL FELIPE | F482: 35548 | G482: M | H482: camargo_d@javeriana.edu.co | I482: 301/492-4437 | K482: Ingeniería Industrial | L482: Ingeniería | M482: CDIO-3 | N482: 1910NULOS-2410 | O482: =IFERROR(IF(Tbla_actores[[#This Row],[codigo_proyecto]]="","",_xlfn.XLOOKUP(Tbla_actores[[#This Row],[codigo_proyecto]],Proyectos!$A:$A,Proyectos!$C:$C)),"") -> NULOS
... A830: 1026595836 | B830: CC | C830: 2021-10 | D830: Practicante | E830: JUAN SEBASTIAN ANGARITA TORRES | F830: 36091 | G830: M | H830: angaritat.js@javeriana.edu.co | I830: 300/211-2575 | K830: Ingeniería de Sistemas | L830: Ingeniería | M830: PSU | N830: 1910NULOS-2410 | O830: =IFERROR(IF(Tbla_actores[[#This Row],[codigo_proyecto]]="","",_xlfn.XLOOKUP(Tbla_actores[[#This Row],[codigo_proyecto]],Proyectos!$A:$A,Proyectos!$C:$C)),"") -> NULOS
A831: 1000764044 | B831: CC | C831: 2021-10 | D831: Practicante | E831: JORGE RODRIGO SALGADO TELLO | F831: NO ENCONTRADO | G831: NO ENCONTRADO | H831: NO ENCONTRADO | I831: NO ENCONTRADO | K831: Ingeniería de Sistemas | L831: Ingeniería | M831: N/A | N831: 1910NULOS-2410 | O831: =IFERROR(IF(Tbla_actores[[#This Row],[codigo_proyecto]]="","",_xlfn.XLOOKUP(Tbla_actores[[#This Row],[codigo_proyecto]],Proyectos!$A:$A,Proyectos!$C:$C)),"") -> NULOS
A832: 1000832289 | B832: CC | C832: 2021-10 | D832: Practicante | E832: MARIA ALEJANDRA SANDOVAL LOPEZ | F832: 36560 | G832: F | H832: sandovall_maria@javeriana.edu.co | I832: 316/867-0976 | K832: Ingeniería de Sistemas | L832: Ingeniería | M832: PSU | N832: 1910NULOS-2410 | O832: =IFERROR(IF(Tbla_actores[[#This Row],[codigo_proyecto]]="","",_xlfn.XLOOKUP(Tbla_actores[[#This Row],[codigo_proyecto]],Proyectos!$A:$A,Proyectos!$C:$C)),"") -> NULOS
A833: 1127342619 | B833: CC | C833: 2021-10 | D833: Practicante | E833: PEDRO HUMBERTO GUERRERO INFANTE | F833: 35888 | G833: M | H833: guerrero-pedro@javeriana.edu.co | I833: 312/414-2683 | K833: Ingeniería de Sistemas | L833: Ingeniería | M833: PSU | N833: 1910NULOS-2410 | O833: =IFERROR(IF(Tbla_actores[[#This Row],[codigo_proyecto]]="","",_xlfn.XLOOKUP(Tbla_actores[[#This Row],[codigo_proyecto]],Proyectos!$A:$A,Proyectos!$C:$C)),"") -> NULOS
A834: 1026302972 | B834: CC | C834: 2021-10 | D834: Practicante | E834: JUAN SEBASTIAN OSORIO GARCIA | F834: 36055 | G834: M | H834: osorio_j@javeriana.edu.co | I834: 320/318-6407 | K834: Ingeniería de Sistemas | L834: Ingeniería | M834: PSU | N834: 1910NULOS-2410 | O834: =IFERROR(IF(Tbla_actores[[#This Row],[codigo_proyecto]]="","",_xlfn.XLOOKUP(Tbla_actores[[#This Row],[codigo_proyecto]],Proyectos!$A:$A,Proyectos!$C:$C)),"") -> NULOS
A835: 1136888831 | B835: CC | C835: 2021-10 | D835: Practicante | E835: ABEL SANTIAGO CORTÉS | F835: 35840 | G835: M | H835: abel.cortes@javeriana.edu.co | I835: 317/400-6489 | K835: Ingeniería de Sistemas | L835: Ingeniería | M835: PSU | N835: 1910NULOS-2410 | O835: =IFERROR(IF(Tbla_actores[[#This Row],[codigo_proyecto]]="","",_xlfn.XLOOKUP(Tbla_actores[[#This Row],[codigo_proyecto]],Proyectos!$A:$A,Proyectos!$C:$C)),"") -> NULOS
A836: 1016105069 | B836: CC | C836: 2021-10 | D836: Practicante | E836: DIEGO MAURICIO BULLA NUÑEZ | F836: 36036 | G836: M | H836: diegobulla@javeriana.edu.co | I836: 712-1644 | K836: Ingeniería de Sistemas | L836: Ingeniería | M836: PSU | N836: 1910NULOS-2410 | O836: =IFERROR(IF(Tbla_actores[[#This Row],[codigo_proyecto]]="","",_xlfn.XLOOKUP(Tbla_actores[[#This Row],[codigo_proyecto]],Proyectos!$A:$A,Proyectos!$C:$C)),"") -> NULOS
A837: 1019140880 | B837: CC | C837: 2021-10 | D837: Practicante | E837: GABRIEL GOMEZ CORREDOR | F837: 35913 | G837: M | H837: gomezga@javeriana.edu.co | I837: 318/802-9323 | K837: Ingeniería de Sistemas | L837: Ingeniería | M837: PSU | N837: 1910NULOS-2410 | O837: =IFERROR(IF(Tbla_actores[[#This Row],[codigo_proyecto]]="","",_xlfn.XLOOKUP(Tbla_actores[[#This Row],[codigo_proyecto]],Proyectos!$A:$A,Proyectos!$C:$C)),"") -> NULOS
A838: 1000576456 | B838: CC | C838: 2021-10 | D838: Practicante | E838: GONZALEZ SOLANO,ERIKA ALEJANDRA | F838: 36601 | G838: F | H838: gonzalez_erika@javeriana.edu.co | I838: 320/806-2234 | K838: Ingeniería de Sistemas | L838: Ingeniería | M838: PSU | N838: 1910NULOS-2410 | O838: =IFERROR(IF(Tbla_actores[[#This Row],[codigo_proyecto]]="","",_xlfn.XLOOKUP(Tbla_actores[[#This Row],[codigo_proyecto]],Proyectos!$A:$A,Proyectos!$C:$C)),"") -> NULOS
A839: 1010123696 | B839: CC | C839: 2021-10 | D839: Practicante | E839: LONDOÑO LONDOÑO,LEONEL STEVEN | F839: 36577 | G839: M | H839: leonel-londono@javeriana.edu.co | I839: 314/332-0740 | K839: Ingeniería de Sistemas | L839: Ingeniería | M839: PSU | N839: 1910NULOS-2410 | O839: =IFERROR(IF(Tbla_actores[[#This Row],[codigo_proyecto]]="","",_xlfn.XLOOKUP(Tbla_actores[[#This Row],[codigo_proyecto]],Proyectos!$A:$A,Proyectos!$C:$C)),"") -> NULOS
A840: 1020828518 | B840: CC | C840: 2021-10 | D840: Practicante | E840: CHAFLOQUE MESIA,JUAN CAMILO | F840: 35699 | G840: M | H840: juanchafloque@javeriana.edu.co | I840: 301/658-1019 | K840: Ingeniería de Sistemas | L840: Ingeniería | M840: PSU | N840: 1910NULOS-2410 | O840: =IFERROR(IF(Tbla_actores[[#This Row],[codigo_proyecto]]="","",_xlfn.XLOOKUP(Tbla_actores[[#This Row],[codigo_proyecto]],Proyectos!$A:$A,Proyectos!$C:$C)),"") -> NULOS
A841: 1233908628 | B841: CC | C841: 2021-10 | D841: Practicante | E841: JIMENEZ JIMENEZ,LAURA MARIANA | F841: 36349 | G841: F | H841: la.jimenez@javeriana.edu.co | I841: 310/810-5207 | K841: Ingeniería de Sistemas | L841: Ingeniería | M841: PSU | N841: 1910NULOS-2410 | O841: =IFERROR(IF(Tbla_actores[[#This Row],[codigo_proyecto]]="","",_xlfn.XLOOKUP(Tbla_actores[[#This Row],[codigo_proyecto]],Proyectos!$A:$A,Proyectos!$C:$C)),"") -> NULOS
A842: 1007167437 | B842: CC | C842: 2021-10 | D842: Practicante | E842: SANTIAGO ANDRES CAROPRESE HIDALGO | F842: 36550 | G842: M | H842: scaropresse@javeriana.edu.co | I842: 320/838-0231 | K842: Ingeniería de Sistemas | L842: Ingeniería | M842: PSU | N842: 1910NULOS-2410 | O842: =IFERROR(IF(Tbla_actores[[#This Row],[codigo_proyecto]]="","",_xlfn.XLOOKUP(Tbla_actores[[#This Row],[codigo_proyecto]],Proyectos!$A:$A,Proyectos!$C:$C)),"") -> NULOS
A843: 1019144457 | B843: CC | C843: 2021-10 | D843: Practicante | E843: ROA DUEÑAS,SANTIAGO | F843: 36108 | G843: M | H843: santiago.roa@javeriana.edu.co | I843: 317/667-2341 | K843: Ingeniería de Sistemas | L843: Ingeniería | M843: PSU | N843: 1910NULOS-2410 | O843: =IFERROR(IF(Tbla_actores[[#This Row],[codigo_proyecto]]="","",_xlfn.XLOOKUP(Tbla_actores[[#This Row],[codigo_proyecto]],Proyectos!$A:$A,Proyectos!$C:$C)),"") -> NULOS
... A964: 1030682786 | B964: CC | C964: 2021-10 | D964: Practicante | E964: Luisa Fernanda Rojas | F964: 35767 | G964: F | H964: luisa_rojas@javeriana.edu.co | I964: 305/791-1959 | K964: Ingeniería Civil | L964: Ingeniería | M964: PSU | N964: 1910NULOS-2410 | O964: =IFERROR(IF(Tbla_actores[[#This Row],[codigo_proyecto]]="","",_xlfn.XLOOKUP(Tbla_actores[[#This Row],[codigo_proyecto]],Proyectos!$A:$A,Proyectos!$C:$C)),"") -> NULOS
A965: NO ENCONTRADO | B965: CC | C965: 2021-10 | D965: Practicante | E965: Grupo con solo dos estudiantes | F965: NO ENCONTRADO | G965: NO ENCONTRADO | H965: NO ENCONTRADO | I965: NO ENCONTRADO | K965: Ingeniería Civil | L965: Ingeniería | M965: N/A | N965: 1910NULOS-2410 | O965: =IFERROR(IF(Tbla_actores[[#This Row],[codigo_proyecto]]="","",_xlfn.XLOOKUP(Tbla_actores[[#This Row],[codigo_proyecto]],Proyectos!$A:$A,Proyectos!$C:$C)),"") -> NULOS
A966: 1007435569 | B966: CC | C966: 2021-10 | D966: Practicante | E966: William Camilo Pérez | F966: 36688 | G966: M | H966: perez.william@javeriana.edu.co | I966: 351/777-9660 | K966: Ingeniería Civil | L966: Ingeniería | M966: PSU | N966: 1910NULOS-2410 | O966: =IFERROR(IF(Tbla_actores[[#This Row],[codigo_proyecto]]="","",_xlfn.XLOOKUP(Tbla_actores[[#This Row],[codigo_proyecto]],Proyectos!$A:$A,Proyectos!$C:$C)),"") -> NULOS
A967: 1193524569 | B967: CC | C967: 2021-10 | D967: Practicante | E967: Michael Leandro Luna Riscanevo | F967: 36748 | G967: M | H967: michael_luna@javeriana.edu.co | I967: 300/438-1593 | K967: Ingeniería Civil | L967: Ingeniería | M967: PSU | N967: 1910NULOS-2410 | O967: =IFERROR(IF(Tbla_actores[[#This Row],[codigo_proyecto]]="","",_xlfn.XLOOKUP(Tbla_actores[[#This Row],[codigo_proyecto]],Proyectos!$A:$A,Proyectos!$C:$C)),"") -> NULOS
A968: 1015473347 | B968: CC | C968: 2021-10 | D968: Practicante | E968: Héctor Abel Fonseca | F968: 35832 | G968: M | H968: hectorfonseca@javeriana.edu.co | I968: 311/257-5670 | K968: Ingeniería Civil | L968: Ingeniería | M968: PSU | N968: 1910NULOS-2410 | O968: =IFERROR(IF(Tbla_actores[[#This Row],[codigo_proyecto]]="","",_xlfn.XLOOKUP(Tbla_actores[[#This Row],[codigo_proyecto]],Proyectos!$A:$A,Proyectos!$C:$C)),"") -> NULOS
A969: 1007391701 | B969: CC | C969: 2021-10 | D969: Practicante | E969: Jose Fernando Ropero Carreño | F969: 36590 | G969: M | H969: ropero-j@javeriana.edu.co | I969: 310/288-9120 | K969: Ingeniería Civil | L969: Ingeniería | M969: PSU | N969: 1910NULOS-2410 | O969: =IFERROR(IF(Tbla_actores[[#This Row],[codigo_proyecto]]="","",_xlfn.XLOOKUP(Tbla_actores[[#This Row],[codigo_proyecto]],Proyectos!$A:$A,Proyectos!$C:$C)),"") -> NULOS
A970: 1032508387 | B970: CC | C970: 2021-10 | D970: Practicante | E970: Luis Fernando Mosquera | F970: 36502 | G970: M | H970: luismosquera@javeriana.edu.co | I970: 310/483-9700 | K970: Ingeniería Civil | L970: Ingeniería | M970: PSU | N970: 1910NULOS-2410 | O970: =IFERROR(IF(Tbla_actores[[#This Row],[codigo_proyecto]]="","",_xlfn.XLOOKUP(Tbla_actores[[#This Row],[codigo_proyecto]],Proyectos!$A:$A,Proyectos!$C:$C)),"") -> NULOS
A971: 1026305494 | B971: CC | C971: 2021-10 | D971: Practicante | E971: Nicolas illitch Martinez | F971: 36278 | G971: M | H971: ma-nicolas@javeriana.edu.co | I971: 664-4018 | K971: Ingeniería Civil | L971: Ingeniería | M971: PSU | N971: 1910NULOS-2410 | O971: =IFERROR(IF(Tbla_actores[[#This Row],[codigo_proyecto]]="","",_xlfn.XLOOKUP(Tbla_actores[[#This Row],[codigo_proyecto]],Proyectos!$A:$A,Proyectos!$C:$C)),"") -> NULOS
A972: 1073246417 | B972: CC | C972: 2021-10 | D972: Practicante | E972: Juan Diego Amaya Sáenz | F972: 35292 | G972: M | H972: juan_amaya@javeriana.edu.co | I972: 893-1968 | K972: Ingeniería Civil | L972: Ingeniería | M972: PSU | N972: 1910NULOS-2410 | O972: =IFERROR(IF(Tbla_actores[[#This Row],[codigo_proyecto]]="","",_xlfn.XLOOKUP(Tbla_actores[[#This Row],[codigo_proyecto]],Proyectos!$A:$A,Proyectos!$C:$C)),"") -> NULOS
A973: 1019128601 | B973: CC | C973: 2021-10 | D973: Practicante | E973: Daniela Bautista Collante | F973: 35495 | G973: F | H973: bautistadaniela@javeriana.edu.co | I973: 310/203-9979 | K973: Ingeniería Civil | L973: Ingeniería | M973: PSU | N973: 1910NULOS-2410 | O973: =IFERROR(IF(Tbla_actores[[#This Row],[codigo_proyecto]]="","",_xlfn.XLOOKUP(Tbla_actores[[#This Row],[codigo_proyecto]],Proyectos!$A:$A,Proyectos!$C:$C)),"") -> NULOS
A974: 1032499802 | B974: CC | C974: 2021-10 | D974: Practicante | E974: Valentina Romero Gonzalez | F974: 36026 | G974: F | H974: romerovalentina@javeriana.edu.co | I974: 321/370-2530 | K974: Ingeniería Civil | L974: Ingeniería | M974: PSU | N974: 1910NULOS-2410 | O974: =IFERROR(IF(Tbla_actores[[#This Row],[codigo_proyecto]]="","",_xlfn.XLOOKUP(Tbla_actores[[#This Row],[codigo_proyecto]],Proyectos!$A:$A,Proyectos!$C:$C)),"") -> NULOS
A975: 1082924067 | B975: CC | C975: 2021-10 | D975: Practicante | E975: Maria Camila Vargas Cabas | F975: 36617 | G975: F | H975: vargasma@javeriana.edu.co | I975: 676-9136 | K975: Ingeniería Civil | L975: Ingeniería | M975: PSU | N975: 1910NULOS-2410 | O975: =IFERROR(IF(Tbla_actores[[#This Row],[codigo_proyecto]]="","",_xlfn.XLOOKUP(Tbla_actores[[#This Row],[codigo_proyecto]],Proyectos!$A:$A,Proyectos!$C:$C)),"") -> NULOS
A976: 1019135505 | B976: CC | C976: 2021-10 | D976: Practicante | E976: Nathalia del Pilar Díaz | F976: 35769 | G976: F | H976: diaz.nathalia@javeriana.edu.co | I976: 311/526-3470 | K976: Ingeniería Civil | L976: Ingeniería | M976: PSU | N976: 1910NULOS-2410 | O976: =IFERROR(IF(Tbla_actores[[#This Row],[codigo_proyecto]]="","",_xlfn.XLOOKUP(Tbla_actores[[#This Row],[codigo_proyecto]],Proyectos!$A:$A,Proyectos!$C:$C)),"") -> NULOS
A977: 1233892522 | B977: CC | C977: 2021-10 | D977: Practicante | E977: Carlos Eduardo Castillo | F977: 35667 | G977: M | H977: carlos_castillo@javeriana.edu.co | I977: 318/400-3260 | K977: Ingeniería Civil | L977: Ingeniería | M977: PSU | N977: 1910NULOS-2410 | O977: =IFERROR(IF(Tbla_actores[[#This Row],[codigo_proyecto]]="","",_xlfn.XLOOKUP(Tbla_actores[[#This Row],[codigo_proyecto]],Proyectos!$A:$A,Proyectos!$C:$C)),"") -> NULOS
... A1102: 1019124610 | B1102: CC | C1102: 2021-30 | D1102: Practicante | E1102: ALEJANDRO CASTRO MARTINEZ | F1102: 35163 | G1102: M | H1102: alejandrocastro@javeriana.edu.co | I1102: 310/249-8720 | K1102: Ingeniería de Sistemas | L1102: Ingeniería | M1102: PSU | N1102: 1910NULOS-2410 | O1102: =IFERROR(IF(Tbla_actores[[#This Row],[codigo_proyecto]]="","",_xlfn.XLOOKUP(Tbla_actores[[#This Row],[codigo_proyecto]],Proyectos!$A:$A,Proyectos!$C:$C)),"") -> NULOS
A1103: 746497 | B1103: CC | C1103: 2021-30 | D1103: Practicante | E1103: CRISTIAN JAVIER DA CAMARA SOUSA | F1103: NO ENCONTRADO | G1103: NO ENCONTRADO | H1103: NO ENCONTRADO | I1103: NO ENCONTRADO | K1103: Ingeniería de Sistemas | L1103: Ingeniería | M1103: N/A | N1103: 1910NULOS-2410 | O1103: =IFERROR(IF(Tbla_actores[[#This Row],[codigo_proyecto]]="","",_xlfn.XLOOKUP(Tbla_actores[[#This Row],[codigo_proyecto]],Proyectos!$A:$A,Proyectos!$C:$C)),"") -> NULOS
A1104: 1004910794 | B1104: CC | C1104: 2021-30 | D1104: Practicante | E1104: ABRAHAM IGNACIO AYALA ACUÑA | F1104: 37043 | G1104: M | H1104: ayala_abrahan@javeriana.edu.co | I1104: 310/314-8347 | K1104: Ingeniería de Sistemas | L1104: Ingeniería | M1104: PSU | N1104: 1910NULOS-2410 | O1104: =IFERROR(IF(Tbla_actores[[#This Row],[codigo_proyecto]]="","",_xlfn.XLOOKUP(Tbla_actores[[#This Row],[codigo_proyecto]],Proyectos!$A:$A,Proyectos!$C:$C)),"") -> NULOS
A1105: 1016086751 | B1105: CC | C1105: 2021-30 | D1105: Practicante | E1105: GUERRERO LEON,LIDA KATHERINE | F1105: 35243 | G1105: F | H1105: lida.guerrero@javeriana.edu.co | I1105: 317/647-4579 | K1105: Ingeniería de Sistemas | L1105: Ingeniería | M1105: PSU | N1105: 1910NULOS-2410 | O1105: =IFERROR(IF(Tbla_actores[[#This Row],[codigo_proyecto]]="","",_xlfn.XLOOKUP(Tbla_actores[[#This Row],[codigo_proyecto]],Proyectos!$A:$A,Proyectos!$C:$C)),"") -> NULOS
A1106: 1098721983 | B1106: CC | C1106: 2021-30 | D1106: Practicante | E1106: DUARTE LOPEZ,JUAN MANUEL | F1106: 33742 | G1106: M | H1106: duarte-juan@javeriana.edu.co | I1106: 316/301-2382 | K1106: Ingeniería de Sistemas | L1106: Ingeniería | M1106: PSU | N1106: 1910NULOS-2410 | O1106: =IFERROR(IF(Tbla_actores[[#This Row],[codigo_proyecto]]="","",_xlfn.XLOOKUP(Tbla_actores[[#This Row],[codigo_proyecto]],Proyectos!$A:$A,Proyectos!$C:$C)),"") -> NULOS
A1107: 1032500407 | B1107: CC | C1107: 2021-30 | D1107: Practicante | E1107: DANIEL SANTIAGO BERMUDEZ RIVERA | F1107: 36055 | G1107: M | H1107: ds.bermudezr@javeriana.edu.co | I1107: 300/319-4500 | K1107: Ingeniería de Sistemas | L1107: Ingeniería | M1107: PSU | N1107: 1910NULOS-2410 | O1107: =IFERROR(IF(Tbla_actores[[#This Row],[codigo_proyecto]]="","",_xlfn.XLOOKUP(Tbla_actores[[#This Row],[codigo_proyecto]],Proyectos!$A:$A,Proyectos!$C:$C)),"") -> NULOS
A1108: 1032507770 | B1108: CC | C1108: 2021-30 | D1108: Practicante | E1108: CAMILO ANDRES BUITRAGO LADINO | F1108: 36456 | G1108: M | H1108: bu.camilo@javeriana.edu.co | I1108: 304/595-5980 | K1108: Ingeniería de Sistemas | L1108: Ingeniería | M1108: PSU | N1108: 1910NULOS-2410 | O1108: =IFERROR(IF(Tbla_actores[[#This Row],[codigo_proyecto]]="","",_xlfn.XLOOKUP(Tbla_actores[[#This Row],[codigo_proyecto]],Proyectos!$A:$A,Proyectos!$C:$C)),"") -> NULOS
A1109: 1000987714 | B1109: CC | C1109: 2021-30 | D1109: Practicante | E1109: CAMILO ANDRES SANDOVAL GUAYAMBUCO | F1109: 37123 | G1109: M | H1109: sandovalg.camilo@javeriana.edu.co | I1109: 322/817-3281 | K1109: Ingeniería de Sistemas | L1109: Ingeniería | M1109: PSU | N1109: 1910NULOS-2410 | O1109: =IFERROR(IF(Tbla_actores[[#This Row],[codigo_proyecto]]="","",_xlfn.XLOOKUP(Tbla_actores[[#This Row],[codigo_proyecto]],Proyectos!$A:$A,Proyectos!$C:$C)),"") -> NULOS
A1110: 1192817456 | B1110: CC | C1110: 2021-30 | D1110: Practicante | E1110: KENNETH DAVID LEONEL TRIANA | F1110: 36871 | G1110: M | H1110: kdavidleonelt@javeriana.edu.co | I1110: 318/870-7862 | K1110: Ingeniería de Sistemas | L1110: Ingeniería | M1110: PSU | N1110: 1910NULOS-2410 | O1110: =IFERROR(IF(Tbla_actores[[#This Row],[codigo_proyecto]]="","",_xlfn.XLOOKUP(Tbla_actores[[#This Row],[codigo_proyecto]],Proyectos!$A:$A,Proyectos!$C:$C)),"") -> NULOS
A1111: 1003801668 | B1111: CC | C1111: 2021-30 | D1111: Practicante | E1111: RIVERA FONSECA,THOMAS SANTIAGO | F1111: 36744 | G1111: M | H1111: thomasrivera@javeriana.edu.co | I1111: 311/840-5584 | K1111: Ingeniería de Sistemas | L1111: Ingeniería | M1111: PSU | N1111: 1910NULOS-2410 | O1111: =IFERROR(IF(Tbla_actores[[#This Row],[codigo_proyecto]]="","",_xlfn.XLOOKUP(Tbla_actores[[#This Row],[codigo_proyecto]],Proyectos!$A:$A,Proyectos!$C:$C)),"") -> NULOS
A1112: 1007681906 | B1112: CC | C1112: 2021-30 | D1112: Practicante | E1112: TRUJILLO ALVAREZ,DIEGO FERNANDO | F1112: 36729 | G1112: M | H1112: diego_trujillo@javeriana.edu.co | I1112: 305/348-8060 | K1112: Ingeniería de Sistemas | L1112: Ingeniería | M1112: PSU | N1112: 1910NULOS-2410 | O1112: =IFERROR(IF(Tbla_actores[[#This Row],[codigo_proyecto]]="","",_xlfn.XLOOKUP(Tbla_actores[[#This Row],[codigo_proyecto]],Proyectos!$A:$A,Proyectos!$C:$C)),"") -> NULOS
A1113: 1018513976 | B1113: CC | C1113: 2021-30 | D1113: Practicante | E1113: LUIS MANUEL PEÑARANDA RAMIREZ | F1113: 36440 | G1113: M | H1113: penaranda-lm@javeriana.edu.co | I1113: 302/371-2606 | K1113: Ingeniería de Sistemas | L1113: Ingeniería | M1113: PSU | N1113: 1910NULOS-2410 | O1113: =IFERROR(IF(Tbla_actores[[#This Row],[codigo_proyecto]]="","",_xlfn.XLOOKUP(Tbla_actores[[#This Row],[codigo_proyecto]],Proyectos!$A:$A,Proyectos!$C:$C)),"") -> NULOS
A1114: 1071171996 | B1114: CC | C1114: 2021-30 | D1114: Practicante | E1114: NICOLAS BARRAGAN SANCHEZ | F1114: 36388 | G1114: M | H1114: nbarragans@javeriana.edu.co | I1114: 314/515-4501 | K1114: Ingeniería de Sistemas | L1114: Ingeniería | M1114: PSU | N1114: 1910NULOS-2410 | O1114: =IFERROR(IF(Tbla_actores[[#This Row],[codigo_proyecto]]="","",_xlfn.XLOOKUP(Tbla_actores[[#This Row],[codigo_proyecto]],Proyectos!$A:$A,Proyectos!$C:$C)),"") -> NULOS
A1115: 1010043682 | B1115: CC | C1115: 2021-30 | D1115: Practicante | E1115: SERGIO ESTEBAN TRIANA BOBADILLA | F1115: 36730 | G1115: M | H1115: triana_se@javeriana.edu.co | I1115: 305/239-0609 | K1115: Ingeniería de Sistemas | L1115: Ingeniería | M1115: PSU | N1115: 1910NULOS-2410 | O1115: =IFERROR(IF(Tbla_actores[[#This Row],[codigo_proyecto]]="","",_xlfn.XLOOKUP(Tbla_actores[[#This Row],[codigo_proyecto]],Proyectos!$A:$A,Proyectos!$C:$C)),"") -> NULOS
... A1891: 1005341141 | B1891: CC | C1891: 2022-30 | D1891: Practicante | E1891: Diaz Forero Emanuel | F1891: 36773 | G1891: M | H1891: diaz_emanuel@javeriana.edu.co | I1891: 304/380-6975 | K1891: Ingeniería Civil | L1891: Ingeniería | M1891: PSU | N1891: 1910NULOS-2410 | O1891: =IFERROR(IF(Tbla_actores[[#This Row],[codigo_proyecto]]="","",_xlfn.XLOOKUP(Tbla_actores[[#This Row],[codigo_proyecto]],Proyectos!$A:$A,Proyectos!$C:$C)),"") -> NULOS
A1892: 1007766988 | B1892: CC | C1892: 2022-30 | D1892: Practicante | E1892: Fonseca Cruz Gabriela | F1892: NO ENCONTRADO | G1892: NO ENCONTRADO | H1892: NO ENCONTRADO | I1892: NO ENCONTRADO | K1892: Ingeniería Civil | L1892: Ingeniería | M1892: N/A | N1892: 1910NULOS-2410 | O1892: =IFERROR(IF(Tbla_actores[[#This Row],[codigo_proyecto]]="","",_xlfn.XLOOKUP(Tbla_actores[[#This Row],[codigo_proyecto]],Proyectos!$A:$A,Proyectos!$C:$C)),"") -> NULOS
A1893: 1055651056 | B1893: CC | C1893: 2022-30 | D1893: Practicante | E1893: Castiblanco Ramirez Andres Felipe | F1893: 35712 | G1893: M | H1893: andrescastiblanco@javeriana.edu.co | I1893: 313/253-8440 | K1893: Ingeniería Civil | L1893: Ingeniería | M1893: PSU | N1893: 1910NULOS-2410 | O1893: =IFERROR(IF(Tbla_actores[[#This Row],[codigo_proyecto]]="","",_xlfn.XLOOKUP(Tbla_actores[[#This Row],[codigo_proyecto]],Proyectos!$A:$A,Proyectos!$C:$C)),"") -> NULOS
A1894: 1000796246 | B1894: CC | C1894: 2022-30 | D1894: Practicante | E1894: Perez Rodriguez Juan Felipe | F1894: 36962 | G1894: M | H1894: juanf.perez@javeriana.edu.co | I1894: 311/444-3209 | K1894: Ingeniería Civil | L1894: Ingeniería | M1894: PSU | N1894: 1910NULOS-2410 | O1894: =IFERROR(IF(Tbla_actores[[#This Row],[codigo_proyecto]]="","",_xlfn.XLOOKUP(Tbla_actores[[#This Row],[codigo_proyecto]],Proyectos!$A:$A,Proyectos!$C:$C)),"") -> NULOS
A1895: 1032505514 | B1895: CC | C1895: 2022-30 | D1895: Practicante | E1895: Santamaria Ruiz Santiago | F1895: 36337 | G1895: M | H1895: santamaria_santiago@javeriana.edu.co | I1895: 322/218-7394 | K1895: Ingeniería Civil | L1895: Ingeniería | M1895: PSU | N1895: 1910NULOS-2410 | O1895: =IFERROR(IF(Tbla_actores[[#This Row],[codigo_proyecto]]="","",_xlfn.XLOOKUP(Tbla_actores[[#This Row],[codigo_proyecto]],Proyectos!$A:$A,Proyectos!$C:$C)),"") -> NULOS
A1896: 1000366108 | B1896: CC | C1896: 2022-30 | D1896: Practicante | E1896: Avendaño Ortiz Sebastian | F1896: 37087 | G1896: M | H1896: sebastian.avendanoo@javeriana.edu.co | I1896: 469-4541 | K1896: Ingeniería Civil | L1896: Ingeniería | M1896: PSU | N1896: 1910NULOS-2410 | O1896: =IFERROR(IF(Tbla_actores[[#This Row],[codigo_proyecto]]="","",_xlfn.XLOOKUP(Tbla_actores[[#This Row],[codigo_proyecto]],Proyectos!$A:$A,Proyectos!$C:$C)),"") -> NULOS
A1897: 1010095902 | B1897: CC | C1897: 2022-30 | D1897: Practicante | E1897: Duarte Montaño Jesus David | F1897: 36723 | G1897: M | H1897: jesusd.duarte@javeriana.edu.co | I1897: 314/786-5767 | K1897: Ingeniería Civil | L1897: Ingeniería | M1897: PSU | N1897: 1910NULOS-2410 | O1897: =IFERROR(IF(Tbla_actores[[#This Row],[codigo_proyecto]]="","",_xlfn.XLOOKUP(Tbla_actores[[#This Row],[codigo_proyecto]],Proyectos!$A:$A,Proyectos!$C:$C)),"") -> NULOS
A1898: 1000708909 | B1898: CC | C1898: 2022-30 | D1898: Practicante | E1898: Ocampo Ruiz Nicolas | F1898: 37051 | G1898: M | H1898: ocampor_nicolas@javeriana.edu.co | I1898: 316/293-2858 | K1898: Ingeniería Civil | L1898: Ingeniería | M1898: PSU | N1898: 1910NULOS-2410 | O1898: =IFERROR(IF(Tbla_actores[[#This Row],[codigo_proyecto]]="","",_xlfn.XLOOKUP(Tbla_actores[[#This Row],[codigo_proyecto]],Proyectos!$A:$A,Proyectos!$C:$C)),"") -> NULOS
A1899: 1088342717 | B1899: CC | C1899: 2022-30 | D1899: Practicante | E1899: Restrepo Hoyos Jose Alejandro | F1899: 35538 | G1899: M | H1899: joserestrepo@javeriana.edu.co | I1899: 314/668-7877 | K1899: Ingeniería Civil | L1899: Ingeniería | M1899: PSU | N1899: 1910NULOS-2410 | O1899: =IFERROR(IF(Tbla_actores[[#This Row],[codigo_proyecto]]="","",_xlfn.XLOOKUP(Tbla_actores[[#This Row],[codigo_proyecto]],Proyectos!$A:$A,Proyectos!$C:$C)),"") -> NULOS
A1900: 1193143570 | B1900: CC | C1900: 2022-30 | D1900: Practicante | E1900: Lopez Beltran Andres Felipe | F1900: 36589 | G1900: M | H1900: andresflopez@javeriana.edu.co | I1900: 310/589-1529 | K1900: Ingeniería Civil | L1900: Ingeniería | M1900: PSU | N1900: 1910NULOS-2410 | O1900: =IFERROR(IF(Tbla_actores[[#This Row],[codigo_proyecto]]="","",_xlfn.XLOOKUP(Tbla_actores[[#This Row],[codigo_proyecto]],Proyectos!$A:$A,Proyectos!$C:$C)),"") -> NULOS
A1901: 1007536527 | B1901: CC | C1901: 2022-30 | D1901: Practicante | E1901: Alfaro Martinez Juan Esteban | F1901: 36721 | G1901: M | H1901: juane.alfaro@javeriana.edu.co | I1901: 312/377-5124 | K1901: Ingeniería Civil | L1901: Ingeniería | M1901: PSU | N1901: 1910NULOS-2410 | O1901: =IFERROR(IF(Tbla_actores[[#This Row],[codigo_proyecto]]="","",_xlfn.XLOOKUP(Tbla_actores[[#This Row],[codigo_proyecto]],Proyectos!$A:$A,Proyectos!$C:$C)),"") -> NULOS
A1902: 1005186974 | B1902: CC | C1902: 2022-30 | D1902: Practicante | E1902: Arguello Calderon Cristian Andres | F1902: 36672 | G1902: M | H1902: cristianarguello@javeriana.edu.co | I1902: 315/089-9992 | K1902: Ingeniería Civil | L1902: Ingeniería | M1902: PSU | N1902: 1910NULOS-2410 | O1902: =IFERROR(IF(Tbla_actores[[#This Row],[codigo_proyecto]]="","",_xlfn.XLOOKUP(Tbla_actores[[#This Row],[codigo_proyecto]],Proyectos!$A:$A,Proyectos!$C:$C)),"") -> NULOS
A1903: 1020830354 | B1903: CC | C1903: 2022-30 | D1903: Practicante | E1903: Molina Castillo Antonio Carlos | F1903: 35781 | G1903: M | H1903: antoniomolina@javeriana.edu.co | I1903: 318/595-3566 | K1903: Ingeniería Civil | L1903: Ingeniería | M1903: PSU | N1903: 1910NULOS-2410 | O1903: =IFERROR(IF(Tbla_actores[[#This Row],[codigo_proyecto]]="","",_xlfn.XLOOKUP(Tbla_actores[[#This Row],[codigo_proyecto]],Proyectos!$A:$A,Proyectos!$C:$C)),"") -> NULOS
A1904: 1032507836 | B1904: CC | C1904: 2022-30 | D1904: Practicante | E1904: Colmenares Tarazona Omar Alexis | F1904: 36431 | G1904: M | H1904: oalexis.colmenarest@javeriana.edu.co | I1904: 318/279-7201 | K1904: Ingeniería Civil | L1904: Ingeniería | M1904: PSU | N1904: 1910NULOS-2410 | O1904: =IFERROR(IF(Tbla_actores[[#This Row],[codigo_proyecto]]="","",_xlfn.XLOOKUP(Tbla_actores[[#This Row],[codigo_proyecto]],Proyectos!$A:$A,Proyectos!$C:$C)),"") -> NULOS
... A2064: 1000706285 | B2064: CC | C2064: 2022-30 | D2064: Practicante | E2064: Herrera Cala Simon | F2064: 36615 | G2064: M | H2064: s.herrerac@javeriana.edu.co | I2064: 310/809-4252 | K2064: Ingeniería Industrial | L2064: Ingeniería | M2064: CDIO-3 | N2064: 1910NULOS-2410 | O2064: =IFERROR(IF(Tbla_actores[[#This Row],[codigo_proyecto]]="","",_xlfn.XLOOKUP(Tbla_actores[[#This Row],[codigo_proyecto]],Proyectos!$A:$A,Proyectos!$C:$C)),"") -> NULOS
A2065: 368353 | B2065: CC | C2065: 2022-30 | D2065: Practicante | E2065: De souza Lessa Lacerda Gabriel | F2065: NO ENCONTRADO | G2065: NO ENCONTRADO | H2065: NO ENCONTRADO | I2065: NO ENCONTRADO | K2065: Ingeniería de Sistemas | L2065: Ingeniería | M2065: N/A | N2065: 1910NULOS-2410 | O2065: =IFERROR(IF(Tbla_actores[[#This Row],[codigo_proyecto]]="","",_xlfn.XLOOKUP(Tbla_actores[[#This Row],[codigo_proyecto]],Proyectos!$A:$A,Proyectos!$C:$C)),"") -> NULOS
A2066: 1018514875 | B2066: CC | C2066: 2022-30 | D2066: Practicante | E2066: Bonilla Montero Kateryne | F2066: 36512 | G2066: F | H2066: kl-bonilla@javeriana.edu.co | I2066: 313/890-1376 | K2066: Ingeniería Electrónica | L2066: Ingeniería | M2066: PSU | N2066: 1910NULOS-2410 | O2066: =IFERROR(IF(Tbla_actores[[#This Row],[codigo_proyecto]]="","",_xlfn.XLOOKUP(Tbla_actores[[#This Row],[codigo_proyecto]],Proyectos!$A:$A,Proyectos!$C:$C)),"") -> NULOS
...

Sheet Proyectos
A1: codigo_proyecto | B1: semestre | C1: titulo_proyecto | D1: tipo_proyecto | E1: objetivos | F1: tematica | G1: tipo_actividades | H1: encargado_docente | I1: fecha_inicio | J1: fecha_fin | K1: duracion_meses | L1: departamento | M1: municipio | N1: latitud | O1: longitud | P1: estado | Q1: observaciones
A2: 2510ISISTALI-1 | B2: =LEFT(Tbla_proyectos[[#This Row],[codigo_proyecto]],4) -> 2510 | C2: Proyecto 1 | D2: Prácticas | E2: Desarrollo y mantenimiento de la página web de la entidad. Implementación y gestión de estrategias de marketing digital. Configuración y optimización de aplicaciones en Google App. Soporte y administración de la plataforma Salesforce. | F2: Desarrollo Web | G2: Asesoría Técnica | H2: Alicia Mercedes Arenas Valderrama | K2: =IF(OR(Tbla_proyectos[[#This Row],[fecha_inicio]]="",Tbla_proyectos[[#This Row],[fecha_fin]]=""),"",DATEDIF(Tbla_proyectos[[#This Row],[fecha_inicio]],Tbla_proyectos[[#This Row],[fecha_fin]],"M")) | L2: BOGOTA | M2: BOGOTÁ, D.C. | N2: =IF(Tbla_proyectos[[#This Row],[municipio]]="","",VLOOKUP(Tbla_proyectos[[#This Row],[municipio]],INDIRECT(Tbla_proyectos[[#This Row],[departamento]]),2,0)) -> 4.3161077 | O2: =IF(Tbla_proyectos[[#This Row],[municipio]]="","",VLOOKUP(Tbla_proyectos[[#This Row],[municipio]],INDIRECT(Tbla_proyectos[[#This Row],[departamento]]),2,0)) -> 4.3161077
A3: 2530IINDSMAR-2 | B3: =LEFT(Tbla_proyectos[[#This Row],[codigo_proyecto]],4) -> 2530 | C3: Diseño de procesos y procedimientos | D3: Prácticas | E3: Elaborar, documentar y proponer los procesos y procedimientos del colegio Agudelo Restrepo | F3: Gestión de Procesos | G3: Asesoría Técnica y Capacitación | H3: Marcela Camargo Pabón | K3: =IF(OR(Tbla_proyectos[[#This Row],[fecha_inicio]]="",Tbla_proyectos[[#This Row],[fecha_fin]]=""),"",DATEDIF(Tbla_proyectos[[#This Row],[fecha_inicio]],Tbla_proyectos[[#This Row],[fecha_fin]],"M")) | L3: BOGOTA | M3: BOGOTÁ, D.C. | N3: =IF(Tbla_proyectos[[#This Row],[municipio]]="","",VLOOKUP(Tbla_proyectos[[#This Row],[municipio]],INDIRECT(Tbla_proyectos[[#This Row],[departamento]]),2,0)) -> 4.3161077 | O3: =IF(Tbla_proyectos[[#This Row],[municipio]]="","",VLOOKUP(Tbla_proyectos[[#This Row],[municipio]],INDIRECT(Tbla_proyectos[[#This Row],[departamento]]),2,0)) -> 4.3161077 | P3: Nuevo
A4: 2530IINDSMAR-1 | B4: =LEFT(Tbla_proyectos[[#This Row],[codigo_proyecto]],4) -> 2530 | C4: Evaluación de residuos en la playa de Santa Marta | D4: Prácticas | E4: Investigación de microplásticos y manejo de residuos en la playa de Santa Marta Colombia | F4: Gestión de Residuos | G4: Asesoría Técnica y Capacitación | H4: Marcela Camargo Pabón | K4: =IF(OR(Tbla_proyectos[[#This Row],[fecha_inicio]]="",Tbla_proyectos[[#This Row],[fecha_fin]]=""),"",DATEDIF(Tbla_proyectos[[#This Row],[fecha_inicio]],Tbla_proyectos[[#This Row],[fecha_fin]],"M")) | L4: BOGOTA | M4: BOGOTÁ, D.C. | N4: =IF(Tbla_proyectos[[#This Row],[municipio]]="","",VLOOKUP(Tbla_proyectos[[#This Row],[municipio]],INDIRECT(Tbla_proyectos[[#This Row],[departamento]]),2,0)) -> 4.3161077 | O4: =IF(Tbla_proyectos[[#This Row],[municipio]]="","",VLOOKUP(Tbla_proyectos[[#This Row],[municipio]],INDIRECT(Tbla_proyectos[[#This Row],[departamento]]),2,0)) -> 4.3161077 | P4: Nuevo
A5: 2430IINDSMAR-1 | B5: =LEFT(Tbla_proyectos[[#This Row],[codigo_proyecto]],4) -> 2430 | C5: Revisión y ajuste de procesos proyecto estudiar para construir | D5: Prácticas | E5: Revisión y ajuste de procesos del proyecto "Estudiar para Construir". Visitas a sedes a obras de construcción en Fontibón y Madrid para realizar un análisis detallado de los procesos en campo. | F5: Capacitación en Construcción | G5: Asesoría Técnica | H5: Marcela Camargo Pabón | K5: =IF(OR(Tbla_proyectos[[#This Row],[fecha_inicio]]="",Tbla_proyectos[[#This Row],[fecha_fin]]=""),"",DATEDIF(Tbla_proyectos[[#This Row],[fecha_inicio]],Tbla_proyectos[[#This Row],[fecha_fin]],"M")) | L5: BOGOTA | M5: BOGOTÁ, D.C. | N5: =IF(Tbla_proyectos[[#This Row],[municipio]]="","",VLOOKUP(Tbla_proyectos[[#This Row],[municipio]],INDIRECT(Tbla_proyectos[[#This Row],[departamento]]),2,0)) -> 4.3161077 | O5: =IF(Tbla_proyectos[[#This Row],[municipio]]="","",VLOOKUP(Tbla_proyectos[[#This Row],[municipio]],INDIRECT(Tbla_proyectos[[#This Row],[departamento]]),2,0)) -> 4.3161077 | P5: Continuidad
A6: 2510IINDSGIO-5 | B6: =LEFT(Tbla_proyectos[[#This Row],[codigo_proyecto]],4) -> 2510 | C6: PROPUESTA DE GESTION Y ANALISIS ESTRATEGICO | D6: Prácticas | E6: Asesoría técnica por medio de reuniones de exploración, entendimiento, evaluación y ejecución de propuestas de proyectos de ingeniería que le ayuden a la entidad a mejorar la gestión de procesos. | F6: Gestión de Procesos | G6: Asesoría Técnica y Capacitación | H6: Giovanna Rosa Fiorillo Obando | K6: =IF(OR(Tbla_proyectos[[#This Row],[fecha_inicio]]="",Tbla_proyectos[[#This Row],[fecha_fin]]=""),"",DATEDIF(Tbla_proyectos[[#This Row],[fecha_inicio]],Tbla_proyectos[[#This Row],[fecha_fin]],"M")) | L6: BOGOTA | M6: BOGOTÁ, D.C. | N6: =IF(Tbla_proyectos[[#This Row],[municipio]]="","",VLOOKUP(Tbla_proyectos[[#This Row],[municipio]],INDIRECT(Tbla_proyectos[[#This Row],[departamento]]),2,0)) -> 4.3161077 | O6: =IF(Tbla_proyectos[[#This Row],[municipio]]="","",VLOOKUP(Tbla_proyectos[[#This Row],[municipio]],INDIRECT(Tbla_proyectos[[#This Row],[departamento]]),2,0)) -> 4.3161077 | P6: Continuidad
A7: 2530IINDSGIO-5 | B7: =LEFT(Tbla_proyectos[[#This Row],[codigo_proyecto]],4) -> 2530 | C7: PROPUESTA DE GESTION Y ANALISIS ESTRATEGICO | D7: Prácticas | E7: Asesoría técnica por medio de reuniones de exploración, entendimiento, evaluación y ejecución de propuestas de proyectos de ingeniería que le ayuden a la entidad a mejorar la gestión de procesos. | F7: Gestión de Procesos | G7: Asesoría Técnica y Capacitación | H7: Giovanna Rosa Fiorillo Obando | K7: =IF(OR(Tbla_proyectos[[#This Row],[fecha_inicio]]="",Tbla_proyectos[[#This Row],[fecha_fin]]=""),"",DATEDIF(Tbla_proyectos[[#This Row],[fecha_inicio]],Tbla_proyectos[[#This Row],[fecha_fin]],"M")) | L7: BOGOTA | M7: BOGOTÁ, D.C. | N7: =IF(Tbla_proyectos[[#This Row],[municipio]]="","",VLOOKUP(Tbla_proyectos[[#This Row],[municipio]],INDIRECT(Tbla_proyectos[[#This Row],[departamento]]),2,0)) -> 4.3161077 | O7: =IF(Tbla_proyectos[[#This Row],[municipio]]="","",VLOOKUP(Tbla_proyectos[[#This Row],[municipio]],INDIRECT(Tbla_proyectos[[#This Row],[departamento]]),2,0)) -> 4.3161077 | P7: Continuidad
A8: 2430IINDSGIO-5 | B8: =LEFT(Tbla_proyectos[[#This Row],[codigo_proyecto]],4) -> 2430 | C8: PROPUESTA DE GESTION Y ANALISIS ESTRATEGICO | D8: Prácticas | E8: Asesoría técnica por medio de reuniones de exploración, entendimiento, evaluación y ejecución de propuestas de proyectos de ingeniería que le ayuden a la entidad a mejorar la gestión de procesos. | F8: Gestión de Procesos | G8: Asesoría Técnica y Capacitación | H8: Giovanna Rosa Fiorillo Obando | K8: =IF(OR(Tbla_proyectos[[#This Row],[fecha_inicio]]="",Tbla_proyectos[[#This Row],[fecha_fin]]=""),"",DATEDIF(Tbla_proyectos[[#This Row],[fecha_inicio]],Tbla_proyectos[[#This Row],[fecha_fin]],"M")) | L8: BOGOTA | M8: BOGOTÁ, D.C. | N8: =IF(Tbla_proyectos[[#This Row],[municipio]]="","",VLOOKUP(Tbla_proyectos[[#This Row],[municipio]],INDIRECT(Tbla_proyectos[[#This Row],[departamento]]),2,0)) -> 4.3161077 | O8: =IF(Tbla_proyectos[[#This Row],[municipio]]="","",VLOOKUP(Tbla_proyectos[[#This Row],[municipio]],INDIRECT(Tbla_proyectos[[#This Row],[departamento]]),2,0)) -> 4.3161077 | P8: Continuidad
A9: 2510IELECDIE-1 | B9: =LEFT(Tbla_proyectos[[#This Row],[codigo_proyecto]],4) -> 2510 | C9: Sistema Antiescape en dispositivos de cuidado residencial | D9: Prácticas | E9: Diseño e implentación de un sistema anti-escape para mejorar la seguridad de la entidad. Realización de actividades de integración con los residentes de la asociación, quienes tienen Trastorno Mental Severo. | F9: Tecnologías de Asistencia | G9: Asesoría Técnica | H9: Diego Fernando Parra Díaz | K9: =IF(OR(Tbla_proyectos[[#This Row],[fecha_inicio]]="",Tbla_proyectos[[#This Row],[fecha_fin]]=""),"",DATEDIF(Tbla_proyectos[[#This Row],[fecha_inicio]],Tbla_proyectos[[#This Row],[fecha_fin]],"M")) | L9: BOGOTA | M9: BOGOTÁ, D.C. | N9: =IF(Tbla_proyectos[[#This Row],[municipio]]="","",VLOOKUP(Tbla_proyectos[[#This Row],[municipio]],INDIRECT(Tbla_proyectos[[#This Row],[departamento]]),2,0)) -> 4.3161077 | O9: =IF(Tbla_proyectos[[#This Row],[municipio]]="","",VLOOKUP(Tbla_proyectos[[#This Row],[municipio]],INDIRECT(Tbla_proyectos[[#This Row],[departamento]]),2,0)) -> 4.3161077 | P9: Continuidad
A10: 2530IELECDIE-1 | B10: =LEFT(Tbla_proyectos[[#This Row],[codigo_proyecto]],4) -> 2530 | C10: Sistema Antiescape en dispositivos de cuidado residencial | D10: Prácticas | E10: Diseño e implentación de un sistema anti-escape para mejorar la seguridad de la entidad. Realización de actividades de integración con los residentes de la asociación, quienes tienen Trastorno Mental Severo. | F10: Tecnologías de Asistencia | G10: Asesoría Técnica | H10: Diego Fernando Parra Díaz | K10: =IF(OR(Tbla_proyectos[[#This Row],[fecha_inicio]]="",Tbla_proyectos[[#This Row],[fecha_fin]]=""),"",DATEDIF(Tbla_proyectos[[#This Row],[fecha_inicio]],Tbla_proyectos[[#This Row],[fecha_fin]],"M")) | L10: BOGOTA | M10: BOGOTÁ, D.C. | N10: =IF(Tbla_proyectos[[#This Row],[municipio]]="","",VLOOKUP(Tbla_proyectos[[#This Row],[municipio]],INDIRECT(Tbla_proyectos[[#This Row],[departamento]]),2,0)) -> 4.3161077 | O10: =IF(Tbla_proyectos[[#This Row],[municipio]]="","",VLOOKUP(Tbla_proyectos[[#This Row],[municipio]],INDIRECT(Tbla_proyectos[[#This Row],[departamento]]),2,0)) -> 4.3161077 | P10: Continuidad
A11: 2430IELECDIE-1 | B11: =LEFT(Tbla_proyectos[[#This Row],[codigo_proyecto]],4) -> 2430 | C11: Sistema Antiescape en dispositivos de cuidado residencial | D11: Prácticas | E11: Diseño e implentación de un sistema anti-escape para mejorar la seguridad de la entidad. Realización de actividades de integración con los residentes de la asociación, quienes tienen Trastorno Mental Severo. | F11: Tecnologías de Asistencia | G11: Asesoría Técnica | H11: Diego Fernando Parra Díaz | K11: =IF(OR(Tbla_proyectos[[#This Row],[fecha_inicio]]="",Tbla_proyectos[[#This Row],[fecha_fin]]=""),"",DATEDIF(Tbla_proyectos[[#This Row],[fecha_inicio]],Tbla_proyectos[[#This Row],[fecha_fin]],"M")) | L11: BOGOTA | M11: BOGOTÁ, D.C. | N11: =IF(Tbla_proyectos[[#This Row],[municipio]]="","",VLOOKUP(Tbla_proyectos[[#This Row],[municipio]],INDIRECT(Tbla_proyectos[[#This Row],[departamento]]),2,0)) -> 4.3161077 | O11: =IF(Tbla_proyectos[[#This Row],[municipio]]="","",VLOOKUP(Tbla_proyectos[[#This Row],[municipio]],INDIRECT(Tbla_proyectos[[#This Row],[departamento]]),2,0)) -> 4.3161077 | P11: Continuidad
A12: 2520IELECDIE-1 | B12: =LEFT(Tbla_proyectos[[#This Row],[codigo_proyecto]],4) -> 2520 | C12: Sistema Antiescape en dispositivos de cuidado residencial | D12: Prácticas | E12: Diseño e implentación de un sistema anti-escape para mejorar la seguridad de la entidad. Realización de actividades de integración con los residentes de la asociación, quienes tienen Trastorno Mental Severo. | F12: Tecnologías de Asistencia | G12: Asesoría Técnica | H12: Diego Fernando Parra Díaz | K12: =IF(OR(Tbla_proyectos[[#This Row],[fecha_inicio]]="",Tbla_proyectos[[#This Row],[fecha_fin]]=""),"",DATEDIF(Tbla_proyectos[[#This Row],[fecha_inicio]],Tbla_proyectos[[#This Row],[fecha_fin]],"M")) | L12: BOGOTA | M12: BOGOTÁ, D.C. | N12: =IF(Tbla_proyectos[[#This Row],[municipio]]="","",VLOOKUP(Tbla_proyectos[[#This Row],[municipio]],INDIRECT(Tbla_proyectos[[#This Row],[departamento]]),2,0)) -> 4.3161077 | O12: =IF(Tbla_proyectos[[#This Row],[municipio]]="","",VLOOKUP(Tbla_proyectos[[#This Row],[municipio]],INDIRECT(Tbla_proyectos[[#This Row],[departamento]]),2,0)) -> 4.3161077 | P12: Continuidad
A13: 2510IINDSBLA-4 | B13: =LEFT(Tbla_proyectos[[#This Row],[codigo_proyecto]],4) -> 2510 | C13: Asesoría en proyecto productivo en las veredas altas del Municipio de Venecia, Cundinamarca | D13: Prácticas | E13: Definición de un posible abordaje de proyecto productivo agrícola en las veredas altas del Municipio de Venencia, Cundinamarca | F13: Gestión de Procesos | G13: Asesoría Técnica | H13: Blanca Elvira Oviedo Torres | K13: =IF(OR(Tbla_proyectos[[#This Row],[fecha_inicio]]="",Tbla_proyectos[[#This Row],[fecha_fin]]=""),"",DATEDIF(Tbla_proyectos[[#This Row],[fecha_inicio]],Tbla_proyectos[[#This Row],[fecha_fin]],"M")) | L13: CUNDINAMARCA | M13: VENECIA | N13: =IF(Tbla_proyectos[[#This Row],[municipio]]="","",VLOOKUP(Tbla_proyectos[[#This Row],[municipio]],INDIRECT(Tbla_proyectos[[#This Row],[departamento]]),2,0)) -> 4.0633421 | O13: =IF(Tbla_proyectos[[#This Row],[municipio]]="","",VLOOKUP(Tbla_proyectos[[#This Row],[municipio]],INDIRECT(Tbla_proyectos[[#This Row],[departamento]]),2,0)) -> 4.0633421 | P13: Nuevo
A14: 2510ICIVLJOR-1 | B14: =LEFT(Tbla_proyectos[[#This Row],[codigo_proyecto]],4) -> 2510 | C14: Desarrollo del plan de gestión integral del recurso hídrico para la ZRC de Venecia (Cundinamarca) | D14: Prácticas | E14: Diagnóstico de la relación de la comunidad de la ZRC con el agua a nivel de unidad de vivienda. | F14: Gestión del Agua | G14: Apoyo Técnico | H14: Jorge Escobar Vargas | K14: =IF(OR(Tbla_proyectos[[#This Row],[fecha_inicio]]="",Tbla_proyectos[[#This Row],[fecha_fin]]=""),"",DATEDIF(Tbla_proyectos[[#This Row],[fecha_inicio]],Tbla_proyectos[[#This Row],[fecha_fin]],"M")) | L14: CUNDINAMARCA | M14: VENECIA | N14: =IF(Tbla_proyectos[[#This Row],[municipio]]="","",VLOOKUP(Tbla_proyectos[[#This Row],[municipio]],INDIRECT(Tbla_proyectos[[#This Row],[departamento]]),2,0)) -> 4.0633421 | O14: =IF(Tbla_proyectos[[#This Row],[municipio]]="","",VLOOKUP(Tbla_proyectos[[#This Row],[municipio]],INDIRECT(Tbla_proyectos[[#This Row],[departamento]]),2,0)) -> 4.0633421 | P14: Continuidad
A15: 2510ISISTJUA-12 | B15: =LEFT(Tbla_proyectos[[#This Row],[codigo_proyecto]],4) -> 2510 | D15: Prácticas | E15: Identificar y documentar las falencias de la organización. Realizar un análisis DOFA detallado. Sistematizar la información recopilada. Proponer estrategias de mejora basadas en el análisis realizado. Brindar asesoría técnica sobre las mejoras organizacionales. | F15: Gestión de Procesos | G15: Asesoría Técnica | H15: Juan Felipe Salcedo | K15: =IF(OR(Tbla_proyectos[[#This Row],[fecha_inicio]]="",Tbla_proyectos[[#This Row],[fecha_fin]]=""),"",DATEDIF(Tbla_proyectos[[#This Row],[fecha_inicio]],Tbla_proyectos[[#This Row],[fecha_fin]],"M")) | L15: BOGOTA | M15: BOGOTÁ, D.C. | N15: =IF(Tbla_proyectos[[#This Row],[municipio]]="","",VLOOKUP(Tbla_proyectos[[#This Row],[municipio]],INDIRECT(Tbla_proyectos[[#This Row],[departamento]]),2,0)) -> 4.3161077 | O15: =IF(Tbla_proyectos[[#This Row],[municipio]]="","",VLOOKUP(Tbla_proyectos[[#This Row],[municipio]],INDIRECT(Tbla_proyectos[[#This Row],[departamento]]),2,0)) -> 4.3161077 | P15: Nuevo
A16: 2430ICIVLLUI-1 | B16: =LEFT(Tbla_proyectos[[#This Row],[codigo_proyecto]],4) -> 2430 | C16: PROYECTO “CAPACITACIÓN EN CONSTRUCCIÓN-CAMACOL” | D16: Prácticas | E16: Capacitación en construcción a trabajadores de la industria de la construcción afiliada a CAMACOL. Módulo 1, Módulo 2, Módulo 3 o Módulo 4. | F16: Capacitación en Construcción | G16: Capacitación | H16: Luis Alberto Jaramillo Gómez | K16: =IF(OR(Tbla_proyectos[[#This Row],[fecha_inicio]]="",Tbla_proyectos[[#This Row],[fecha_fin]]=""),"",DATEDIF(Tbla_proyectos[[#This Row],[fecha_inicio]],Tbla_proyectos[[#This Row],[fecha_fin]],"M")) | L16: BOGOTA | M16: BOGOTÁ, D.C. | N16: =IF(Tbla_proyectos[[#This Row],[municipio]]="","",VLOOKUP(Tbla_proyectos[[#This Row],[municipio]],INDIRECT(Tbla_proyectos[[#This Row],[departamento]]),2,0)) -> 4.3161077 | O16: =IF(Tbla_proyectos[[#This Row],[municipio]]="","",VLOOKUP(Tbla_proyectos[[#This Row],[municipio]],INDIRECT(Tbla_proyectos[[#This Row],[departamento]]),2,0)) -> 4.3161077 | P16: Continuidad
A17: 2510ICIVLLUI-1 | B17: =LEFT(Tbla_proyectos[[#This Row],[codigo_proyecto]],4) -> 2510 | C17: PROYECTO “CAPACITACIÓN EN CONSTRUCCIÓN-CAMACOL” | D17: Prácticas | E17: Capacitación en construcción a trabajadores de la industria de la construcción afiliada a CAMACOL. Módulo 1, Módulo 2, Módulo 3 o Módulo 4. | F17: Capacitación en Construcción | G17: Capacitación | H17: Luis Alberto Jaramillo Gómez | K17: =IF(OR(Tbla_proyectos[[#This Row],[fecha_inicio]]="",Tbla_proyectos[[#This Row],[fecha_fin]]=""),"",DATEDIF(Tbla_proyectos[[#This Row],[fecha_inicio]],Tbla_proyectos[[#This Row],[fecha_fin]],"M")) | L17: BOGOTA | M17: BOGOTÁ, D.C. | N17: =IF(Tbla_proyectos[[#This Row],[municipio]]="","",VLOOKUP(Tbla_proyectos[[#This Row],[municipio]],INDIRECT(Tbla_proyectos[[#This Row],[departamento]]),2,0)) -> 4.3161077 | O17: =IF(Tbla_proyectos[[#This Row],[municipio]]="","",VLOOKUP(Tbla_proyectos[[#This Row],[municipio]],INDIRECT(Tbla_proyectos[[#This Row],[departamento]]),2,0)) -> 4.3161077 | P17: Continuidad
A18: 2530ICIVLLUI-1 | B18: =LEFT(Tbla_proyectos[[#This Row],[codigo_proyecto]],4) -> 2530 | C18: PROYECTO “CAPACITACIÓN EN CONSTRUCCIÓN-CAMACOL” | D18: Prácticas | E18: Capacitación en construcción a trabajadores de la industria de la construcción afiliada a CAMACOL. Módulo 1, Módulo 2, Módulo 3 o Módulo 4. | F18: Capacitación en Construcción | G18: Capacitación | H18: Luis Alberto Jaramillo Gómez | K18: =IF(OR(Tbla_proyectos[[#This Row],[fecha_inicio]]="",Tbla_proyectos[[#This Row],[fecha_fin]]=""),"",DATEDIF(Tbla_proyectos[[#This Row],[fecha_inicio]],Tbla_proyectos[[#This Row],[fecha_fin]],"M")) | L18: BOGOTA | M18: BOGOTÁ, D.C. | N18: =IF(Tbla_proyectos[[#This Row],[municipio]]="","",VLOOKUP(Tbla_proyectos[[#This Row],[municipio]],INDIRECT(Tbla_proyectos[[#This Row],[departamento]]),2,0)) -> 4.3161077 | O18: =IF(Tbla_proyectos[[#This Row],[municipio]]="","",VLOOKUP(Tbla_proyectos[[#This Row],[municipio]],INDIRECT(Tbla_proyectos[[#This Row],[departamento]]),2,0)) -> 4.3161077 | P18: Continuidad
A19: 2430ICIVLLUI-6 | B19: =LEFT(Tbla_proyectos[[#This Row],[codigo_proyecto]],4) -> 2430 | C19: CURSO BÁSICO EN CONSTRICCIÓN | D19: Prácticas | E19: Desarrollar cursos de capacitación a maestros de la construcción, con énfasis en el desarrollo de bases teóricas y habilidades prácticas a partir de cuatro módulos, | F19: Capacitación en Construcción | G19: Capacitación | H19: Luis Alberto Jaramillo Gómez | K19: =IF(OR(Tbla_proyectos[[#This Row],[fecha_inicio]]="",Tbla_proyectos[[#This Row],[fecha_fin]]=""),"",DATEDIF(Tbla_proyectos[[#This Row],[fecha_inicio]],Tbla_proyectos[[#This Row],[fecha_fin]],"M")) | L19: BOGOTA | M19: BOGOTÁ, D.C. | N19: =IF(Tbla_proyectos[[#This Row],[municipio]]="","",VLOOKUP(Tbla_proyectos[[#This Row],[municipio]],INDIRECT(Tbla_proyectos[[#This Row],[departamento]]),2,0)) -> 4.3161077 | O19: =IF(Tbla_proyectos[[#This Row],[municipio]]="","",VLOOKUP(Tbla_proyectos[[#This Row],[municipio]],INDIRECT(Tbla_proyectos[[#This Row],[departamento]]),2,0)) -> 4.3161077 | P19: Continuidad
A20: 2530IELECDIE-5 | B20: =LEFT(Tbla_proyectos[[#This Row],[codigo_proyecto]],4) -> 2530 | C20: Diagnodtico de necesidades de asesoría técnica para las labores de cuidado | D20: Prácticas | E20: Levantamiento de reporte de necesidades de asesoría técnica para las labores de cuidado de la institución | F20: Tecnologías de Asistencia | G20: Asesoría Técnica | H20: Diego Fernando Parra Díaz | K20: =IF(OR(Tbla_proyectos[[#This Row],[fecha_inicio]]="",Tbla_proyectos[[#This Row],[fecha_fin]]=""),"",DATEDIF(Tbla_proyectos[[#This Row],[fecha_inicio]],Tbla_proyectos[[#This Row],[fecha_fin]],"M")) | L20: BOGOTA | M20: BOGOTÁ, D.C. | N20: =IF(Tbla_proyectos[[#This Row],[municipio]]="","",VLOOKUP(Tbla_proyectos[[#This Row],[municipio]],INDIRECT(Tbla_proyectos[[#This Row],[departamento]]),2,0)) -> 4.3161077 | O20: =IF(Tbla_proyectos[[#This Row],[municipio]]="","",VLOOKUP(Tbla_proyectos[[#This Row],[municipio]],INDIRECT(Tbla_proyectos[[#This Row],[departamento]]),2,0)) -> 4.3161077 | P20: Nuevo
A21: 2510IINDSBLA-2 | B21: =LEFT(Tbla_proyectos[[#This Row],[codigo_proyecto]],4) -> 2510 | C21: Manual de Funciones para el Colegio | D21: Prácticas | E21: Completar la elaboración del manual de funciones del Colegio Gabriel García Márquez y divulgarlo para asegurar su implementación y comprensión. | F21: Gestión de Procesos | G21: Asesoría Técnica | H21: Blanca Elvira Oviedo Torres | K21: =IF(OR(Tbla_proyectos[[#This Row],[fecha_inicio]]="",Tbla_proyectos[[#This Row],[fecha_fin]]=""),"",DATEDIF(Tbla_proyectos[[#This Row],[fecha_inicio]],Tbla_proyectos[[#This Row],[fecha_fin]],"M")) | L21: BOGOTA | M21: BOGOTÁ, D.C. | N21: =IF(Tbla_proyectos[[#This Row],[municipio]]="","",VLOOKUP(Tbla_proyectos[[#This Row],[municipio]],INDIRECT(Tbla_proyectos[[#This Row],[departamento]]),2,0)) -> 4.3161077 | O21: =IF(Tbla_proyectos[[#This Row],[municipio]]="","",VLOOKUP(Tbla_proyectos[[#This Row],[municipio]],INDIRECT(Tbla_proyectos[[#This Row],[departamento]]),2,0)) -> 4.3161077 | P21: Continuidad
A22: 2430ISISTALI-2 | B22: =LEFT(Tbla_proyectos[[#This Row],[codigo_proyecto]],4) -> 2430 | C22: Proyecto 3 | D22: Prácticas | E22: Desarrollo de software utilizando técnicas de programación modernas. Aplicación del modelo RUP (Rational Unified Process) en el ciclo de vida del proyecto de software. Implementación y seguimiento de metodologías SCRUM para la gestión ágil de proyectos. | F22: Desarrollo de Software | G22: Asesoría Técnica | H22: Alicia Mercedes Arenas Valderrama | K22: =IF(OR(Tbla_proyectos[[#This Row],[fecha_inicio]]="",Tbla_proyectos[[#This Row],[fecha_fin]]=""),"",DATEDIF(Tbla_proyectos[[#This Row],[fecha_inicio]],Tbla_proyectos[[#This Row],[fecha_fin]],"M")) | L22: BOGOTA | M22: BOGOTÁ, D.C. | N22: =IF(Tbla_proyectos[[#This Row],[municipio]]="","",VLOOKUP(Tbla_proyectos[[#This Row],[municipio]],INDIRECT(Tbla_proyectos[[#This Row],[departamento]]),2,0)) -> 4.3161077 | O22: =IF(Tbla_proyectos[[#This Row],[municipio]]="","",VLOOKUP(Tbla_proyectos[[#This Row],[municipio]],INDIRECT(Tbla_proyectos[[#This Row],[departamento]]),2,0)) -> 4.3161077
A23: 2510ISISTALI-3 | B23: =LEFT(Tbla_proyectos[[#This Row],[codigo_proyecto]],4) -> 2510 | C23: Proyecto 3 | D23: Prácticas | E23: Desarrollar sesiones de capacitación en programación básica y avanzada y en ofimática. | F23: Capacitación en Programación | G23: Capacitación | H23: Alicia Mercedes Arenas Valderrama | K23: =IF(OR(Tbla_proyectos[[#This Row],[fecha_inicio]]="",Tbla_proyectos[[#This Row],[fecha_fin]]=""),"",DATEDIF(Tbla_proyectos[[#This Row],[fecha_inicio]],Tbla_proyectos[[#This Row],[fecha_fin]],"M")) | L23: BOGOTA | M23: BOGOTÁ, D.C. | N23: =IF(Tbla_proyectos[[#This Row],[municipio]]="","",VLOOKUP(Tbla_proyectos[[#This Row],[municipio]],INDIRECT(Tbla_proyectos[[#This Row],[departamento]]),2,0)) -> 4.3161077 | O23: =IF(Tbla_proyectos[[#This Row],[municipio]]="","",VLOOKUP(Tbla_proyectos[[#This Row],[municipio]],INDIRECT(Tbla_proyectos[[#This Row],[departamento]]),2,0)) -> 4.3161077
A24: 2430ISISTALI-3 | B24: =LEFT(Tbla_proyectos[[#This Row],[codigo_proyecto]],4) -> 2430 | C24: Proyecto 4 | D24: Prácticas | E24: Desarrollar sesiones de capacitación en programación básica y avanzada y en ofimática. | F24: Capacitación en Programación | G24: Capacitación | H24: Alicia Mercedes Arenas Valderrama | K24: =IF(OR(Tbla_proyectos[[#This Row],[fecha_inicio]]="",Tbla_proyectos[[#This Row],[fecha_fin]]=""),"",DATEDIF(Tbla_proyectos[[#This Row],[fecha_inicio]],Tbla_proyectos[[#This Row],[fecha_fin]],"M")) | L24: BOGOTA | M24: BOGOTÁ, D.C. | N24: =IF(Tbla_proyectos[[#This Row],[municipio]]="","",VLOOKUP(Tbla_proyectos[[#This Row],[municipio]],INDIRECT(Tbla_proyectos[[#This Row],[departamento]]),2,0)) -> 4.3161077 | O24: =IF(Tbla_proyectos[[#This Row],[municipio]]="","",VLOOKUP(Tbla_proyectos[[#This Row],[municipio]],INDIRECT(Tbla_proyectos[[#This Row],[departamento]]),2,0)) -> 4.3161077
A25: 2510IELECJOS-3 | B25: =LEFT(Tbla_proyectos[[#This Row],[codigo_proyecto]],4) -> 2510 | D25: Prácticas | E25: Desarrollo de sesiones de capacitación en electrónica básica, electricidad y alfabetización digital. | F25: Capacitación en Electricidad y Electrónica | G25: Capacitación | H25: José Ignacio Acevedo | K25: =IF(OR(Tbla_proyectos[[#This Row],[fecha_inicio]]="",Tbla_proyectos[[#This Row],[fecha_fin]]=""),"",DATEDIF(Tbla_proyectos[[#This Row],[fecha_inicio]],Tbla_proyectos[[#This Row],[fecha_fin]],"M")) | L25: BOGOTA | M25: BOGOTÁ, D.C. | N25: =IF(Tbla_proyectos[[#This Row],[municipio]]="","",VLOOKUP(Tbla_proyectos[[#This Row],[municipio]],INDIRECT(Tbla_proyectos[[#This Row],[departamento]]),2,0)) -> 4.3161077 | O25: =IF(Tbla_proyectos[[#This Row],[municipio]]="","",VLOOKUP(Tbla_proyectos[[#This Row],[municipio]],INDIRECT(Tbla_proyectos[[#This Row],[departamento]]),2,0)) -> 4.3161077 | P25: Continuidad
A26: 2430IELECJOS-3 | B26: =LEFT(Tbla_proyectos[[#This Row],[codigo_proyecto]],4) -> 2430 | C26: PROSOFI | D26: Prácticas | E26: Desarrollo de sesiones de capacitación en electrónica básica, electricidad y alfabetización digital. | F26: Capacitación en Electricidad y Electrónica | G26: Capacitación | H26: José Ignacio Acevedo Gordo | K26: =IF(OR(Tbla_proyectos[[#This Row],[fecha_inicio]]="",Tbla_proyectos[[#This Row],[fecha_fin]]=""),"",DATEDIF(Tbla_proyectos[[#This Row],[fecha_inicio]],Tbla_proyectos[[#This Row],[fecha_fin]],"M")) | L26: BOGOTA | M26: BOGOTÁ, D.C. | N26: =IF(Tbla_proyectos[[#This Row],[municipio]]="","",VLOOKUP(Tbla_proyectos[[#This Row],[municipio]],INDIRECT(Tbla_proyectos[[#This Row],[departamento]]),2,0)) -> 4.3161077 | O26: =IF(Tbla_proyectos[[#This Row],[municipio]]="","",VLOOKUP(Tbla_proyectos[[#This Row],[municipio]],INDIRECT(Tbla_proyectos[[#This Row],[departamento]]),2,0)) -> 4.3161077 | P26: Continuidad
A27: 2510IINDSBLA-1 | B27: =LEFT(Tbla_proyectos[[#This Row],[codigo_proyecto]],4) -> 2510 | C27: Estrategias para lograr equilibrio económico | D27: Prácticas | E27: Análisis de aspectos organizacionales del colegio para identificar áreas de mejora. Propuesta de acciones estratégicas para lograr el equilibrio económico del colegio. | F27: Gestión de Procesos | G27: Asesoría Técnica y Capacitación | H27: Blanca Elvira Oviedo Torres | K27: =IF(OR(Tbla_proyectos[[#This Row],[fecha_inicio]]="",Tbla_proyectos[[#This Row],[fecha_fin]]=""),"",DATEDIF(Tbla_proyectos[[#This Row],[fecha_inicio]],Tbla_proyectos[[#This Row],[fecha_fin]],"M")) | L27: BOGOTA | M27: BOGOTÁ, D.C. | N27: =IF(Tbla_proyectos[[#This Row],[municipio]]="","",VLOOKUP(Tbla_proyectos[[#This Row],[municipio]],INDIRECT(Tbla_proyectos[[#This Row],[departamento]]),2,0)) -> 4.3161077 | O27: =IF(Tbla_proyectos[[#This Row],[municipio]]="","",VLOOKUP(Tbla_proyectos[[#This Row],[municipio]],INDIRECT(Tbla_proyectos[[#This Row],[departamento]]),2,0)) -> 4.3161077 | P27: Continuidad
A28: 2430IINDSBLA-1 | B28: =LEFT(Tbla_proyectos[[#This Row],[codigo_proyecto]],4) -> 2430 | C28: Estrategias para lograr equilibrio económico | D28: Prácticas | E28: Análisis de aspectos organizacionales del colegio para identificar áreas de mejora. Propuesta de acciones estratégicas para lograr el equilibrio económico del colegio. | F28: Gestión de Procesos | G28: Asesoría Técnica y Capacitación | H28: Blanca Elvira Oviedo Torres | K28: =IF(OR(Tbla_proyectos[[#This Row],[fecha_inicio]]="",Tbla_proyectos[[#This Row],[fecha_fin]]=""),"",DATEDIF(Tbla_proyectos[[#This Row],[fecha_inicio]],Tbla_proyectos[[#This Row],[fecha_fin]],"M")) | L28: BOGOTA | M28: BOGOTÁ, D.C. | N28: =IF(Tbla_proyectos[[#This Row],[municipio]]="","",VLOOKUP(Tbla_proyectos[[#This Row],[municipio]],INDIRECT(Tbla_proyectos[[#This Row],[departamento]]),2,0)) -> 4.3161077 | O28: =IF(Tbla_proyectos[[#This Row],[municipio]]="","",VLOOKUP(Tbla_proyectos[[#This Row],[municipio]],INDIRECT(Tbla_proyectos[[#This Row],[departamento]]),2,0)) -> 4.3161077 | P28: Continuidad
A29: 2510IELECJOS-5 | B29: =LEFT(Tbla_proyectos[[#This Row],[codigo_proyecto]],4) -> 2510 | C29: Reparación de Equipos de Computo CSGH | D29: Prácticas | E29: Revisión y reparación de equipos de computo y de sistemas de sonido y audiovisuales. Capacitación en sistemas | F29: Reparación de Electrodomésticos | G29: Asesoría Técnica y Capacitación | H29: José Ignacio Acevedo | K29: =IF(OR(Tbla_proyectos[[#This Row],[fecha_inicio]]="",Tbla_proyectos[[#This Row],[fecha_fin]]=""),"",DATEDIF(Tbla_proyectos[[#This Row],[fecha_inicio]],Tbla_proyectos[[#This Row],[fecha_fin]],"M")) | L29: BOGOTA | M29: BOGOTÁ, D.C. | N29: =IF(Tbla_proyectos[[#This Row],[municipio]]="","",VLOOKUP(Tbla_proyectos[[#This Row],[municipio]],INDIRECT(Tbla_proyectos[[#This Row],[departamento]]),2,0)) -> 4.3161077 | O29: =IF(Tbla_proyectos[[#This Row],[municipio]]="","",VLOOKUP(Tbla_proyectos[[#This Row],[municipio]],INDIRECT(Tbla_proyectos[[#This Row],[departamento]]),2,0)) -> 4.3161077 | P29: Continuidad
A30: 2430IELECJOS-5 | B30: =LEFT(Tbla_proyectos[[#This Row],[codigo_proyecto]],4) -> 2430 | C30: Reparación de Equipos de Computo CSGH | D30: Prácticas | E30: Revisión y reparación de equipos de computo y de sistemas de sonido y audiovisuales. Capacitación en sistemas | F30: Reparación de Electrodomésticos | G30: Asesoría Técnica y Capacitación | H30: José Ignacio Acevedo Gordo | K30: =IF(OR(Tbla_proyectos[[#This Row],[fecha_inicio]]="",Tbla_proyectos[[#This Row],[fecha_fin]]=""),"",DATEDIF(Tbla_proyectos[[#This Row],[fecha_inicio]],Tbla_proyectos[[#This Row],[fecha_fin]],"M")) | L30: BOGOTA | M30: BOGOTÁ, D.C. | N30: =IF(Tbla_proyectos[[#This Row],[municipio]]="","",VLOOKUP(Tbla_proyectos[[#This Row],[municipio]],INDIRECT(Tbla_proyectos[[#This Row],[departamento]]),2,0)) -> 4.3161077 | O30: =IF(Tbla_proyectos[[#This Row],[municipio]]="","",VLOOKUP(Tbla_proyectos[[#This Row],[municipio]],INDIRECT(Tbla_proyectos[[#This Row],[departamento]]),2,0)) -> 4.3161077 | P30: Continuidad
A31: 2510ICIVLLUI-4 | B31: =LEFT(Tbla_proyectos[[#This Row],[codigo_proyecto]],4) -> 2510 | C31: PROYECTO "ALTOS DE LA FLORIDA – SOACHA" | D31: Prácticas | E31: Elaboración de la topografía del sector 3 de Altos de la Florida en Soacha como base para la proyección de las redes de acueducto y alcantarillado. Realización de estudios de estabilidad estructural en casas del barrio Altos de la Florida en la Comuna 6 del municipio de Soacha, Cundinamarca. Definición preliminar de las redes de acueducto y alcantarillado sanitario para el sector 3 de Altos de la Florida en Soacha. | F31: Acueductos Comunitarios | G31: Asesoría Técnica | H31: Luis Alberto Jaramillo Gómez | K31: =IF(OR(Tbla_proyectos[[#This Row],[fecha_inicio]]="",Tbla_proyectos[[#This Row],[fecha_fin]]=""),"",DATEDIF(Tbla_proyectos[[#This Row],[fecha_inicio]],Tbla_proyectos[[#This Row],[fecha_fin]],"M")) | L31: CUNDINAMARCA | M31: SOACHA | N31: =IF(Tbla_proyectos[[#This Row],[municipio]]="","",VLOOKUP(Tbla_proyectos[[#This Row],[municipio]],INDIRECT(Tbla_proyectos[[#This Row],[departamento]]),2,0)) -> 4.5818663 | O31: =IF(Tbla_proyectos[[#This Row],[municipio]]="","",VLOOKUP(Tbla_proyectos[[#This Row],[municipio]],INDIRECT(Tbla_proyectos[[#This Row],[departamento]]),2,0)) -> 4.5818663 | P31: Continuidad
A32: 2430ICIVLLUI-4 | B32: =LEFT(Tbla_proyectos[[#This Row],[codigo_proyecto]],4) -> 2430 | C32: PROYECTO "ALTOS DE LA FLORIDA – SOACHA" | D32: Prácticas | E32: Elaboración de la topografía del sector 3 de Altos de la Florida en Soacha como base para la proyección de las redes de acueducto y alcantarillado. Realización de estudios de estabilidad estructural en casas del barrio Altos de la Florida en la Comuna 6 del municipio de Soacha, Cundinamarca. Definición preliminar de las redes de acueducto y alcantarillado sanitario para el sector 3 de Altos de la Florida en Soacha. | F32: Gestión del Riesgo | G32: Asesoría Técnica | H32: Luis Alberto Jaramillo Gómez | K32: =IF(OR(Tbla_proyectos[[#This Row],[fecha_inicio]]="",Tbla_proyectos[[#This Row],[fecha_fin]]=""),"",DATEDIF(Tbla_proyectos[[#This Row],[fecha_inicio]],Tbla_proyectos[[#This Row],[fecha_fin]],"M")) | L32: CUNDINAMARCA | M32: SOACHA | N32: =IF(Tbla_proyectos[[#This Row],[municipio]]="","",VLOOKUP(Tbla_proyectos[[#This Row],[municipio]],INDIRECT(Tbla_proyectos[[#This Row],[departamento]]),2,0)) -> 4.5818663 | O32: =IF(Tbla_proyectos[[#This Row],[municipio]]="","",VLOOKUP(Tbla_proyectos[[#This Row],[municipio]],INDIRECT(Tbla_proyectos[[#This Row],[departamento]]),2,0)) -> 4.5818663 | P32: Continuidad
A33: 2430ISISTALI-27 | B33: =LEFT(Tbla_proyectos[[#This Row],[codigo_proyecto]],4) -> 2430 | D33: Prácticas | E33: Desarrollo y ejecución de sesiones de capacitación en alfabetización digital. Capacitación con énfasis en herramientas de ofimática. | F33: Capacitación en Ofimática | H33: Alicia Mercedes Arenas Valderrama | K33: =IF(OR(Tbla_proyectos[[#This Row],[fecha_inicio]]="",Tbla_proyectos[[#This Row],[fecha_fin]]=""),"",DATEDIF(Tbla_proyectos[[#This Row],[fecha_inicio]],Tbla_proyectos[[#This Row],[fecha_fin]],"M")) | L33: CUNDINAMARCA | M33: SOACHA | N33: =IF(Tbla_proyectos[[#This Row],[municipio]]="","",VLOOKUP(Tbla_proyectos[[#This Row],[municipio]],INDIRECT(Tbla_proyectos[[#This Row],[departamento]]),2,0)) -> 4.5818663 | O33: =IF(Tbla_proyectos[[#This Row],[municipio]]="","",VLOOKUP(Tbla_proyectos[[#This Row],[municipio]],INDIRECT(Tbla_proyectos[[#This Row],[departamento]]),2,0)) -> 4.5818663
A34: 2510IINDSCLA-5 | B34: =LEFT(Tbla_proyectos[[#This Row],[codigo_proyecto]],4) -> 2510 | D34: Prácticas | E34: Asesoría técnica por medio de reuniones de exploración, entendimiento, evaluación y ejecución de propuestas de proyectos de ingeniería que le ayuden a la entidad a mejorar la gestión de procesos. | F34: Gestión de Procesos | G34: Asesoría Técnica y Capacitación | H34: Clara Mabel Solano Vanegas | K34: =IF(OR(Tbla_proyectos[[#This Row],[fecha_inicio]]="",Tbla_proyectos[[#This Row],[fecha_fin]]=""),"",DATEDIF(Tbla_proyectos[[#This Row],[fecha_inicio]],Tbla_proyectos[[#This Row],[fecha_fin]],"M")) | L34: BOGOTA | M34: BOGOTÁ, D.C. | N34: =IF(Tbla_proyectos[[#This Row],[municipio]]="","",VLOOKUP(Tbla_proyectos[[#This Row],[municipio]],INDIRECT(Tbla_proyectos[[#This Row],[departamento]]),2,0)) -> 4.3161077 | O34: =IF(Tbla_proyectos[[#This Row],[municipio]]="","",VLOOKUP(Tbla_proyectos[[#This Row],[municipio]],INDIRECT(Tbla_proyectos[[#This Row],[departamento]]),2,0)) -> 4.3161077 | P34: Continuidad
A35: 2530IINDSCLA-5 | B35: =LEFT(Tbla_proyectos[[#This Row],[codigo_proyecto]],4) -> 2530 | C35: Mejoramiento procesos alistamiento prendas. | D35: Prácticas | E35: Asesoría técnica por medio de reuniones de exploración, entendimiento, evaluación y ejecución de propuestas de proyectos de ingeniería que le ayuden a la entidad a mejorar la gestión de procesos. | F35: Gestión de Procesos | G35: Asesoría Técnica y Capacitación | H35: Clara Mabel Solano Vanegas | K35: =IF(OR(Tbla_proyectos[[#This Row],[fecha_inicio]]="",Tbla_proyectos[[#This Row],[fecha_fin]]=""),"",DATEDIF(Tbla_proyectos[[#This Row],[fecha_inicio]],Tbla_proyectos[[#This Row],[fecha_fin]],"M")) | L35: BOGOTA | M35: BOGOTÁ, D.C. | N35: =IF(Tbla_proyectos[[#This Row],[municipio]]="","",VLOOKUP(Tbla_proyectos[[#This Row],[municipio]],INDIRECT(Tbla_proyectos[[#This Row],[departamento]]),2,0)) -> 4.3161077 | O35: =IF(Tbla_proyectos[[#This Row],[municipio]]="","",VLOOKUP(Tbla_proyectos[[#This Row],[municipio]],INDIRECT(Tbla_proyectos[[#This Row],[departamento]]),2,0)) -> 4.3161077 | P35: Continuidad
A36: 2430IINDSCLA-5 | B36: =LEFT(Tbla_proyectos[[#This Row],[codigo_proyecto]],4) -> 2430 | D36: Prácticas | E36: Asesoría técnica por medio de reuniones de exploración, entendimiento, evaluación y ejecución de propuestas de proyectos de ingeniería que le ayuden a la entidad a mejorar la gestión de procesos. | F36: Gestión de Procesos | G36: Asesoría Técnica y Capacitación | H36: Clara Mabel Solano Vanegas | K36: =IF(OR(Tbla_proyectos[[#This Row],[fecha_inicio]]="",Tbla_proyectos[[#This Row],[fecha_fin]]=""),"",DATEDIF(Tbla_proyectos[[#This Row],[fecha_inicio]],Tbla_proyectos[[#This Row],[fecha_fin]],"M")) | L36: BOGOTA | M36: BOGOTÁ, D.C. | N36: =IF(Tbla_proyectos[[#This Row],[municipio]]="","",VLOOKUP(Tbla_proyectos[[#This Row],[municipio]],INDIRECT(Tbla_proyectos[[#This Row],[departamento]]),2,0)) -> 4.3161077 | O36: =IF(Tbla_proyectos[[#This Row],[municipio]]="","",VLOOKUP(Tbla_proyectos[[#This Row],[municipio]],INDIRECT(Tbla_proyectos[[#This Row],[departamento]]),2,0)) -> 4.3161077 | P36: Continuidad
A37: 2510BIOINMAR-7 | B37: =LEFT(Tbla_proyectos[[#This Row],[codigo_proyecto]],4) -> 2510 | C37: Proyecto de bioseguridad, información, protocolos y procedimientos | D37: Prácticas | E37: Elaborar, documentar y propopner protocolos de bioseguridad y construcción de procesos y procedimientos | F37: Gestión de Procesos | G37: Asesoría Técnica | H37: Marcela Camargo Pabón | K37: =IF(OR(Tbla_proyectos[[#This Row],[fecha_inicio]]="",Tbla_proyectos[[#This Row],[fecha_fin]]=""),"",DATEDIF(Tbla_proyectos[[#This Row],[fecha_inicio]],Tbla_proyectos[[#This Row],[fecha_fin]],"M")) | L37: BOGOTA | M37: BOGOTÁ, D.C. | N37: =IF(Tbla_proyectos[[#This Row],[municipio]]="","",VLOOKUP(Tbla_proyectos[[#This Row],[municipio]],INDIRECT(Tbla_proyectos[[#This Row],[departamento]]),2,0)) -> 4.3161077 | O37: =IF(Tbla_proyectos[[#This Row],[municipio]]="","",VLOOKUP(Tbla_proyectos[[#This Row],[municipio]],INDIRECT(Tbla_proyectos[[#This Row],[departamento]]),2,0)) -> 4.3161077 | P37: Nuevo
A38: 2510ISISTALI-4 | B38: =LEFT(Tbla_proyectos[[#This Row],[codigo_proyecto]],4) -> 2510 | C38: Proyecto 4 | D38: Prácticas | E38: Desarrollo y mantenimiento de página web. Capacitación en desarrollo web. | F38: Desarrollo Web | G38: Asesoría Técnica y Capacitación | H38: Alicia Mercedes Arenas Valderrama | K38: =IF(OR(Tbla_proyectos[[#This Row],[fecha_inicio]]="",Tbla_proyectos[[#This Row],[fecha_fin]]=""),"",DATEDIF(Tbla_proyectos[[#This Row],[fecha_inicio]],Tbla_proyectos[[#This Row],[fecha_fin]],"M")) | L38: BOGOTA | M38: BOGOTÁ, D.C. | N38: =IF(Tbla_proyectos[[#This Row],[municipio]]="","",VLOOKUP(Tbla_proyectos[[#This Row],[municipio]],INDIRECT(Tbla_proyectos[[#This Row],[departamento]]),2,0)) -> 4.3161077 | O38: =IF(Tbla_proyectos[[#This Row],[municipio]]="","",VLOOKUP(Tbla_proyectos[[#This Row],[municipio]],INDIRECT(Tbla_proyectos[[#This Row],[departamento]]),2,0)) -> 4.3161077
A39: 2530ISISTALI-4 | B39: =LEFT(Tbla_proyectos[[#This Row],[codigo_proyecto]],4) -> 2530 | C39: Proyecto 4 | D39: Prácticas | E39: Desarrollo y mantenimiento de página web. Capacitación en desarrollo web. | F39: Desarrollo Web | G39: Asesoría Técnica y Capacitación | H39: Alicia Mercedes Arenas Valderrama | K39: =IF(OR(Tbla_proyectos[[#This Row],[fecha_inicio]]="",Tbla_proyectos[[#This Row],[fecha_fin]]=""),"",DATEDIF(Tbla_proyectos[[#This Row],[fecha_inicio]],Tbla_proyectos[[#This Row],[fecha_fin]],"M")) | L39: BOGOTA | M39: BOGOTÁ, D.C. | N39: =IF(Tbla_proyectos[[#This Row],[municipio]]="","",VLOOKUP(Tbla_proyectos[[#This Row],[municipio]],INDIRECT(Tbla_proyectos[[#This Row],[departamento]]),2,0)) -> 4.3161077 | O39: =IF(Tbla_proyectos[[#This Row],[municipio]]="","",VLOOKUP(Tbla_proyectos[[#This Row],[municipio]],INDIRECT(Tbla_proyectos[[#This Row],[departamento]]),2,0)) -> 4.3161077
A40: 2430ISISTALI-4 | B40: =LEFT(Tbla_proyectos[[#This Row],[codigo_proyecto]],4) -> 2430 | C40: Proyecto 18 | D40: Prácticas | E40: Desarrollo y mantenimiento de página web. Capacitación en Ofimática | F40: Desarrollo Web | G40: Asesoría Técnica y Capacitación | H40: Alicia Mercedes Arenas Valderrama | K40: =IF(OR(Tbla_proyectos[[#This Row],[fecha_inicio]]="",Tbla_proyectos[[#This Row],[fecha_fin]]=""),"",DATEDIF(Tbla_proyectos[[#This Row],[fecha_inicio]],Tbla_proyectos[[#This Row],[fecha_fin]],"M")) | L40: BOGOTA | M40: BOGOTÁ, D.C. | N40: =IF(Tbla_proyectos[[#This Row],[municipio]]="","",VLOOKUP(Tbla_proyectos[[#This Row],[municipio]],INDIRECT(Tbla_proyectos[[#This Row],[departamento]]),2,0)) -> 4.3161077 | O40: =IF(Tbla_proyectos[[#This Row],[municipio]]="","",VLOOKUP(Tbla_proyectos[[#This Row],[municipio]],INDIRECT(Tbla_proyectos[[#This Row],[departamento]]),2,0)) -> 4.3161077
A41: 2530IELECJOS-7 | B41: =LEFT(Tbla_proyectos[[#This Row],[codigo_proyecto]],4) -> 2530 | C41: Reparación equipos y refuerzo escolar | D41: Prácticas | E41: Revisión y reparación de equipos de computo y de sistemas de sonido y audiovisuales. Refuerzo escular a personas vinculadas a la fundación. | F41: Reparación de Electrodomésticos | G41: Asesoría Técnica y Capacitación | H41: José Ignacio Acevedo Gordo | K41: =IF(OR(Tbla_proyectos[[#This Row],[fecha_inicio]]="",Tbla_proyectos[[#This Row],[fecha_fin]]=""),"",DATEDIF(Tbla_proyectos[[#This Row],[fecha_inicio]],Tbla_proyectos[[#This Row],[fecha_fin]],"M")) | N41: =IF(Tbla_proyectos[[#This Row],[municipio]]="","",VLOOKUP(Tbla_proyectos[[#This Row],[municipio]],INDIRECT(Tbla_proyectos[[#This Row],[departamento]]),2,0)) | O41: =IF(Tbla_proyectos[[#This Row],[municipio]]="","",VLOOKUP(Tbla_proyectos[[#This Row],[municipio]],INDIRECT(Tbla_proyectos[[#This Row],[departamento]]),2,0)) | P41: Nuevo
A42: 2530ISISTALI-7 | B42: =LEFT(Tbla_proyectos[[#This Row],[codigo_proyecto]],4) -> 2530 | C42: Proyecto 7 | D42: Prácticas | E42: Desarrollo y mantenimiento de la página web de VeaS, con asesoría de una experta en comunicaciones. Creación y activación de correos institucionales para la organización. Coordinación y ejecución de talleres con la población de hogares y adultos mayores. | F42: Gestión de Comunicación Digital | G42: Asesoría Técnica y Capacitación | H42: Alicia Mercedes Arenas Valderrama | K42: =IF(OR(Tbla_proyectos[[#This Row],[fecha_inicio]]="",Tbla_proyectos[[#This Row],[fecha_fin]]=""),"",DATEDIF(Tbla_proyectos[[#This Row],[fecha_inicio]],Tbla_proyectos[[#This Row],[fecha_fin]],"M")) | L42: BOGOTA | M42: BOGOTÁ, D.C. | N42: =IF(Tbla_proyectos[[#This Row],[municipio]]="","",VLOOKUP(Tbla_proyectos[[#This Row],[municipio]],INDIRECT(Tbla_proyectos[[#This Row],[departamento]]),2,0)) -> 4.3161077 | O42: =IF(Tbla_proyectos[[#This Row],[municipio]]="","",VLOOKUP(Tbla_proyectos[[#This Row],[municipio]],INDIRECT(Tbla_proyectos[[#This Row],[departamento]]),2,0)) -> 4.3161077
A43: 2530ISISTALI-16 | B43: =LEFT(Tbla_proyectos[[#This Row],[codigo_proyecto]],4) -> 2530 | C43: Proyecto 7 | D43: Prácticas | E43: Aseoria Técnica y capacitación a niños y enfermeras en temas de alfabetización digital | F43: Alfabetización Digital | G43: Asesoría Técnica y Capacitación | H43: Alicia Mercedes Arenas Valderrama | K43: =IF(OR(Tbla_proyectos[[#This Row],[fecha_inicio]]="",Tbla_proyectos[[#This Row],[fecha_fin]]=""),"",DATEDIF(Tbla_proyectos[[#This Row],[fecha_inicio]],Tbla_proyectos[[#This Row],[fecha_fin]],"M")) | L43: BOGOTA | M43: BOGOTÁ, D.C. | N43: =IF(Tbla_proyectos[[#This Row],[municipio]]="","",VLOOKUP(Tbla_proyectos[[#This Row],[municipio]],INDIRECT(Tbla_proyectos[[#This Row],[departamento]]),2,0)) -> 4.3161077 | O43: =IF(Tbla_proyectos[[#This Row],[municipio]]="","",VLOOKUP(Tbla_proyectos[[#This Row],[municipio]],INDIRECT(Tbla_proyectos[[#This Row],[departamento]]),2,0)) -> 4.3161077
A44: 2530BIOINMAR-8 | B44: =LEFT(Tbla_proyectos[[#This Row],[codigo_proyecto]],4) -> 2530 | C44: Diseño y construcción de maetodologías de almacenamiento y empaque de alimentos, distribución y manejo de residuos | D44: Prácticas | E44: Elanorar metodologías aplicabes a la fundación para el almacenamiento y empaque de alimentos a distribuir, con sus respectivas capacitaciones y protocoloes de bioseguridad y manejo de rresiduos | F44: Gestión de Procesos | G44: Asesoría Técnica | H44: Marcela Camargo Pabón | K44: =IF(OR(Tbla_proyectos[[#This Row],[fecha_inicio]]="",Tbla_proyectos[[#This Row],[fecha_fin]]=""),"",DATEDIF(Tbla_proyectos[[#This Row],[fecha_inicio]],Tbla_proyectos[[#This Row],[fecha_fin]],"M")) | L44: BOGOTA | M44: BOGOTÁ, D.C. | N44: =IF(Tbla_proyectos[[#This Row],[municipio]]="","",VLOOKUP(Tbla_proyectos[[#This Row],[municipio]],INDIRECT(Tbla_proyectos[[#This Row],[departamento]]),2,0)) -> 4.3161077 | O44: =IF(Tbla_proyectos[[#This Row],[municipio]]="","",VLOOKUP(Tbla_proyectos[[#This Row],[municipio]],INDIRECT(Tbla_proyectos[[#This Row],[departamento]]),2,0)) -> 4.3161077
A45: 2530ISISTALI-1 | B45: =LEFT(Tbla_proyectos[[#This Row],[codigo_proyecto]],4) -> 2530 | C45: Proyecto 1 | D45: Prácticas | E45: Desarrollo y mantenimiento de la página web de la entidad. Implementación y gestión de estrategias de marketing digital. Configuración y optimización de aplicaciones en Google App. Soporte y administración de la plataforma Salesforce. | F45: Gestión de Comunicación Digital | G45: Asesoría Técnica | H45: Alicia Mercedes Arenas Valderrama | K45: =IF(OR(Tbla_proyectos[[#This Row],[fecha_inicio]]="",Tbla_proyectos[[#This Row],[fecha_fin]]=""),"",DATEDIF(Tbla_proyectos[[#This Row],[fecha_inicio]],Tbla_proyectos[[#This Row],[fecha_fin]],"M")) | L45: BOGOTA | M45: BOGOTÁ, D.C. | N45: =IF(Tbla_proyectos[[#This Row],[municipio]]="","",VLOOKUP(Tbla_proyectos[[#This Row],[municipio]],INDIRECT(Tbla_proyectos[[#This Row],[departamento]]),2,0)) -> 4.3161077 | O45: =IF(Tbla_proyectos[[#This Row],[municipio]]="","",VLOOKUP(Tbla_proyectos[[#This Row],[municipio]],INDIRECT(Tbla_proyectos[[#This Row],[departamento]]),2,0)) -> 4.3161077
A46: 2430ISISTALI-1 | B46: =LEFT(Tbla_proyectos[[#This Row],[codigo_proyecto]],4) -> 2430 | C46: Proyecto 1 | D46: Prácticas | E46: Desarrollo y mantenimiento de la página web de la entidad. Implementación y gestión de estrategias de marketing digital. Configuración y optimización de aplicaciones en Google App. Soporte y administración de la plataforma Salesforce. | F46: Gestión de Comunicación Digital | G46: Asesoría Técnica | H46: Alicia Mercedes Arenas Valderrama | K46: =IF(OR(Tbla_proyectos[[#This Row],[fecha_inicio]]="",Tbla_proyectos[[#This Row],[fecha_fin]]=""),"",DATEDIF(Tbla_proyectos[[#This Row],[fecha_inicio]],Tbla_proyectos[[#This Row],[fecha_fin]],"M")) | L46: BOGOTA | M46: BOGOTÁ, D.C. | N46: =IF(Tbla_proyectos[[#This Row],[municipio]]="","",VLOOKUP(Tbla_proyectos[[#This Row],[municipio]],INDIRECT(Tbla_proyectos[[#This Row],[departamento]]),2,0)) -> 4.3161077 | O46: =IF(Tbla_proyectos[[#This Row],[municipio]]="","",VLOOKUP(Tbla_proyectos[[#This Row],[municipio]],INDIRECT(Tbla_proyectos[[#This Row],[departamento]]),2,0)) -> 4.3161077
A47: 2510ICIVLLUI-2 | B47: =LEFT(Tbla_proyectos[[#This Row],[codigo_proyecto]],4) -> 2510 | C47: PROYECTO "DESARROLLO DE UN SISTEMA DE GESTIÓN DE PUENTES MUNICIPIO DE FACATATIVÁ" | D47: Prácticas | E47: Asesoría técnica para gestión del riesgo y analisis de la calidad del agua una desembocadura de la quebrada de La Mancialla, que presenta escombros por caida de puente. Estudios de calidad de agua de la Vereda La Mancilla Elaboración de manual de uso y glosario del sistema informativo de gestión de puentes (SGP). | F47: Gestión del Agua | G47: Apoyo Técnico | H47: Luis Alberto Jaramillo Gómez | K47: =IF(OR(Tbla_proyectos[[#This Row],[fecha_inicio]]="",Tbla_proyectos[[#This Row],[fecha_fin]]=""),"",DATEDIF(Tbla_proyectos[[#This Row],[fecha_inicio]],Tbla_proyectos[[#This Row],[fecha_fin]],"M")) | L47: CUNDINAMARCA | M47: FACATATIVÁ | N47: =IF(Tbla_proyectos[[#This Row],[municipio]]="","",VLOOKUP(Tbla_proyectos[[#This Row],[municipio]],INDIRECT(Tbla_proyectos[[#This Row],[departamento]]),2,0)) -> 4.8340523 | O47: =IF(Tbla_proyectos[[#This Row],[municipio]]="","",VLOOKUP(Tbla_proyectos[[#This Row],[municipio]],INDIRECT(Tbla_proyectos[[#This Row],[departamento]]),2,0)) -> 4.8340523 | P47: Continuidad
A48: 2510ISISTALI-5 | B48: =LEFT(Tbla_proyectos[[#This Row],[codigo_proyecto]],4) -> 2510 | C48: Proyecto 5 | D48: Prácticas | E48: Desarrollar sesiones de capacitación y enseñanza en el uso de nuevas tecnologías. | F48: Capacitación en Tecnología | G48: Capacitación | H48: Alicia Mercedes Arenas Valderrama | K48: =IF(OR(Tbla_proyectos[[#This Row],[fecha_inicio]]="",Tbla_proyectos[[#This Row],[fecha_fin]]=""),"",DATEDIF(Tbla_proyectos[[#This Row],[fecha_inicio]],Tbla_proyectos[[#This Row],[fecha_fin]],"M")) | L48: BOGOTA | M48: BOGOTÁ, D.C. | N48: =IF(Tbla_proyectos[[#This Row],[municipio]]="","",VLOOKUP(Tbla_proyectos[[#This Row],[municipio]],INDIRECT(Tbla_proyectos[[#This Row],[departamento]]),2,0)) -> 4.3161077 | O48: =IF(Tbla_proyectos[[#This Row],[municipio]]="","",VLOOKUP(Tbla_proyectos[[#This Row],[municipio]],INDIRECT(Tbla_proyectos[[#This Row],[departamento]]),2,0)) -> 4.3161077
A49: 2530ISISTALI-5 | B49: =LEFT(Tbla_proyectos[[#This Row],[codigo_proyecto]],4) -> 2530 | C49: Proyecto 5 | D49: Prácticas | E49: Desarrollar sesiones de capacitación y enseñanza en el uso de nuevas tecnologías. | F49: Capacitación en Tecnología | G49: Capacitación | H49: Alicia Mercedes Arenas Valderrama | K49: =IF(OR(Tbla_proyectos[[#This Row],[fecha_inicio]]="",Tbla_proyectos[[#This Row],[fecha_fin]]=""),"",DATEDIF(Tbla_proyectos[[#This Row],[fecha_inicio]],Tbla_proyectos[[#This Row],[fecha_fin]],"M")) | L49: BOGOTA | M49: BOGOTÁ, D.C. | N49: =IF(Tbla_proyectos[[#This Row],[municipio]]="","",VLOOKUP(Tbla_proyectos[[#This Row],[municipio]],INDIRECT(Tbla_proyectos[[#This Row],[departamento]]),2,0)) -> 4.3161077 | O49: =IF(Tbla_proyectos[[#This Row],[municipio]]="","",VLOOKUP(Tbla_proyectos[[#This Row],[municipio]],INDIRECT(Tbla_proyectos[[#This Row],[departamento]]),2,0)) -> 4.3161077
A50: 2430ISISTALI-5 | B50: =LEFT(Tbla_proyectos[[#This Row],[codigo_proyecto]],4) -> 2430 | C50: Proyecto 2 | D50: Prácticas | E50: Desarrollar sesiones de capacitación y enseñanza en el uso de nuevas tecnologías. | F50: Capacitación en Tecnología | G50: Capacitación | H50: Alicia Mercedes Arenas Valderrama | K50: =IF(OR(Tbla_proyectos[[#This Row],[fecha_inicio]]="",Tbla_proyectos[[#This Row],[fecha_fin]]=""),"",DATEDIF(Tbla_proyectos[[#This Row],[fecha_inicio]],Tbla_proyectos[[#This Row],[fecha_fin]],"M")) | L50: BOGOTA | M50: BOGOTÁ, D.C. | N50: =IF(Tbla_proyectos[[#This Row],[municipio]]="","",VLOOKUP(Tbla_proyectos[[#This Row],[municipio]],INDIRECT(Tbla_proyectos[[#This Row],[departamento]]),2,0)) -> 4.3161077 | O50: =IF(Tbla_proyectos[[#This Row],[municipio]]="","",VLOOKUP(Tbla_proyectos[[#This Row],[municipio]],INDIRECT(Tbla_proyectos[[#This Row],[departamento]]),2,0)) -> 4.3161077
A51: 2510IINDSCLA-4 | B51: =LEFT(Tbla_proyectos[[#This Row],[codigo_proyecto]],4) -> 2510 | D51: Prácticas | E51: Asesoría técnica por medio de reuniones de exploración, entendimiento, evaluación y ejecución de propuestas de proyectos de ingeniería que le ayuden a la entidad a mejorar la gestión de procesos. | F51: Gestión de Procesos | G51: Asesoría Técnica y Capacitación | H51: Clara Mabel Solano Vanegas | K51: =IF(OR(Tbla_proyectos[[#This Row],[fecha_inicio]]="",Tbla_proyectos[[#This Row],[fecha_fin]]=""),"",DATEDIF(Tbla_proyectos[[#This Row],[fecha_inicio]],Tbla_proyectos[[#This Row],[fecha_fin]],"M")) | L51: BOGOTA | M51: BOGOTÁ, D.C. | N51: =IF(Tbla_proyectos[[#This Row],[municipio]]="","",VLOOKUP(Tbla_proyectos[[#This Row],[municipio]],INDIRECT(Tbla_proyectos[[#This Row],[departamento]]),2,0)) -> 4.3161077 | O51: =IF(Tbla_proyectos[[#This Row],[municipio]]="","",VLOOKUP(Tbla_proyectos[[#This Row],[municipio]],INDIRECT(Tbla_proyectos[[#This Row],[departamento]]),2,0)) -> 4.3161077 | P51: Continuidad
A52: 2530IINDSCLA-4 | B52: =LEFT(Tbla_proyectos[[#This Row],[codigo_proyecto]],4) -> 2530 | C52: Mejoramiento procesos alistamiento alimentos. | D52: Prácticas | E52: Asesoría técnica por medio de reuniones de exploración, entendimiento, evaluación y ejecución de propuestas de proyectos de ingeniería que le ayuden a la entidad a mejorar la gestión de procesos. | F52: Gestión de Procesos | G52: Asesoría Técnica y Capacitación | H52: Clara Mabel Solano Vanegas | K52: =IF(OR(Tbla_proyectos[[#This Row],[fecha_inicio]]="",Tbla_proyectos[[#This Row],[fecha_fin]]=""),"",DATEDIF(Tbla_proyectos[[#This Row],[fecha_inicio]],Tbla_proyectos[[#This Row],[fecha_fin]],"M")) | L52: BOGOTA | M52: BOGOTÁ, D.C. | N52: =IF(Tbla_proyectos[[#This Row],[municipio]]="","",VLOOKUP(Tbla_proyectos[[#This Row],[municipio]],INDIRECT(Tbla_proyectos[[#This Row],[departamento]]),2,0)) -> 4.3161077 | O52: =IF(Tbla_proyectos[[#This Row],[municipio]]="","",VLOOKUP(Tbla_proyectos[[#This Row],[municipio]],INDIRECT(Tbla_proyectos[[#This Row],[departamento]]),2,0)) -> 4.3161077 | P52: Continuidad
A53: 2430IINDSCLA-4 | B53: =LEFT(Tbla_proyectos[[#This Row],[codigo_proyecto]],4) -> 2430 | D53: Prácticas | E53: Asesoría técnica por medio de reuniones de exploración, entendimiento, evaluación y ejecución de propuestas de proyectos de ingeniería que le ayuden a la entidad a mejorar la gestión de procesos. | F53: Gestión de Procesos | G53: Asesoría Técnica y Capacitación | H53: Clara Mabel Solano Vanegas | K53: =IF(OR(Tbla_proyectos[[#This Row],[fecha_inicio]]="",Tbla_proyectos[[#This Row],[fecha_fin]]=""),"",DATEDIF(Tbla_proyectos[[#This Row],[fecha_inicio]],Tbla_proyectos[[#This Row],[fecha_fin]],"M")) | L53: BOGOTA | M53: BOGOTÁ, D.C. | N53: =IF(Tbla_proyectos[[#This Row],[municipio]]="","",VLOOKUP(Tbla_proyectos[[#This Row],[municipio]],INDIRECT(Tbla_proyectos[[#This Row],[departamento]]),2,0)) -> 4.3161077 | O53: =IF(Tbla_proyectos[[#This Row],[municipio]]="","",VLOOKUP(Tbla_proyectos[[#This Row],[municipio]],INDIRECT(Tbla_proyectos[[#This Row],[departamento]]),2,0)) -> 4.3161077 | P53: Continuidad
A54: 2510IELECJOS-1 | B54: =LEFT(Tbla_proyectos[[#This Row],[codigo_proyecto]],4) -> 2510 | C54: Reparación de Electrodomésticos BA | D54: Prácticas | E54: Revisión, reparación y selección de electrodomésticos y dispositivos electrónicos. | F54: Reparación de Electrodomésticos | G54: Asesoría Técnica | H54: José Ignacio Acevedo | K54: =IF(OR(Tbla_proyectos[[#This Row],[fecha_inicio]]="",Tbla_proyectos[[#This Row],[fecha_fin]]=""),"",DATEDIF(Tbla_proyectos[[#This Row],[fecha_inicio]],Tbla_proyectos[[#This Row],[fecha_fin]],"M")) | L54: BOGOTA | M54: BOGOTÁ, D.C. | N54: =IF(Tbla_proyectos[[#This Row],[municipio]]="","",VLOOKUP(Tbla_proyectos[[#This Row],[municipio]],INDIRECT(Tbla_proyectos[[#This Row],[departamento]]),2,0)) -> 4.3161077 | O54: =IF(Tbla_proyectos[[#This Row],[municipio]]="","",VLOOKUP(Tbla_proyectos[[#This Row],[municipio]],INDIRECT(Tbla_proyectos[[#This Row],[departamento]]),2,0)) -> 4.3161077 | P54: Continuidad
A55: 2530IELECJOS-1 | B55: =LEFT(Tbla_proyectos[[#This Row],[codigo_proyecto]],4) -> 2530 | C55: Reparación de Electrodomésticos BA | D55: Prácticas | E55: Revisión, reparación y selección de electrodomésticos y dispositivos electrónicos. | F55: Reparación de Electrodomésticos | G55: Asesoría Técnica | H55: José Ignacio Acevedo Gordo | K55: =IF(OR(Tbla_proyectos[[#This Row],[fecha_inicio]]="",Tbla_proyectos[[#This Row],[fecha_fin]]=""),"",DATEDIF(Tbla_proyectos[[#This Row],[fecha_inicio]],Tbla_proyectos[[#This Row],[fecha_fin]],"M")) | L55: BOGOTA | M55: BOGOTÁ, D.C. | N55: =IF(Tbla_proyectos[[#This Row],[municipio]]="","",VLOOKUP(Tbla_proyectos[[#This Row],[municipio]],INDIRECT(Tbla_proyectos[[#This Row],[departamento]]),2,0)) -> 4.3161077 | O55: =IF(Tbla_proyectos[[#This Row],[municipio]]="","",VLOOKUP(Tbla_proyectos[[#This Row],[municipio]],INDIRECT(Tbla_proyectos[[#This Row],[departamento]]),2,0)) -> 4.3161077 | P55: Continuidad
A56: 2430IELECJOS-1 | B56: =LEFT(Tbla_proyectos[[#This Row],[codigo_proyecto]],4) -> 2430 | C56: Reparación de Electrodomésticos BA | D56: Prácticas | E56: Revisión, reparación y selección de electrodomésticos y dispositivos electrónicos. | F56: Reparación de Electrodomésticos | G56: Asesoría Técnica | H56: José Ignacio Acevedo Gordo | K56: =IF(OR(Tbla_proyectos[[#This Row],[fecha_inicio]]="",Tbla_proyectos[[#This Row],[fecha_fin]]=""),"",DATEDIF(Tbla_proyectos[[#This Row],[fecha_inicio]],Tbla_proyectos[[#This Row],[fecha_fin]],"M")) | L56: BOGOTA | M56: BOGOTÁ, D.C. | N56: =IF(Tbla_proyectos[[#This Row],[municipio]]="","",VLOOKUP(Tbla_proyectos[[#This Row],[municipio]],INDIRECT(Tbla_proyectos[[#This Row],[departamento]]),2,0)) -> 4.3161077 | O56: =IF(Tbla_proyectos[[#This Row],[municipio]]="","",VLOOKUP(Tbla_proyectos[[#This Row],[municipio]],INDIRECT(Tbla_proyectos[[#This Row],[departamento]]),2,0)) -> 4.3161077 | P56: Continuidad
A57: 2510BIOINMAR-5 | B57: =LEFT(Tbla_proyectos[[#This Row],[codigo_proyecto]],4) -> 2510 | C57: Clasificación y actualización de equipos y construcción de hojas técnicas | D57: Prácticas | E57: Construcción, clasificación y actualización de equipos, automoviles de la funcación como la construcción de hojas técnicas de los mismos. | G57: Asesoría Técnica y Capacitación | H57: Marcela Camargo Pabón | K57: =IF(OR(Tbla_proyectos[[#This Row],[fecha_inicio]]="",Tbla_proyectos[[#This Row],[fecha_fin]]=""),"",DATEDIF(Tbla_proyectos[[#This Row],[fecha_inicio]],Tbla_proyectos[[#This Row],[fecha_fin]],"M")) | L57: BOGOTA | M57: BOGOTÁ, D.C. | N57: =IF(Tbla_proyectos[[#This Row],[municipio]]="","",VLOOKUP(Tbla_proyectos[[#This Row],[municipio]],INDIRECT(Tbla_proyectos[[#This Row],[departamento]]),2,0)) -> 4.3161077 | O57: =IF(Tbla_proyectos[[#This Row],[municipio]]="","",VLOOKUP(Tbla_proyectos[[#This Row],[municipio]],INDIRECT(Tbla_proyectos[[#This Row],[departamento]]),2,0)) -> 4.3161077 | P57: Continuidad
A58: 2530BIOINMAR-5 | B58: =LEFT(Tbla_proyectos[[#This Row],[codigo_proyecto]],4) -> 2530 | C58: Elaboración y análisis de compostaje | D58: Prácticas | E58: Elaboración de pruebas de compostaje para residuos y análisis para la aplicación e implementación de diferentes comuniddades donde el banco de alimentos tiene presencia . | F58: Gestión de Residuos | G58: Asesoría Técnica y Capacitación | H58: Marcela Camargo Pabón | K58: =IF(OR(Tbla_proyectos[[#This Row],[fecha_inicio]]="",Tbla_proyectos[[#This Row],[fecha_fin]]=""),"",DATEDIF(Tbla_proyectos[[#This Row],[fecha_inicio]],Tbla_proyectos[[#This Row],[fecha_fin]],"M")) | L58: BOGOTA | M58: BOGOTÁ, D.C. | N58: =IF(Tbla_proyectos[[#This Row],[municipio]]="","",VLOOKUP(Tbla_proyectos[[#This Row],[municipio]],INDIRECT(Tbla_proyectos[[#This Row],[departamento]]),2,0)) -> 4.3161077 | O58: =IF(Tbla_proyectos[[#This Row],[municipio]]="","",VLOOKUP(Tbla_proyectos[[#This Row],[municipio]],INDIRECT(Tbla_proyectos[[#This Row],[departamento]]),2,0)) -> 4.3161077 | P58: Continuidad
A59: 2530IMECAMAR-5 | B59: =LEFT(Tbla_proyectos[[#This Row],[codigo_proyecto]],4) -> 2530 | C59: Diseño de equipos y elaboración de proptotipos con sus hojas técnicas | D59: Prácticas | E59: Diesño de equipos y elaboración de prototipos con sus respectivas cotizaciones y planos para su uso y optimización de recursos | F59: Diseño Mecánico | G59: Asesoría Técnica y Capacitación | H59: Marcela Camargo Pabón | K59: =IF(OR(Tbla_proyectos[[#This Row],[fecha_inicio]]="",Tbla_proyectos[[#This Row],[fecha_fin]]=""),"",DATEDIF(Tbla_proyectos[[#This Row],[fecha_inicio]],Tbla_proyectos[[#This Row],[fecha_fin]],"M")) | L59: BOGOTA | M59: BOGOTÁ, D.C. | N59: =IF(Tbla_proyectos[[#This Row],[municipio]]="","",VLOOKUP(Tbla_proyectos[[#This Row],[municipio]],INDIRECT(Tbla_proyectos[[#This Row],[departamento]]),2,0)) -> 4.3161077 | O59: =IF(Tbla_proyectos[[#This Row],[municipio]]="","",VLOOKUP(Tbla_proyectos[[#This Row],[municipio]],INDIRECT(Tbla_proyectos[[#This Row],[departamento]]),2,0)) -> 4.3161077 | P59: Continuidad
A60: 2430IMECAMAR-5 | B60: =LEFT(Tbla_proyectos[[#This Row],[codigo_proyecto]],4) -> 2430 | C60: Proyecto 5 | D60: Prácticas | E60: Elaboración instructivos (manuales) para el uso y mantenimiento de estibadores hidráulicos. Planeación y ejecución de mantenimientos preventivos de estibadores hidráulicos. Capacitación al personal sobre el manejo y mantenimiento de estibadores hidráulicos. | F60: Procesos y Producción | G60: Asesoría Técnica y Capacitación | H60: Marcela Camargo Pabón | K60: =IF(OR(Tbla_proyectos[[#This Row],[fecha_inicio]]="",Tbla_proyectos[[#This Row],[fecha_fin]]=""),"",DATEDIF(Tbla_proyectos[[#This Row],[fecha_inicio]],Tbla_proyectos[[#This Row],[fecha_fin]],"M")) | L60: BOGOTA | M60: BOGOTÁ, D.C. | N60: =IF(Tbla_proyectos[[#This Row],[municipio]]="","",VLOOKUP(Tbla_proyectos[[#This Row],[municipio]],INDIRECT(Tbla_proyectos[[#This Row],[departamento]]),2,0)) -> 4.3161077 | O60: =IF(Tbla_proyectos[[#This Row],[municipio]]="","",VLOOKUP(Tbla_proyectos[[#This Row],[municipio]],INDIRECT(Tbla_proyectos[[#This Row],[departamento]]),2,0)) -> 4.3161077 | P60: Nuevo
A61: 2520IELECJOS-1 | B61: =LEFT(Tbla_proyectos[[#This Row],[codigo_proyecto]],4) -> 2520 | C61: Reparación de Electrodomésticos BA | D61: Prácticas | E61: Revisión, reparación y selección de electrodomésticos y dispositivos electrónicos. | F61: Reparación de Electrodomésticos | G61: Asesoría Técnica | H61: Cristian Camilo León Bohorquez | K61: =IF(OR(Tbla_proyectos[[#This Row],[fecha_inicio]]="",Tbla_proyectos[[#This Row],[fecha_fin]]=""),"",DATEDIF(Tbla_proyectos[[#This Row],[fecha_inicio]],Tbla_proyectos[[#This Row],[fecha_fin]],"M")) | L61: BOGOTA | M61: BOGOTÁ, D.C. | N61: =IF(Tbla_proyectos[[#This Row],[municipio]]="","",VLOOKUP(Tbla_proyectos[[#This Row],[municipio]],INDIRECT(Tbla_proyectos[[#This Row],[departamento]]),2,0)) -> 4.3161077 | O61: =IF(Tbla_proyectos[[#This Row],[municipio]]="","",VLOOKUP(Tbla_proyectos[[#This Row],[municipio]],INDIRECT(Tbla_proyectos[[#This Row],[departamento]]),2,0)) -> 4.3161077 | P61: Continuidad
A62: 2510ISISTALI-6 | B62: =LEFT(Tbla_proyectos[[#This Row],[codigo_proyecto]],4) -> 2510 | C62: Proyecto 6 | D62: Prácticas | E62: Desarllo web y gestión de redes sociales | F62: Desarrollo Web + Gestión de Comunicación Digital | G62: Asesoría Técnica | H62: Alicia Mercedes Arenas Valderrama | K62: =IF(OR(Tbla_proyectos[[#This Row],[fecha_inicio]]="",Tbla_proyectos[[#This Row],[fecha_fin]]=""),"",DATEDIF(Tbla_proyectos[[#This Row],[fecha_inicio]],Tbla_proyectos[[#This Row],[fecha_fin]],"M")) | L62: BOGOTA | M62: BOGOTÁ, D.C. | N62: =IF(Tbla_proyectos[[#This Row],[municipio]]="","",VLOOKUP(Tbla_proyectos[[#This Row],[municipio]],INDIRECT(Tbla_proyectos[[#This Row],[departamento]]),2,0)) -> 4.3161077 | O62: =IF(Tbla_proyectos[[#This Row],[municipio]]="","",VLOOKUP(Tbla_proyectos[[#This Row],[municipio]],INDIRECT(Tbla_proyectos[[#This Row],[departamento]]),2,0)) -> 4.3161077
A63: 2530ISISTALI-6 | B63: =LEFT(Tbla_proyectos[[#This Row],[codigo_proyecto]],4) -> 2530 | C63: Proyecto 6 | D63: Prácticas | E63: Desarllo web y gestión de redes sociales | F63: Desarrollo Web + Gestión de Comunicación Digital | G63: Asesoría Técnica | H63: Alicia Mercedes Arenas Valderrama | K63: =IF(OR(Tbla_proyectos[[#This Row],[fecha_inicio]]="",Tbla_proyectos[[#This Row],[fecha_fin]]=""),"",DATEDIF(Tbla_proyectos[[#This Row],[fecha_inicio]],Tbla_proyectos[[#This Row],[fecha_fin]],"M")) | L63: BOGOTA | M63: BOGOTÁ, D.C. | N63: =IF(Tbla_proyectos[[#This Row],[municipio]]="","",VLOOKUP(Tbla_proyectos[[#This Row],[municipio]],INDIRECT(Tbla_proyectos[[#This Row],[departamento]]),2,0)) -> 4.3161077 | O63: =IF(Tbla_proyectos[[#This Row],[municipio]]="","",VLOOKUP(Tbla_proyectos[[#This Row],[municipio]],INDIRECT(Tbla_proyectos[[#This Row],[departamento]]),2,0)) -> 4.3161077
A64: 2430ISISTALI-6 | B64: =LEFT(Tbla_proyectos[[#This Row],[codigo_proyecto]],4) -> 2430 | C64: Proyecto 5 | D64: Prácticas | E64: Desarllo web y gestión de redes sociales | F64: Desarrollo Web + Gestión de Comunicación Digital | G64: Asesoría Técnica | H64: Alicia Mercedes Arenas Valderrama | K64: =IF(OR(Tbla_proyectos[[#This Row],[fecha_inicio]]="",Tbla_proyectos[[#This Row],[fecha_fin]]=""),"",DATEDIF(Tbla_proyectos[[#This Row],[fecha_inicio]],Tbla_proyectos[[#This Row],[fecha_fin]],"M")) | L64: BOGOTA | M64: BOGOTÁ, D.C. | N64: =IF(Tbla_proyectos[[#This Row],[municipio]]="","",VLOOKUP(Tbla_proyectos[[#This Row],[municipio]],INDIRECT(Tbla_proyectos[[#This Row],[departamento]]),2,0)) -> 4.3161077 | O64: =IF(Tbla_proyectos[[#This Row],[municipio]]="","",VLOOKUP(Tbla_proyectos[[#This Row],[municipio]],INDIRECT(Tbla_proyectos[[#This Row],[departamento]]),2,0)) -> 4.3161077
A65: 2510BIOINMAR-3 | B65: =LEFT(Tbla_proyectos[[#This Row],[codigo_proyecto]],4) -> 2510 | C65: Diseño y construcción de sistemas digitale, visuales y manuales para audiometría | D65: Prácticas | E65: Diseño y construcción de sistemas digitales, visuales y manuales para la realización y evaluación de pruebas audiométricas. | F65: Tecnologías de Asistencia | G65: Asesoría Técnica | H65: Marcela Camargo Pabón | K65: =IF(OR(Tbla_proyectos[[#This Row],[fecha_inicio]]="",Tbla_proyectos[[#This Row],[fecha_fin]]=""),"",DATEDIF(Tbla_proyectos[[#This Row],[fecha_inicio]],Tbla_proyectos[[#This Row],[fecha_fin]],"M")) | L65: BOGOTA | M65: BOGOTÁ, D.C. | N65: =IF(Tbla_proyectos[[#This Row],[municipio]]="","",VLOOKUP(Tbla_proyectos[[#This Row],[municipio]],INDIRECT(Tbla_proyectos[[#This Row],[departamento]]),2,0)) -> 4.3161077 | O65: =IF(Tbla_proyectos[[#This Row],[municipio]]="","",VLOOKUP(Tbla_proyectos[[#This Row],[municipio]],INDIRECT(Tbla_proyectos[[#This Row],[departamento]]),2,0)) -> 4.3161077 | P65: Continuidad
A66: 2530IELECJOS-9 | B66: =LEFT(Tbla_proyectos[[#This Row],[codigo_proyecto]],4) -> 2530 | C66: Diseño y construcción de sistemas digitale, visuales y manuales para audiometría | D66: Prácticas | E66: Diseño y construcción de sistemas digitales, visuales y manuales para la realización y evaluación de pruebas audiométricas. | F66: Tecnologías de Asistencia | G66: Asesoría Técnica | H66: José Ignacio Acevedo Gordo | K66: =IF(OR(Tbla_proyectos[[#This Row],[fecha_inicio]]="",Tbla_proyectos[[#This Row],[fecha_fin]]=""),"",DATEDIF(Tbla_proyectos[[#This Row],[fecha_inicio]],Tbla_proyectos[[#This Row],[fecha_fin]],"M")) | L66: BOGOTA | M66: BOGOTÁ, D.C. | N66: =IF(Tbla_proyectos[[#This Row],[municipio]]="","",VLOOKUP(Tbla_proyectos[[#This Row],[municipio]],INDIRECT(Tbla_proyectos[[#This Row],[departamento]]),2,0)) -> 4.3161077 | O66: =IF(Tbla_proyectos[[#This Row],[municipio]]="","",VLOOKUP(Tbla_proyectos[[#This Row],[municipio]],INDIRECT(Tbla_proyectos[[#This Row],[departamento]]),2,0)) -> 4.3161077 | P66: Continuidad
A67: 2530BIOINMAR-3 | B67: =LEFT(Tbla_proyectos[[#This Row],[codigo_proyecto]],4) -> 2530 | C67: Diseño y construcción de sistemas digitale, visuales y manuales para audiometría | D67: Prácticas | E67: Diseño y construcción de sistemas digitales, visuales y manuales para la realización y evaluación de pruebas audiométricas. | F67: Tecnologías de Asistencia | G67: Asesoría Técnica | H67: Marcela Camargo Pabón | K67: =IF(OR(Tbla_proyectos[[#This Row],[fecha_inicio]]="",Tbla_proyectos[[#This Row],[fecha_fin]]=""),"",DATEDIF(Tbla_proyectos[[#This Row],[fecha_inicio]],Tbla_proyectos[[#This Row],[fecha_fin]],"M")) | L67: BOGOTA | M67: BOGOTÁ, D.C. | N67: =IF(Tbla_proyectos[[#This Row],[municipio]]="","",VLOOKUP(Tbla_proyectos[[#This Row],[municipio]],INDIRECT(Tbla_proyectos[[#This Row],[departamento]]),2,0)) -> 4.3161077 | O67: =IF(Tbla_proyectos[[#This Row],[municipio]]="","",VLOOKUP(Tbla_proyectos[[#This Row],[municipio]],INDIRECT(Tbla_proyectos[[#This Row],[departamento]]),2,0)) -> 4.3161077 | P67: Continuidad
A68: 2430IMECAMAR-3 | B68: =LEFT(Tbla_proyectos[[#This Row],[codigo_proyecto]],4) -> 2430 | C68: Diseño y construcción de sistemas digitale, visuales y manuales para audiometría | D68: Prácticas | E68: Diseño y construcción de sistemas digitales, visuales y manuales para la realización y evaluación de pruebas audiométricas. | F68: Tecnologías de Asistencia | G68: Asesoría Técnica | H68: Marcela Camargo Pabón | K68: =IF(OR(Tbla_proyectos[[#This Row],[fecha_inicio]]="",Tbla_proyectos[[#This Row],[fecha_fin]]=""),"",DATEDIF(Tbla_proyectos[[#This Row],[fecha_inicio]],Tbla_proyectos[[#This Row],[fecha_fin]],"M")) | L68: BOGOTA | M68: BOGOTÁ, D.C. | N68: =IF(Tbla_proyectos[[#This Row],[municipio]]="","",VLOOKUP(Tbla_proyectos[[#This Row],[municipio]],INDIRECT(Tbla_proyectos[[#This Row],[departamento]]),2,0)) -> 4.3161077 | O68: =IF(Tbla_proyectos[[#This Row],[municipio]]="","",VLOOKUP(Tbla_proyectos[[#This Row],[municipio]],INDIRECT(Tbla_proyectos[[#This Row],[departamento]]),2,0)) -> 4.3161077 | P68: Continuidad
A69: 2430BIOINMAR-3 | B69: =LEFT(Tbla_proyectos[[#This Row],[codigo_proyecto]],4) -> 2430 | C69: Diseño y construcción de sistemas digitale, visuales y manuales para audiometría | D69: Prácticas | E69: Diseño y construcción de sistemas digitales, visuales y manuales para la realización y evaluación de pruebas audiométricas. | F69: Tecnologías de Asistencia | G69: Asesoría Técnica | H69: Marcela Camargo Pabón | K69: =IF(OR(Tbla_proyectos[[#This Row],[fecha_inicio]]="",Tbla_proyectos[[#This Row],[fecha_fin]]=""),"",DATEDIF(Tbla_proyectos[[#This Row],[fecha_inicio]],Tbla_proyectos[[#This Row],[fecha_fin]],"M")) | L69: BOGOTA | M69: BOGOTÁ, D.C. | N69: =IF(Tbla_proyectos[[#This Row],[municipio]]="","",VLOOKUP(Tbla_proyectos[[#This Row],[municipio]],INDIRECT(Tbla_proyectos[[#This Row],[departamento]]),2,0)) -> 4.3161077 | O69: =IF(Tbla_proyectos[[#This Row],[municipio]]="","",VLOOKUP(Tbla_proyectos[[#This Row],[municipio]],INDIRECT(Tbla_proyectos[[#This Row],[departamento]]),2,0)) -> 4.3161077 | P69: Continuidad
A70: 2510ISISTALI-7 | B70: =LEFT(Tbla_proyectos[[#This Row],[codigo_proyecto]],4) -> 2510 | C70: Proyecto 7 | D70: Prácticas | E70: Desarrollo y mantenimiento de la página web de VeaS, con asesoría de una experta en comunicaciones. Creación y activación de correos institucionales para la organización. Coordinación y ejecución de talleres con la población de hogares y adultos mayores. | F70: Gestión de Comunicación Digital | G70: Asesoría Técnica y Capacitación | H70: Alicia Mercedes Arenas Valderrama | K70: =IF(OR(Tbla_proyectos[[#This Row],[fecha_inicio]]="",Tbla_proyectos[[#This Row],[fecha_fin]]=""),"",DATEDIF(Tbla_proyectos[[#This Row],[fecha_inicio]],Tbla_proyectos[[#This Row],[fecha_fin]],"M")) | L70: BOGOTA | M70: BOGOTÁ, D.C. | N70: =IF(Tbla_proyectos[[#This Row],[municipio]]="","",VLOOKUP(Tbla_proyectos[[#This Row],[municipio]],INDIRECT(Tbla_proyectos[[#This Row],[departamento]]),2,0)) -> 4.3161077 | O70: =IF(Tbla_proyectos[[#This Row],[municipio]]="","",VLOOKUP(Tbla_proyectos[[#This Row],[municipio]],INDIRECT(Tbla_proyectos[[#This Row],[departamento]]),2,0)) -> 4.3161077
A71: 2430ISISTALI-7 | B71: =LEFT(Tbla_proyectos[[#This Row],[codigo_proyecto]],4) -> 2430 | C71: Proyecto 6 | D71: Prácticas | E71: Desarrollo y mantenimiento de la página web de VeaS, con asesoría de una experta en comunicaciones. Creación y activación de correos institucionales para la organización. Coordinación y ejecución de talleres con la población de hogares y adultos mayores. | F71: Gestión de Comunicación Digital | G71: Asesoría Técnica y Capacitación | H71: Alicia Mercedes Arenas Valderrama | K71: =IF(OR(Tbla_proyectos[[#This Row],[fecha_inicio]]="",Tbla_proyectos[[#This Row],[fecha_fin]]=""),"",DATEDIF(Tbla_proyectos[[#This Row],[fecha_inicio]],Tbla_proyectos[[#This Row],[fecha_fin]],"M")) | L71: BOGOTA | M71: BOGOTÁ, D.C. | N71: =IF(Tbla_proyectos[[#This Row],[municipio]]="","",VLOOKUP(Tbla_proyectos[[#This Row],[municipio]],INDIRECT(Tbla_proyectos[[#This Row],[departamento]]),2,0)) -> 4.3161077 | O71: =IF(Tbla_proyectos[[#This Row],[municipio]]="","",VLOOKUP(Tbla_proyectos[[#This Row],[municipio]],INDIRECT(Tbla_proyectos[[#This Row],[departamento]]),2,0)) -> 4.3161077
A72: 2510IELECJOS-7 | B72: =LEFT(Tbla_proyectos[[#This Row],[codigo_proyecto]],4) -> 2510 | C72: Reparación equipos y refuerzo escolar | D72: Prácticas | E72: Revisión y reparación de equipos de computo. Refuerzo escular a personas vinculadas a la fundación. | F72: Reparación de Electrodomésticos + Desarrollo Educativo | G72: Asesoría Técnica y Capacitación | H72: José Ignacio Acevedo | K72: =IF(OR(Tbla_proyectos[[#This Row],[fecha_inicio]]="",Tbla_proyectos[[#This Row],[fecha_fin]]=""),"",DATEDIF(Tbla_proyectos[[#This Row],[fecha_inicio]],Tbla_proyectos[[#This Row],[fecha_fin]],"M")) | N72: =IF(Tbla_proyectos[[#This Row],[municipio]]="","",VLOOKUP(Tbla_proyectos[[#This Row],[municipio]],INDIRECT(Tbla_proyectos[[#This Row],[departamento]]),2,0)) | O72: =IF(Tbla_proyectos[[#This Row],[municipio]]="","",VLOOKUP(Tbla_proyectos[[#This Row],[municipio]],INDIRECT(Tbla_proyectos[[#This Row],[departamento]]),2,0)) | P72: Nuevo
A73: 2430ICIVLLUI-2 | B73: =LEFT(Tbla_proyectos[[#This Row],[codigo_proyecto]],4) -> 2430 | C73: PROYECTO "DESARROLLO DE UN SISTEMA DE GESTIÓN DE PUENTES MUNICIPIO DE FACATATIVÁ" | D73: Prácticas | E73: Puesta a prueba y alimentación del sistema de gestión de puentes para municipios; prueba piloto en el municipio de Facatativá. | F73: Sistemas de Información | G73: Apoyo Técnico | H73: Luis Alberto Jaramillo Gómez | K73: =IF(OR(Tbla_proyectos[[#This Row],[fecha_inicio]]="",Tbla_proyectos[[#This Row],[fecha_fin]]=""),"",DATEDIF(Tbla_proyectos[[#This Row],[fecha_inicio]],Tbla_proyectos[[#This Row],[fecha_fin]],"M")) | L73: CUNDINAMARCA | M73: Facatativá | N73: =IF(Tbla_proyectos[[#This Row],[municipio]]="","",VLOOKUP(Tbla_proyectos[[#This Row],[municipio]],INDIRECT(Tbla_proyectos[[#This Row],[departamento]]),2,0)) -> 4.8340523 | O73: =IF(Tbla_proyectos[[#This Row],[municipio]]="","",VLOOKUP(Tbla_proyectos[[#This Row],[municipio]],INDIRECT(Tbla_proyectos[[#This Row],[departamento]]),2,0)) -> 4.8340523 | P73: Continuidad
A74: 2510IINDSCLA-6 | B74: =LEFT(Tbla_proyectos[[#This Row],[codigo_proyecto]],4) -> 2510 | D74: Prácticas | E74: Asesoría técnica por medio de reuniones de exploración, entendimiento, evaluación y ejecución de propuestas de proyectos de ingeniería que le ayuden a la entidad a mejorar la gestión de procesos. | F74: Gestión de Procesos | G74: Asesoría Técnica y Capacitación | H74: Clara Mabel Solano Vanegas | K74: =IF(OR(Tbla_proyectos[[#This Row],[fecha_inicio]]="",Tbla_proyectos[[#This Row],[fecha_fin]]=""),"",DATEDIF(Tbla_proyectos[[#This Row],[fecha_inicio]],Tbla_proyectos[[#This Row],[fecha_fin]],"M")) | L74: BOGOTA | M74: BOGOTÁ, D.C. | N74: =IF(Tbla_proyectos[[#This Row],[municipio]]="","",VLOOKUP(Tbla_proyectos[[#This Row],[municipio]],INDIRECT(Tbla_proyectos[[#This Row],[departamento]]),2,0)) -> 4.3161077 | O74: =IF(Tbla_proyectos[[#This Row],[municipio]]="","",VLOOKUP(Tbla_proyectos[[#This Row],[municipio]],INDIRECT(Tbla_proyectos[[#This Row],[departamento]]),2,0)) -> 4.3161077 | P74: Continuidad
A75: 2430IINDSCLA-6 | B75: =LEFT(Tbla_proyectos[[#This Row],[codigo_proyecto]],4) -> 2430 | D75: Prácticas | E75: Asesoría técnica por medio de reuniones de exploración, entendimiento, evaluación y ejecución de propuestas de proyectos de ingeniería que le ayuden a la entidad a mejorar la gestión de procesos. | F75: Gestión de Procesos | G75: Asesoría Técnica y Capacitación | H75: Clara Mabel Solano Vanegas | K75: =IF(OR(Tbla_proyectos[[#This Row],[fecha_inicio]]="",Tbla_proyectos[[#This Row],[fecha_fin]]=""),"",DATEDIF(Tbla_proyectos[[#This Row],[fecha_inicio]],Tbla_proyectos[[#This Row],[fecha_fin]],"M")) | L75: BOGOTA | M75: BOGOTÁ, D.C. | N75: =IF(Tbla_proyectos[[#This Row],[municipio]]="","",VLOOKUP(Tbla_proyectos[[#This Row],[municipio]],INDIRECT(Tbla_proyectos[[#This Row],[departamento]]),2,0)) -> 4.3161077 | O75: =IF(Tbla_proyectos[[#This Row],[municipio]]="","",VLOOKUP(Tbla_proyectos[[#This Row],[municipio]],INDIRECT(Tbla_proyectos[[#This Row],[departamento]]),2,0)) -> 4.3161077 | P75: Continuidad
A76: 2510ISISTJUA-1 | B76: =LEFT(Tbla_proyectos[[#This Row],[codigo_proyecto]],4) -> 2510 | C76: Proyecto 20 | D76: Prácticas | E76: Desarrollo y ejecución de sesiones de capacitación en emprendimiento con enfoque en la gestión de la información. | F76: Capacitación en Procesos y Emprendimiento + Gestión de Información | G76: Capacitación | H76: Juan Felipe Salcedo | K76: =IF(OR(Tbla_proyectos[[#This Row],[fecha_inicio]]="",Tbla_proyectos[[#This Row],[fecha_fin]]=""),"",DATEDIF(Tbla_proyectos[[#This Row],[fecha_inicio]],Tbla_proyectos[[#This Row],[fecha_fin]],"M")) | L76: BOGOTA | M76: BOGOTÁ, D.C. | N76: =IF(Tbla_proyectos[[#This Row],[municipio]]="","",VLOOKUP(Tbla_proyectos[[#This Row],[municipio]],INDIRECT(Tbla_proyectos[[#This Row],[departamento]]),2,0)) -> 4.3161077 | O76: =IF(Tbla_proyectos[[#This Row],[municipio]]="","",VLOOKUP(Tbla_proyectos[[#This Row],[municipio]],INDIRECT(Tbla_proyectos[[#This Row],[departamento]]),2,0)) -> 4.3161077 | P76: Continuidad
A77: 2430ISISTALI-8 | B77: =LEFT(Tbla_proyectos[[#This Row],[codigo_proyecto]],4) -> 2430 | C77: Proyecto 20 | D77: Prácticas | E77: Desarrollo y ejecución de sesiones de capacitación en emprendimiento con enfoque en la gestión de la información. | F77: Capacitación en Procesos y Emprendimiento + Gestión de Información | G77: Capacitación | H77: Alicia Mercedes Arenas Valderrama | K77: =IF(OR(Tbla_proyectos[[#This Row],[fecha_inicio]]="",Tbla_proyectos[[#This Row],[fecha_fin]]=""),"",DATEDIF(Tbla_proyectos[[#This Row],[fecha_inicio]],Tbla_proyectos[[#This Row],[fecha_fin]],"M")) | L77: BOGOTA | M77: BOGOTÁ, D.C. | N77: =IF(Tbla_proyectos[[#This Row],[municipio]]="","",VLOOKUP(Tbla_proyectos[[#This Row],[municipio]],INDIRECT(Tbla_proyectos[[#This Row],[departamento]]),2,0)) -> 4.3161077 | O77: =IF(Tbla_proyectos[[#This Row],[municipio]]="","",VLOOKUP(Tbla_proyectos[[#This Row],[municipio]],INDIRECT(Tbla_proyectos[[#This Row],[departamento]]),2,0)) -> 4.3161077
A78: 2430ISISTALI-9 | B78: =LEFT(Tbla_proyectos[[#This Row],[codigo_proyecto]],4) -> 2430 | C78: Proyecto 13 | D78: Prácticas | E78: Desarrollo y mantenimiento de aplicaciones web. Gestión y optimización de redes sociales. Implementación de estrategias de mercadeo digital. | F78: Desarrollo Web + Gestión de Comunicación Digital | G78: Asesoría Técnica | H78: Alicia Mercedes Arenas Valderrama | K78: =IF(OR(Tbla_proyectos[[#This Row],[fecha_inicio]]="",Tbla_proyectos[[#This Row],[fecha_fin]]=""),"",DATEDIF(Tbla_proyectos[[#This Row],[fecha_inicio]],Tbla_proyectos[[#This Row],[fecha_fin]],"M")) | L78: BOGOTA | M78: BOGOTÁ, D.C. | N78: =IF(Tbla_proyectos[[#This Row],[municipio]]="","",VLOOKUP(Tbla_proyectos[[#This Row],[municipio]],INDIRECT(Tbla_proyectos[[#This Row],[departamento]]),2,0)) -> 4.3161077 | O78: =IF(Tbla_proyectos[[#This Row],[municipio]]="","",VLOOKUP(Tbla_proyectos[[#This Row],[municipio]],INDIRECT(Tbla_proyectos[[#This Row],[departamento]]),2,0)) -> 4.3161077 | P78: Continuidad
A79: 2510ISISTJUA-2 | B79: =LEFT(Tbla_proyectos[[#This Row],[codigo_proyecto]],4) -> 2510 | C79: Proyecto 13 | D79: Prácticas | E79: Desarrollo y mantenimiento de aplicaciones web. Gestión y optimización de redes sociales. Implementación de estrategias de mercadeo digital. | F79: Desarrollo Web + Gestión de Comunicación Digital | G79: Asesoría Técnica | H79: Juan Felipe Salcedo | K79: =IF(OR(Tbla_proyectos[[#This Row],[fecha_inicio]]="",Tbla_proyectos[[#This Row],[fecha_fin]]=""),"",DATEDIF(Tbla_proyectos[[#This Row],[fecha_inicio]],Tbla_proyectos[[#This Row],[fecha_fin]],"M")) | L79: BOGOTA | M79: BOGOTÁ, D.C. | N79: =IF(Tbla_proyectos[[#This Row],[municipio]]="","",VLOOKUP(Tbla_proyectos[[#This Row],[municipio]],INDIRECT(Tbla_proyectos[[#This Row],[departamento]]),2,0)) -> 4.3161077 | O79: =IF(Tbla_proyectos[[#This Row],[municipio]]="","",VLOOKUP(Tbla_proyectos[[#This Row],[municipio]],INDIRECT(Tbla_proyectos[[#This Row],[departamento]]),2,0)) -> 4.3161077 | P79: Continuidad
A80: 2530ISISTJUA-2 | B80: =LEFT(Tbla_proyectos[[#This Row],[codigo_proyecto]],4) -> 2530 | C80: Proyecto 13 | D80: Prácticas | E80: Desarrollo y mantenimiento de aplicaciones web. Gestión y optimización de redes sociales. Implementación de estrategias de mercadeo digital. | F80: Desarrollo Web + Gestión de Comunicación Digital | G80: Asesoría Técnica | H80: Juan Felipe Salcedo | K80: =IF(OR(Tbla_proyectos[[#This Row],[fecha_inicio]]="",Tbla_proyectos[[#This Row],[fecha_fin]]=""),"",DATEDIF(Tbla_proyectos[[#This Row],[fecha_inicio]],Tbla_proyectos[[#This Row],[fecha_fin]],"M")) | L80: BOGOTA | M80: BOGOTÁ, D.C. | N80: =IF(Tbla_proyectos[[#This Row],[municipio]]="","",VLOOKUP(Tbla_proyectos[[#This Row],[municipio]],INDIRECT(Tbla_proyectos[[#This Row],[departamento]]),2,0)) -> 4.3161077 | O80: =IF(Tbla_proyectos[[#This Row],[municipio]]="","",VLOOKUP(Tbla_proyectos[[#This Row],[municipio]],INDIRECT(Tbla_proyectos[[#This Row],[departamento]]),2,0)) -> 4.3161077 | P80: Continuidad
A81: 2510BIOINMAR-4 | B81: =LEFT(Tbla_proyectos[[#This Row],[codigo_proyecto]],4) -> 2510 | C81: Dispositivo para el control de refigerios y eventos | D81: Prácticas | E81: Asesoría técnica para la mejora de procesos que atiendan a otros requerimientos de la fundación, como en eventos, horas de alimentación capacitaciones entre otros | F81: Gestión de Procesos | G81: Asesoría Técnica y Capacitación | H81: Marcela Camargo Pabón | K81: =IF(OR(Tbla_proyectos[[#This Row],[fecha_inicio]]="",Tbla_proyectos[[#This Row],[fecha_fin]]=""),"",DATEDIF(Tbla_proyectos[[#This Row],[fecha_inicio]],Tbla_proyectos[[#This Row],[fecha_fin]],"M")) | L81: BOGOTA | M81: BOGOTÁ, D.C. | N81: =IF(Tbla_proyectos[[#This Row],[municipio]]="","",VLOOKUP(Tbla_proyectos[[#This Row],[municipio]],INDIRECT(Tbla_proyectos[[#This Row],[departamento]]),2,0)) -> 4.3161077 | O81: =IF(Tbla_proyectos[[#This Row],[municipio]]="","",VLOOKUP(Tbla_proyectos[[#This Row],[municipio]],INDIRECT(Tbla_proyectos[[#This Row],[departamento]]),2,0)) -> 4.3161077 | P81: Nuevo
A82: 2530BIOINMAR-4 | B82: =LEFT(Tbla_proyectos[[#This Row],[codigo_proyecto]],4) -> 2530 | C82: Dispositivo para el control de inventarios y entrega de alimentos | D82: Prácticas | E82: Asesoría técnica para la mejora de procesos que atiendan a otros requerimientos de la fundación, como en eventos, horas de alimentación capacitaciones entre otros | F82: Gestión de Procesos | G82: Asesoría Técnica y Capacitación | H82: Marcela Camargo Pabón | K82: =IF(OR(Tbla_proyectos[[#This Row],[fecha_inicio]]="",Tbla_proyectos[[#This Row],[fecha_fin]]=""),"",DATEDIF(Tbla_proyectos[[#This Row],[fecha_inicio]],Tbla_proyectos[[#This Row],[fecha_fin]],"M")) | L82: BOGOTA | M82: BOGOTÁ, D.C. | N82: =IF(Tbla_proyectos[[#This Row],[municipio]]="","",VLOOKUP(Tbla_proyectos[[#This Row],[municipio]],INDIRECT(Tbla_proyectos[[#This Row],[departamento]]),2,0)) -> 4.3161077 | O82: =IF(Tbla_proyectos[[#This Row],[municipio]]="","",VLOOKUP(Tbla_proyectos[[#This Row],[municipio]],INDIRECT(Tbla_proyectos[[#This Row],[departamento]]),2,0)) -> 4.3161077 | P82: Continuidad
A83: 2530IMECAMAR-4 | B83: =LEFT(Tbla_proyectos[[#This Row],[codigo_proyecto]],4) -> 2530 | C83: Dispositivo para el control de inventarios y registro de alimentos | D83: Prácticas | E83: Asesoría técnica para la mejora de procesos que atiendan a otros requerimientos de la fundación, como en eventos, horas de alimentación capacitaciones entre otros | F83: Gestión de Procesos | G83: Asesoría Técnica y Capacitación | H83: Marcela Camargo Pabón | K83: =IF(OR(Tbla_proyectos[[#This Row],[fecha_inicio]]="",Tbla_proyectos[[#This Row],[fecha_fin]]=""),"",DATEDIF(Tbla_proyectos[[#This Row],[fecha_inicio]],Tbla_proyectos[[#This Row],[fecha_fin]],"M")) | L83: BOGOTA | M83: BOGOTÁ, D.C. | N83: =IF(Tbla_proyectos[[#This Row],[municipio]]="","",VLOOKUP(Tbla_proyectos[[#This Row],[municipio]],INDIRECT(Tbla_proyectos[[#This Row],[departamento]]),2,0)) -> 4.3161077 | O83: =IF(Tbla_proyectos[[#This Row],[municipio]]="","",VLOOKUP(Tbla_proyectos[[#This Row],[municipio]],INDIRECT(Tbla_proyectos[[#This Row],[departamento]]),2,0)) -> 4.3161077 | P83: Continuidad
A84: 2430IMECAMAR-4 | B84: =LEFT(Tbla_proyectos[[#This Row],[codigo_proyecto]],4) -> 2430 | C84: ingeniokids | D84: Prácticas | E84: Desarrollo de proyectos de ingeniería con sus respectivas cartillas instructivas y aplicación práctica en grupos de estudiantes. Asesoría técnica para la mejora de procesos que atiendan a otros requerimientos de la fundación. | F84: Desarrollo de Material Educativo + Gestión de Procesos | G84: Asesoría Técnica y Capacitación | H84: Marcela Camargo Pabón | K84: =IF(OR(Tbla_proyectos[[#This Row],[fecha_inicio]]="",Tbla_proyectos[[#This Row],[fecha_fin]]=""),"",DATEDIF(Tbla_proyectos[[#This Row],[fecha_inicio]],Tbla_proyectos[[#This Row],[fecha_fin]],"M")) | L84: BOGOTA | M84: BOGOTÁ, D.C. | N84: =IF(Tbla_proyectos[[#This Row],[municipio]]="","",VLOOKUP(Tbla_proyectos[[#This Row],[municipio]],INDIRECT(Tbla_proyectos[[#This Row],[departamento]]),2,0)) -> 4.3161077 | O84: =IF(Tbla_proyectos[[#This Row],[municipio]]="","",VLOOKUP(Tbla_proyectos[[#This Row],[municipio]],INDIRECT(Tbla_proyectos[[#This Row],[departamento]]),2,0)) -> 4.3161077 | P84: Continuidad
A85: 2510IINDSCLA-7 | B85: =LEFT(Tbla_proyectos[[#This Row],[codigo_proyecto]],4) -> 2510 | D85: Prácticas | E85: Asesoría técnica por medio de reuniones de exploración, entendimiento, evaluación y ejecución de propuestas de proyectos de ingeniería que le ayuden a la entidad a mejorar la gestión de procesos. | F85: Gestión de Procesos | G85: Asesoría Técnica y Capacitación | H85: Clara Mabel Solano Vanegas | K85: =IF(OR(Tbla_proyectos[[#This Row],[fecha_inicio]]="",Tbla_proyectos[[#This Row],[fecha_fin]]=""),"",DATEDIF(Tbla_proyectos[[#This Row],[fecha_inicio]],Tbla_proyectos[[#This Row],[fecha_fin]],"M")) | L85: BOGOTA | M85: BOGOTÁ, D.C. | N85: =IF(Tbla_proyectos[[#This Row],[municipio]]="","",VLOOKUP(Tbla_proyectos[[#This Row],[municipio]],INDIRECT(Tbla_proyectos[[#This Row],[departamento]]),2,0)) -> 4.3161077 | O85: =IF(Tbla_proyectos[[#This Row],[municipio]]="","",VLOOKUP(Tbla_proyectos[[#This Row],[municipio]],INDIRECT(Tbla_proyectos[[#This Row],[departamento]]),2,0)) -> 4.3161077 | P85: Continuidad
A86: 2530IINDSCLA-7 | B86: =LEFT(Tbla_proyectos[[#This Row],[codigo_proyecto]],4) -> 2530 | C86: Mejoramiento procesos administrativos. | D86: Prácticas | E86: Asesoría técnica por medio de reuniones de exploración, entendimiento, evaluación y ejecución de propuestas de proyectos de ingeniería que le ayuden a la entidad a mejorar la gestión de procesos. | F86: Gestión de Procesos | G86: Asesoría Técnica y Capacitación | H86: Clara Mabel Solano Vanegas | K86: =IF(OR(Tbla_proyectos[[#This Row],[fecha_inicio]]="",Tbla_proyectos[[#This Row],[fecha_fin]]=""),"",DATEDIF(Tbla_proyectos[[#This Row],[fecha_inicio]],Tbla_proyectos[[#This Row],[fecha_fin]],"M")) | L86: BOGOTA | M86: BOGOTÁ, D.C. | N86: =IF(Tbla_proyectos[[#This Row],[municipio]]="","",VLOOKUP(Tbla_proyectos[[#This Row],[municipio]],INDIRECT(Tbla_proyectos[[#This Row],[departamento]]),2,0)) -> 4.3161077 | O86: =IF(Tbla_proyectos[[#This Row],[municipio]]="","",VLOOKUP(Tbla_proyectos[[#This Row],[municipio]],INDIRECT(Tbla_proyectos[[#This Row],[departamento]]),2,0)) -> 4.3161077 | P86: Continuidad
A87: 2430IINDSCLA-7 | B87: =LEFT(Tbla_proyectos[[#This Row],[codigo_proyecto]],4) -> 2430 | D87: Prácticas | E87: Asesoría técnica por medio de reuniones de exploración, entendimiento, evaluación y ejecución de propuestas de proyectos de ingeniería que le ayuden a la entidad a mejorar la gestión de procesos. | F87: Gestión de Procesos | G87: Asesoría Técnica y Capacitación | H87: Clara Mabel Solano Vanegas | K87: =IF(OR(Tbla_proyectos[[#This Row],[fecha_inicio]]="",Tbla_proyectos[[#This Row],[fecha_fin]]=""),"",DATEDIF(Tbla_proyectos[[#This Row],[fecha_inicio]],Tbla_proyectos[[#This Row],[fecha_fin]],"M")) | L87: BOGOTA | M87: BOGOTÁ, D.C. | N87: =IF(Tbla_proyectos[[#This Row],[municipio]]="","",VLOOKUP(Tbla_proyectos[[#This Row],[municipio]],INDIRECT(Tbla_proyectos[[#This Row],[departamento]]),2,0)) -> 4.3161077 | O87: =IF(Tbla_proyectos[[#This Row],[municipio]]="","",VLOOKUP(Tbla_proyectos[[#This Row],[municipio]],INDIRECT(Tbla_proyectos[[#This Row],[departamento]]),2,0)) -> 4.3161077 | P87: Continuidad
A88: 2510BIOINMAR-2 | B88: =LEFT(Tbla_proyectos[[#This Row],[codigo_proyecto]],4) -> 2510 | C88: Mejoramiento de caminador versión 2 y diseño de nuevo caminador para niños | D88: Prácticas | E88: Diseño, construcción y ajuste de un caminador para niños, considerando aspectos ergonómicos y funcionales. Continuación del proyecto anterior con la revisión y selección de un arnés más adecuado para niños, como de las cuerdas, materiales del arnés para evitar lesiones y fácil lavado Evalaución de un segundo caminador | F88: Tecnologías de Asistencia | G88: Asesoría Técnica | H88: Marcela Camargo Pabón | K88: =IF(OR(Tbla_proyectos[[#This Row],[fecha_inicio]]="",Tbla_proyectos[[#This Row],[fecha_fin]]=""),"",DATEDIF(Tbla_proyectos[[#This Row],[fecha_inicio]],Tbla_proyectos[[#This Row],[fecha_fin]],"M")) | L88: BOGOTA | M88: BOGOTÁ, D.C. | N88: =IF(Tbla_proyectos[[#This Row],[municipio]]="","",VLOOKUP(Tbla_proyectos[[#This Row],[municipio]],INDIRECT(Tbla_proyectos[[#This Row],[departamento]]),2,0)) -> 4.3161077 | O88: =IF(Tbla_proyectos[[#This Row],[municipio]]="","",VLOOKUP(Tbla_proyectos[[#This Row],[municipio]],INDIRECT(Tbla_proyectos[[#This Row],[departamento]]),2,0)) -> 4.3161077 | P88: Continuidad
A89: 2530BIOINMAR-2 | B89: =LEFT(Tbla_proyectos[[#This Row],[codigo_proyecto]],4) -> 2530 | C89: Mejoramiento de caminador versión 2 y diseño de nuevo caminador para niños | D89: Prácticas | E89: Diseño, construcción y ajuste de un caminador para niños, considerando aspectos ergonómicos y funcionales. Continuación del proyecto anterior con la revisión y selección de un arnés más adecuado para niños, como de las cuerdas, materiales del arnés para evitar lesiones y fácil lavado Evalaución de un segundo caminador | F89: Tecnologías de Asistencia | G89: Asesoría Técnica | H89: Marcela Camargo Pabón | K89: =IF(OR(Tbla_proyectos[[#This Row],[fecha_inicio]]="",Tbla_proyectos[[#This Row],[fecha_fin]]=""),"",DATEDIF(Tbla_proyectos[[#This Row],[fecha_inicio]],Tbla_proyectos[[#This Row],[fecha_fin]],"M")) | L89: BOGOTA | M89: BOGOTÁ, D.C. | N89: =IF(Tbla_proyectos[[#This Row],[municipio]]="","",VLOOKUP(Tbla_proyectos[[#This Row],[municipio]],INDIRECT(Tbla_proyectos[[#This Row],[departamento]]),2,0)) -> 4.3161077 | O89: =IF(Tbla_proyectos[[#This Row],[municipio]]="","",VLOOKUP(Tbla_proyectos[[#This Row],[municipio]],INDIRECT(Tbla_proyectos[[#This Row],[departamento]]),2,0)) -> 4.3161077 | P89: Continuidad
A90: 2530IMECAMAR-2 | B90: =LEFT(Tbla_proyectos[[#This Row],[codigo_proyecto]],4) -> 2530 | C90: Mejoramiento de caminador versión 3 y diseño de nuevo caminador y soporte para niños | D90: Prácticas | E90: Diseño, construcción y ajuste de un caminador para niños, considerando aspectos ergonómicos y funcionales. Continuación del proyecto anterior con la revisión y selección de un arnés más adecuado para niños, como de las cuerdas, materiales del arnés para evitar lesiones y fácil lavado Evalaución de un segundo caminador | F90: Tecnologías de Asistencia | G90: Asesoría Técnica | H90: Marcela Camargo Pabón | K90: =IF(OR(Tbla_proyectos[[#This Row],[fecha_inicio]]="",Tbla_proyectos[[#This Row],[fecha_fin]]=""),"",DATEDIF(Tbla_proyectos[[#This Row],[fecha_inicio]],Tbla_proyectos[[#This Row],[fecha_fin]],"M")) | L90: BOGOTA | M90: BOGOTÁ, D.C. | N90: =IF(Tbla_proyectos[[#This Row],[municipio]]="","",VLOOKUP(Tbla_proyectos[[#This Row],[municipio]],INDIRECT(Tbla_proyectos[[#This Row],[departamento]]),2,0)) -> 4.3161077 | O90: =IF(Tbla_proyectos[[#This Row],[municipio]]="","",VLOOKUP(Tbla_proyectos[[#This Row],[municipio]],INDIRECT(Tbla_proyectos[[#This Row],[departamento]]),2,0)) -> 4.3161077 | P90: Continuidad
A91: 2430IMECAMAR-2 | B91: =LEFT(Tbla_proyectos[[#This Row],[codigo_proyecto]],4) -> 2430 | C91: Diseño y construcción de Caminador y Camas Hospitalarias para niños | D91: Prácticas | E91: Diseño y construcción de un caminador para niños, considerando aspectos ergonómicos y funcionales. Continuación del proyecto anterior con la revisión y selección de un arnés más adecuado para niños. Mantenimiento y diseño de camas hospitalarias para niños, asegurando su confort y funcionalidad. | F91: Tecnologías de Asistencia | G91: Asesoría Técnica | H91: Marcela Camargo Pabón | K91: =IF(OR(Tbla_proyectos[[#This Row],[fecha_inicio]]="",Tbla_proyectos[[#This Row],[fecha_fin]]=""),"",DATEDIF(Tbla_proyectos[[#This Row],[fecha_inicio]],Tbla_proyectos[[#This Row],[fecha_fin]],"M")) | L91: BOGOTA | M91: BOGOTÁ, D.C. | N91: =IF(Tbla_proyectos[[#This Row],[municipio]]="","",VLOOKUP(Tbla_proyectos[[#This Row],[municipio]],INDIRECT(Tbla_proyectos[[#This Row],[departamento]]),2,0)) -> 4.3161077 | O91: =IF(Tbla_proyectos[[#This Row],[municipio]]="","",VLOOKUP(Tbla_proyectos[[#This Row],[municipio]],INDIRECT(Tbla_proyectos[[#This Row],[departamento]]),2,0)) -> 4.3161077 | P91: Continuidad
A92: 2430BIOINMAR-2 | B92: =LEFT(Tbla_proyectos[[#This Row],[codigo_proyecto]],4) -> 2430 | C92: Diseño y construcción de Caminador y Camas Hospitalarias para niños | D92: Prácticas | E92: Diseño y construcción de un caminador para niños, considerando aspectos ergonómicos y funcionales. Continuación del proyecto anterior con la revisión y selección de un arnés más adecuado para niños. Mantenimiento y diseño de camas hospitalarias para niños, asegurando su confort y funcionalidad. | F92: Tecnologías de Asistencia | G92: Asesoría Técnica | H92: Marcela Camargo Pabón | K92: =IF(OR(Tbla_proyectos[[#This Row],[fecha_inicio]]="",Tbla_proyectos[[#This Row],[fecha_fin]]=""),"",DATEDIF(Tbla_proyectos[[#This Row],[fecha_inicio]],Tbla_proyectos[[#This Row],[fecha_fin]],"M")) | L92: BOGOTA | M92: BOGOTÁ, D.C. | N92: =IF(Tbla_proyectos[[#This Row],[municipio]]="","",VLOOKUP(Tbla_proyectos[[#This Row],[municipio]],INDIRECT(Tbla_proyectos[[#This Row],[departamento]]),2,0)) -> 4.3161077 | O92: =IF(Tbla_proyectos[[#This Row],[municipio]]="","",VLOOKUP(Tbla_proyectos[[#This Row],[municipio]],INDIRECT(Tbla_proyectos[[#This Row],[departamento]]),2,0)) -> 4.3161077 | P92: Continuidad
A93: 2430IELECDIE-2 | B93: =LEFT(Tbla_proyectos[[#This Row],[codigo_proyecto]],4) -> 2430 | C93: Electrónica para la Vida | D93: Prácticas | E93: Diseño del sistema de riego para huertas en colaboración con las mujeres del parque Entrenubes. Capacitación en temas de computación para proporcionar herramientas adicionales para la posterior implementación del sistema de riego. | F93: Huertas + Capacitación en Tecnología | G93: Asesoría Técnica y Capacitación | H93: Diego Fernando Parra Díaz | K93: =IF(OR(Tbla_proyectos[[#This Row],[fecha_inicio]]="",Tbla_proyectos[[#This Row],[fecha_fin]]=""),"",DATEDIF(Tbla_proyectos[[#This Row],[fecha_inicio]],Tbla_proyectos[[#This Row],[fecha_fin]],"M")) | L93: BOGOTA | M93: BOGOTÁ, D.C. | N93: =IF(Tbla_proyectos[[#This Row],[municipio]]="","",VLOOKUP(Tbla_proyectos[[#This Row],[municipio]],INDIRECT(Tbla_proyectos[[#This Row],[departamento]]),2,0)) -> 4.3161077 | O93: =IF(Tbla_proyectos[[#This Row],[municipio]]="","",VLOOKUP(Tbla_proyectos[[#This Row],[municipio]],INDIRECT(Tbla_proyectos[[#This Row],[departamento]]),2,0)) -> 4.3161077 | P93: Continuidad
A94: 2530ISISTALI-15 | B94: =LEFT(Tbla_proyectos[[#This Row],[codigo_proyecto]],4) -> 2530 | C94: Proyecto 7 | D94: Prácticas | E94: Desarrollo y gestión de programación web. Gestión de redes sociales. Implementación de estrategias de mercadeo digital. | F94: Desarrollo Web + Gestión de Comunicación Digital | G94: Asesoría Técnica | H94: Alicia Mercedes Arenas Valderrama | K94: =IF(OR(Tbla_proyectos[[#This Row],[fecha_inicio]]="",Tbla_proyectos[[#This Row],[fecha_fin]]=""),"",DATEDIF(Tbla_proyectos[[#This Row],[fecha_inicio]],Tbla_proyectos[[#This Row],[fecha_fin]],"M")) | L94: BOGOTA | M94: BOGOTÁ, D.C. | N94: =IF(Tbla_proyectos[[#This Row],[municipio]]="","",VLOOKUP(Tbla_proyectos[[#This Row],[municipio]],INDIRECT(Tbla_proyectos[[#This Row],[departamento]]),2,0)) -> 4.3161077 | O94: =IF(Tbla_proyectos[[#This Row],[municipio]]="","",VLOOKUP(Tbla_proyectos[[#This Row],[municipio]],INDIRECT(Tbla_proyectos[[#This Row],[departamento]]),2,0)) -> 4.3161077
A95: 2430ISISTALI-10 | B95: =LEFT(Tbla_proyectos[[#This Row],[codigo_proyecto]],4) -> 2430 | C95: Proyecto 7 | D95: Prácticas | E95: Desarrollo y gestión de programación web. Gestión de redes sociales. Implementación de estrategias de mercadeo digital. | F95: Desarrollo Web + Gestión de Comunicación Digital | G95: Asesoría Técnica | H95: Alicia Mercedes Arenas Valderrama | K95: =IF(OR(Tbla_proyectos[[#This Row],[fecha_inicio]]="",Tbla_proyectos[[#This Row],[fecha_fin]]=""),"",DATEDIF(Tbla_proyectos[[#This Row],[fecha_inicio]],Tbla_proyectos[[#This Row],[fecha_fin]],"M")) | L95: BOGOTA | M95: BOGOTÁ, D.C. | N95: =IF(Tbla_proyectos[[#This Row],[municipio]]="","",VLOOKUP(Tbla_proyectos[[#This Row],[municipio]],INDIRECT(Tbla_proyectos[[#This Row],[departamento]]),2,0)) -> 4.3161077 | O95: =IF(Tbla_proyectos[[#This Row],[municipio]]="","",VLOOKUP(Tbla_proyectos[[#This Row],[municipio]],INDIRECT(Tbla_proyectos[[#This Row],[departamento]]),2,0)) -> 4.3161077
A96: 2510ISISTJUA-3 | B96: =LEFT(Tbla_proyectos[[#This Row],[codigo_proyecto]],4) -> 2510 | C96: Proyecto 7 | D96: Prácticas | E96: Desarrollo y gestión de programación web. Gestión de redes sociales. Implementación de estrategias de mercadeo digital. | F96: Desarrollo Web + Gestión de Comunicación Digital | G96: Asesoría Técnica | H96: Juan Felipe Salcedo | K96: =IF(OR(Tbla_proyectos[[#This Row],[fecha_inicio]]="",Tbla_proyectos[[#This Row],[fecha_fin]]=""),"",DATEDIF(Tbla_proyectos[[#This Row],[fecha_inicio]],Tbla_proyectos[[#This Row],[fecha_fin]],"M")) | L96: BOGOTA | M96: BOGOTÁ, D.C. | N96: =IF(Tbla_proyectos[[#This Row],[municipio]]="","",VLOOKUP(Tbla_proyectos[[#This Row],[municipio]],INDIRECT(Tbla_proyectos[[#This Row],[departamento]]),2,0)) -> 4.3161077 | O96: =IF(Tbla_proyectos[[#This Row],[municipio]]="","",VLOOKUP(Tbla_proyectos[[#This Row],[municipio]],INDIRECT(Tbla_proyectos[[#This Row],[departamento]]),2,0)) -> 4.3161077
A97: 2510IELECJOS-2 | B97: =LEFT(Tbla_proyectos[[#This Row],[codigo_proyecto]],4) -> 2510 | C97: Reparación de Electrodomésticos FSI | D97: Prácticas | E97: Revisión, reparación y selección de electrodomésticos y dispositivos electrónicos. | F97: Reparación de Electrodomésticos | G97: Asesoría Técnica | H97: José Ignacio Acevedo | K97: =IF(OR(Tbla_proyectos[[#This Row],[fecha_inicio]]="",Tbla_proyectos[[#This Row],[fecha_fin]]=""),"",DATEDIF(Tbla_proyectos[[#This Row],[fecha_inicio]],Tbla_proyectos[[#This Row],[fecha_fin]],"M")) | L97: CUNDINAMARCA | M97: CAJICÁ | N97: =IF(Tbla_proyectos[[#This Row],[municipio]]="","",VLOOKUP(Tbla_proyectos[[#This Row],[municipio]],INDIRECT(Tbla_proyectos[[#This Row],[departamento]]),2,0)) -> 4.9304028 | O97: =IF(Tbla_proyectos[[#This Row],[municipio]]="","",VLOOKUP(Tbla_proyectos[[#This Row],[municipio]],INDIRECT(Tbla_proyectos[[#This Row],[departamento]]),2,0)) -> 4.9304028 | P97: Continuidad
A98: 2530IELECJOS-2 | B98: =LEFT(Tbla_proyectos[[#This Row],[codigo_proyecto]],4) -> 2530 | C98: Reparación de Electrodomésticos FSI | D98: Prácticas | E98: Revisión, reparación y selección de electrodomésticos y dispositivos electrónicos. | F98: Reparación de Electrodomésticos | G98: Asesoría Técnica | H98: José Ignacio Acevedo Gordo | K98: =IF(OR(Tbla_proyectos[[#This Row],[fecha_inicio]]="",Tbla_proyectos[[#This Row],[fecha_fin]]=""),"",DATEDIF(Tbla_proyectos[[#This Row],[fecha_inicio]],Tbla_proyectos[[#This Row],[fecha_fin]],"M")) | L98: CUNDINAMARCA | M98: CAJICÁ | N98: =IF(Tbla_proyectos[[#This Row],[municipio]]="","",VLOOKUP(Tbla_proyectos[[#This Row],[municipio]],INDIRECT(Tbla_proyectos[[#This Row],[departamento]]),2,0)) -> 4.9304028 | O98: =IF(Tbla_proyectos[[#This Row],[municipio]]="","",VLOOKUP(Tbla_proyectos[[#This Row],[municipio]],INDIRECT(Tbla_proyectos[[#This Row],[departamento]]),2,0)) -> 4.9304028 | P98: Continuidad
A99: 2430IELECJOS-2 | B99: =LEFT(Tbla_proyectos[[#This Row],[codigo_proyecto]],4) -> 2430 | C99: Reparación de Electrodomésticos FSI | D99: Prácticas | E99: Revisión, reparación y selección de electrodomésticos y dispositivos electrónicos. | F99: Reparación de Electrodomésticos | G99: Asesoría Técnica | H99: José Ignacio Acevedo Gordo | K99: =IF(OR(Tbla_proyectos[[#This Row],[fecha_inicio]]="",Tbla_proyectos[[#This Row],[fecha_fin]]=""),"",DATEDIF(Tbla_proyectos[[#This Row],[fecha_inicio]],Tbla_proyectos[[#This Row],[fecha_fin]],"M")) | L99: CUNDINAMARCA | M99: CAJICÁ | N99: =IF(Tbla_proyectos[[#This Row],[municipio]]="","",VLOOKUP(Tbla_proyectos[[#This Row],[municipio]],INDIRECT(Tbla_proyectos[[#This Row],[departamento]]),2,0)) -> 4.9304028 | O99: =IF(Tbla_proyectos[[#This Row],[municipio]]="","",VLOOKUP(Tbla_proyectos[[#This Row],[municipio]],INDIRECT(Tbla_proyectos[[#This Row],[departamento]]),2,0)) -> 4.9304028 | P99: Continuidad
A100: 2520IELECJOS-2 | B100: =LEFT(Tbla_proyectos[[#This Row],[codigo_proyecto]],4) -> 2520 | C100: Reparación de Electrodomésticos FSI | D100: Prácticas | E100: Revisión, reparación y selección de electrodomésticos y dispositivos electrónicos. | F100: Reparación de Electrodomésticos | G100: Asesoría Técnica | H100: Cristian Camilo León Bohorquez | K100: =IF(OR(Tbla_proyectos[[#This Row],[fecha_inicio]]="",Tbla_proyectos[[#This Row],[fecha_fin]]=""),"",DATEDIF(Tbla_proyectos[[#This Row],[fecha_inicio]],Tbla_proyectos[[#This Row],[fecha_fin]],"M")) | L100: CUNDINAMARCA | M100: CAJICÁ | N100: =IF(Tbla_proyectos[[#This Row],[municipio]]="","",VLOOKUP(Tbla_proyectos[[#This Row],[municipio]],INDIRECT(Tbla_proyectos[[#This Row],[departamento]]),2,0)) -> 4.9304028 | O100: =IF(Tbla_proyectos[[#This Row],[municipio]]="","",VLOOKUP(Tbla_proyectos[[#This Row],[municipio]],INDIRECT(Tbla_proyectos[[#This Row],[departamento]]),2,0)) -> 4.9304028 | P100: Continuidad
...

Sheet Entidades
A1: NIT | B1: codigo_entidad | C1: razon_social | D1: sector_economico | E1: CIUU | F1: CIUU_descripcion | G1: correo_entidad | H1: telef_principal | I1: direccion | J1: localidad | K1: municipio | L1: estado_convenio_javelex | M1: num_convenio_javelex | N1: fecha_vencimiento_convenio | O1: observaciones
A2: 00000111-1 | B2: {=_xlfn.LET(_xlpm._nit,TRIM(A2&""),_xlpm._rs,TRIM(UPPER(C2&"")),_xlpm._txt,TRIM(SUBSTITUTE(SUBSTITUTE(SUBSTITUTE(SUBSTITUTE(SUBSTITUTE(SUBSTITUTE(SUBSTITUTE(_xlpm._rs,".",""),","," "),"-"," "),"/"," "),"("," "),")"," "),":"," ")),_xlpm._pal,_xlfn.TEXTSPLIT(_xlpm._txt," "),_xlpm._util,_xlfn._xlws.FILTER(_xlpm._pal,ISERROR(MATCH(_xlpm._pal,{"DE";"DEL";"LA";"LAS";"EL";"LOS";"Y";"EN";"PARA";"POR";"CON";"A";"AL";"UN";"UNA";"UNOS";"UNAS"},0))),_xlpm._cod,IFERROR(_xlfn.TEXTJOIN("_",TRUE,LEFT(INDEX(_xlpm._util,1,_xlfn.SEQUENCE(1,MIN(5,COLUMNS(_xlpm._util)))),5)),""),IF(OR(_xlpm._nit="",UPPER(_xlpm._nit)="N/A",UPPER(_xlpm._nit)="NA",UPPER(_xlpm._nit)="SIN NIT",UPPER(_xlpm._nit)="NO APLICA",_xlpm._nit="0"),_xlpm._cod,_xlpm._nit))} -> 00000111-1 | C2: Oficina de Responsabilidad Social Universitaria - Javeriana | D2: CUATERNARIO | F2: =IF(Tbla_entidades[[#This Row],[CIUU]]="","",_xlfn.XLOOKUP(Tbla_entidades[[#This Row],[CIUU]],Listas!$N:$N,Listas!$O:$O,"")) | G2: barbosa_alexandra@javeriana.edu.co | I2: Calle 40 No. 5-50 | J2: Teusaquillo | K2: Bogotá D.C. | L2: EN EJECUCIÓN | M2: N/A | N2: N/A
A3: 00000111-2 | B3: {=_xlfn.LET(_xlpm._nit,TRIM(A3&""),_xlpm._rs,TRIM(UPPER(C3&"")),_xlpm._txt,TRIM(SUBSTITUTE(SUBSTITUTE(SUBSTITUTE(SUBSTITUTE(SUBSTITUTE(SUBSTITUTE(SUBSTITUTE(_xlpm._rs,".",""),","," "),"-"," "),"/"," "),"("," "),")"," "),":"," ")),_xlpm._pal,_xlfn.TEXTSPLIT(_xlpm._txt," "),_xlpm._util,_xlfn._xlws.FILTER(_xlpm._pal,ISERROR(MATCH(_xlpm._pal,{"DE";"DEL";"LA";"LAS";"EL";"LOS";"Y";"EN";"PARA";"POR";"CON";"A";"AL";"UN";"UNA";"UNOS";"UNAS"},0))),_xlpm._cod,IFERROR(_xlfn.TEXTJOIN("_",TRUE,LEFT(INDEX(_xlpm._util,1,_xlfn.SEQUENCE(1,MIN(5,COLUMNS(_xlpm._util)))),5)),""),IF(OR(_xlpm._nit="",UPPER(_xlpm._nit)="N/A",UPPER(_xlpm._nit)="NA",UPPER(_xlpm._nit)="SIN NIT",UPPER(_xlpm._nit)="NO APLICA",_xlpm._nit="0"),_xlpm._cod,_xlpm._nit))} -> 00000111-2 | C3: Departamento de Ingeniería Electrónica PUJ | D3: CUATERNARIO | F3: =IF(Tbla_entidades[[#This Row],[CIUU]]="","",_xlfn.XLOOKUP(Tbla_entidades[[#This Row],[CIUU]],Listas!$N:$N,Listas!$O:$O,"")) | G3: jhurtado@javeriana.edu.co | H3: 3137773777 | I3: Calle 40 No. 5-50 | J3: Teusaquillo | K3: Bogotá D.C. | L3: EN EJECUCIÓN | M3: N/A | N3: N/A
A4: 00000111-3 | B4: {=_xlfn.LET(_xlpm._nit,TRIM(A4&""),_xlpm._rs,TRIM(UPPER(C4&"")),_xlpm._txt,TRIM(SUBSTITUTE(SUBSTITUTE(SUBSTITUTE(SUBSTITUTE(SUBSTITUTE(SUBSTITUTE(SUBSTITUTE(_xlpm._rs,".",""),","," "),"-"," "),"/"," "),"("," "),")"," "),":"," ")),_xlpm._pal,_xlfn.TEXTSPLIT(_xlpm._txt," "),_xlpm._util,_xlfn._xlws.FILTER(_xlpm._pal,ISERROR(MATCH(_xlpm._pal,{"DE";"DEL";"LA";"LAS";"EL";"LOS";"Y";"EN";"PARA";"POR";"CON";"A";"AL";"UN";"UNA";"UNOS";"UNAS"},0))),_xlpm._cod,IFERROR(_xlfn.TEXTJOIN("_",TRUE,LEFT(INDEX(_xlpm._util,1,_xlfn.SEQUENCE(1,MIN(5,COLUMNS(_xlpm._util)))),5)),""),IF(OR(_xlpm._nit="",UPPER(_xlpm._nit)="N/A",UPPER(_xlpm._nit)="NA",UPPER(_xlpm._nit)="SIN NIT",UPPER(_xlpm._nit)="NO APLICA",_xlpm._nit="0"),_xlpm._cod,_xlpm._nit))} -> 00000111-3 | C4: Prosofi - Programa Social Facultad de Ingeniería - Javeriana | D4: CUATERNARIO | F4: =IF(Tbla_entidades[[#This Row],[CIUU]]="","",_xlfn.XLOOKUP(Tbla_entidades[[#This Row],[CIUU]],Listas!$N:$N,Listas!$O:$O,"")) | G4: b.oviedo@javeriana.edu.co | I4: Calle 40 No. 5-50 | J4: Usme | K4: Bogotá D.C. | L4: EN EJECUCIÓN | M4: N/A | N4: N/A
A5: 800023096-6 | B5: {=_xlfn.LET(_xlpm._nit,TRIM(A5&""),_xlpm._rs,TRIM(UPPER(C5&"")),_xlpm._txt,TRIM(SUBSTITUTE(SUBSTITUTE(SUBSTITUTE(SUBSTITUTE(SUBSTITUTE(SUBSTITUTE(SUBSTITUTE(_xlpm._rs,".",""),","," "),"-"," "),"/"," "),"("," "),")"," "),":"," ")),_xlpm._pal,_xlfn.TEXTSPLIT(_xlpm._txt," "),_xlpm._util,_xlfn._xlws.FILTER(_xlpm._pal,ISERROR(MATCH(_xlpm._pal,{"DE";"DEL";"LA";"LAS";"EL";"LOS";"Y";"EN";"PARA";"POR";"CON";"A";"AL";"UN";"UNA";"UNOS";"UNAS"},0))),_xlpm._cod,IFERROR(_xlfn.TEXTJOIN("_",TRUE,LEFT(INDEX(_xlpm._util,1,_xlfn.SEQUENCE(1,MIN(5,COLUMNS(_xlpm._util)))),5)),""),IF(OR(_xlpm._nit="",UPPER(_xlpm._nit)="N/A",UPPER(_xlpm._nit)="NA",UPPER(_xlpm._nit)="SIN NIT",UPPER(_xlpm._nit)="NO APLICA",_xlpm._nit="0"),_xlpm._cod,_xlpm._nit))} -> 800023096-6 | C5: Fundación Santa Isabel | D5: CUATERNARIO | F5: =IF(Tbla_entidades[[#This Row],[CIUU]]="","",_xlfn.XLOOKUP(Tbla_entidades[[#This Row],[CIUU]],Listas!$N:$N,Listas!$O:$O,"")) | G5: contacto@fundacionsantaisabel.org | H5: 0 | I5: Km 27 via Cajica | J5: Cajicá | K5: Bogotá D.C. | L5: EN EJECUCIÓN | M5: PUJ-04965-19 | N5: 44767
A6: 800048102-2 | B6: {=_xlfn.LET(_xlpm._nit,TRIM(A6&""),_xlpm._rs,TRIM(UPPER(C6&"")),_xlpm._txt,TRIM(SUBSTITUTE(SUBSTITUTE(SUBSTITUTE(SUBSTITUTE(SUBSTITUTE(SUBSTITUTE(SUBSTITUTE(_xlpm._rs,".",""),","," "),"-"," "),"/"," "),"("," "),")"," "),":"," ")),_xlpm._pal,_xlfn.TEXTSPLIT(_xlpm._txt," "),_xlpm._util,_xlfn._xlws.FILTER(_xlpm._pal,ISERROR(MATCH(_xlpm._pal,{"DE";"DEL";"LA";"LAS";"EL";"LOS";"Y";"EN";"PARA";"POR";"CON";"A";"AL";"UN";"UNA";"UNOS";"UNAS"},0))),_xlpm._cod,IFERROR(_xlfn.TEXTJOIN("_",TRUE,LEFT(INDEX(_xlpm._util,1,_xlfn.SEQUENCE(1,MIN(5,COLUMNS(_xlpm._util)))),5)),""),IF(OR(_xlpm._nit="",UPPER(_xlpm._nit)="N/A",UPPER(_xlpm._nit)="NA",UPPER(_xlpm._nit)="SIN NIT",UPPER(_xlpm._nit)="NO APLICA",_xlpm._nit="0"),_xlpm._cod,_xlpm._nit))} -> 800048102-2 | C6: Fundación Hogar Integral | D6: CUATERNARIO | F6: =IF(Tbla_entidades[[#This Row],[CIUU]]="","",_xlfn.XLOOKUP(Tbla_entidades[[#This Row],[CIUU]],Listas!$N:$N,Listas!$O:$O,"")) | G6: gerencia@fundacionhogarintegral.org | H6: 7105855 | I6: Kra 68 c Bis 37a 54 sur | J6: Tunjuelito | K6: Bogotá D.C. D.C. | L6: EN EJECUCIÓN | M6: PUJ-04539-21 | N6: 46210
A7: 800065394-8 | B7: {=_xlfn.LET(_xlpm._nit,TRIM(A7&""),_xlpm._rs,TRIM(UPPER(C7&"")),_xlpm._txt,TRIM(SUBSTITUTE(SUBSTITUTE(SUBSTITUTE(SUBSTITUTE(SUBSTITUTE(SUBSTITUTE(SUBSTITUTE(_xlpm._rs,".",""),","," "),"-"," "),"/"," "),"("," "),")"," "),":"," ")),_xlpm._pal,_xlfn.TEXTSPLIT(_xlpm._txt," "),_xlpm._util,_xlfn._xlws.FILTER(_xlpm._pal,ISERROR(MATCH(_xlpm._pal,{"DE";"DEL";"LA";"LAS";"EL";"LOS";"Y";"EN";"PARA";"POR";"CON";"A";"AL";"UN";"UNA";"UNOS";"UNAS"},0))),_xlpm._cod,IFERROR(_xlfn.TEXTJOIN("_",TRUE,LEFT(INDEX(_xlpm._util,1,_xlfn.SEQUENCE(1,MIN(5,COLUMNS(_xlpm._util)))),5)),""),IF(OR(_xlpm._nit="",UPPER(_xlpm._nit)="N/A",UPPER(_xlpm._nit)="NA",UPPER(_xlpm._nit)="SIN NIT",UPPER(_xlpm._nit)="NO APLICA",_xlpm._nit="0"),_xlpm._cod,_xlpm._nit))} -> 800065394-8 | C7: Corporación Mundial de la Mujer | D7: CUATERNARIO | F7: =IF(Tbla_entidades[[#This Row],[CIUU]]="","",_xlfn.XLOOKUP(Tbla_entidades[[#This Row],[CIUU]],Listas!$N:$N,Listas!$O:$O,"")) | G7: info@cmmcolombia.org | H7: 3553040- 3229439165 | I7: Calle 31 # 13A -51. Of. 303 | J7: Santa Fé | K7: Bogotá D.C. | L7: EN EJECUCIÓN | M7: PUJ-05885-19 | N7: 44777
A8: 800151826-6 | B8: {=_xlfn.LET(_xlpm._nit,TRIM(A8&""),_xlpm._rs,TRIM(UPPER(C8&"")),_xlpm._txt,TRIM(SUBSTITUTE(SUBSTITUTE(SUBSTITUTE(SUBSTITUTE(SUBSTITUTE(SUBSTITUTE(SUBSTITUTE(_xlpm._rs,".",""),","," "),"-"," "),"/"," "),"("," "),")"," "),":"," ")),_xlpm._pal,_xlfn.TEXTSPLIT(_xlpm._txt," "),_xlpm._util,_xlfn._xlws.FILTER(_xlpm._pal,ISERROR(MATCH(_xlpm._pal,{"DE";"DEL";"LA";"LAS";"EL";"LOS";"Y";"EN";"PARA";"POR";"CON";"A";"AL";"UN";"UNA";"UNOS";"UNAS"},0))),_xlpm._cod,IFERROR(_xlfn.TEXTJOIN("_",TRUE,LEFT(INDEX(_xlpm._util,1,_xlfn.SEQUENCE(1,MIN(5,COLUMNS(_xlpm._util)))),5)),""),IF(OR(_xlpm._nit="",UPPER(_xlpm._nit)="N/A",UPPER(_xlpm._nit)="NA",UPPER(_xlpm._nit)="SIN NIT",UPPER(_xlpm._nit)="NO APLICA",_xlpm._nit="0"),_xlpm._cod,_xlpm._nit))} -> 800151826-6 | C8: Parroquia San Mario | D8: CUATERNARIO | F8: =IF(Tbla_entidades[[#This Row],[CIUU]]="","",_xlfn.XLOOKUP(Tbla_entidades[[#This Row],[CIUU]],Listas!$N:$N,Listas!$O:$O,"")) | G8: jesusarroyave2@gmail.com | H8: 3052164093 | I8: Cra. 13 Este #14, Bogotá | J8: Usme | K8: Bogotá D.C. | L8: EN EJECUCIÓN | M8: PUJ-00209-23 | N8: 19/01/2028
A9: 800189093-9 | B9: {=_xlfn.LET(_xlpm._nit,TRIM(A9&""),_xlpm._rs,TRIM(UPPER(C9&"")),_xlpm._txt,TRIM(SUBSTITUTE(SUBSTITUTE(SUBSTITUTE(SUBSTITUTE(SUBSTITUTE(SUBSTITUTE(SUBSTITUTE(_xlpm._rs,".",""),","," "),"-"," "),"/"," "),"("," "),")"," "),":"," ")),_xlpm._pal,_xlfn.TEXTSPLIT(_xlpm._txt," "),_xlpm._util,_xlfn._xlws.FILTER(_xlpm._pal,ISERROR(MATCH(_xlpm._pal,{"DE";"DEL";"LA";"LAS";"EL";"LOS";"Y";"EN";"PARA";"POR";"CON";"A";"AL";"UN";"UNA";"UNOS";"UNAS"},0))),_xlpm._cod,IFERROR(_xlfn.TEXTJOIN("_",TRUE,LEFT(INDEX(_xlpm._util,1,_xlfn.SEQUENCE(1,MIN(5,COLUMNS(_xlpm._util)))),5)),""),IF(OR(_xlpm._nit="",UPPER(_xlpm._nit)="N/A",UPPER(_xlpm._nit)="NA",UPPER(_xlpm._nit)="SIN NIT",UPPER(_xlpm._nit)="NO APLICA",_xlpm._nit="0"),_xlpm._cod,_xlpm._nit))} -> 800189093-9 | C9: Corporación por el Desarrollo del Norte de la Sabana - Prodensa | D9: CUATERNARIO | G9: coordinacionrs@prodensa.org | H9: 8572147 | I9: Calle 3 no 3 81 | J9: Sopó | K9: Bogotá D.C. | L9: EN EJECUCIÓN | M9: PUJ-04934-21 | N9: 46224
A10: 800197098-9 | B10: {=_xlfn.LET(_xlpm._nit,TRIM(A10&""),_xlpm._rs,TRIM(UPPER(C10&"")),_xlpm._txt,TRIM(SUBSTITUTE(SUBSTITUTE(SUBSTITUTE(SUBSTITUTE(SUBSTITUTE(SUBSTITUTE(SUBSTITUTE(_xlpm._rs,".",""),","," "),"-"," "),"/"," "),"("," "),")"," "),":"," ")),_xlpm._pal,_xlfn.TEXTSPLIT(_xlpm._txt," "),_xlpm._util,_xlfn._xlws.FILTER(_xlpm._pal,ISERROR(MATCH(_xlpm._pal,{"DE";"DEL";"LA";"LAS";"EL";"LOS";"Y";"EN";"PARA";"POR";"CON";"A";"AL";"UN";"UNA";"UNOS";"UNAS"},0))),_xlpm._cod,IFERROR(_xlfn.TEXTJOIN("_",TRUE,LEFT(INDEX(_xlpm._util,1,_xlfn.SEQUENCE(1,MIN(5,COLUMNS(_xlpm._util)))),5)),""),IF(OR(_xlpm._nit="",UPPER(_xlpm._nit)="N/A",UPPER(_xlpm._nit)="NA",UPPER(_xlpm._nit)="SIN NIT",UPPER(_xlpm._nit)="NO APLICA",_xlpm._nit="0"),_xlpm._cod,_xlpm._nit))} -> 800197098-9 | C10: Fundación PT: Participación - Pedagogía - Productividad | F10: =IF(Tbla_entidades[[#This Row],[CIUU]]="","",_xlfn.XLOOKUP(Tbla_entidades[[#This Row],[CIUU]],Listas!$N:$N,Listas!$O:$O,"")) | I10: Carrera 86G #40-60 sur | J10: Kennedy | K10: Bogotá D.C.
A11: 800223876-4 | B11: {=_xlfn.LET(_xlpm._nit,TRIM(A11&""),_xlpm._rs,TRIM(UPPER(C11&"")),_xlpm._txt,TRIM(SUBSTITUTE(SUBSTITUTE(SUBSTITUTE(SUBSTITUTE(SUBSTITUTE(SUBSTITUTE(SUBSTITUTE(_xlpm._rs,".",""),","," "),"-"," "),"/"," "),"("," "),")"," "),":"," ")),_xlpm._pal,_xlfn.TEXTSPLIT(_xlpm._txt," "),_xlpm._util,_xlfn._xlws.FILTER(_xlpm._pal,ISERROR(MATCH(_xlpm._pal,{"DE";"DEL";"LA";"LAS";"EL";"LOS";"Y";"EN";"PARA";"POR";"CON";"A";"AL";"UN";"UNA";"UNOS";"UNAS"},0))),_xlpm._cod,IFERROR(_xlfn.TEXTJOIN("_",TRUE,LEFT(INDEX(_xlpm._util,1,_xlfn.SEQUENCE(1,MIN(5,COLUMNS(_xlpm._util)))),5)),""),IF(OR(_xlpm._nit="",UPPER(_xlpm._nit)="N/A",UPPER(_xlpm._nit)="NA",UPPER(_xlpm._nit)="SIN NIT",UPPER(_xlpm._nit)="NO APLICA",_xlpm._nit="0"),_xlpm._cod,_xlpm._nit))} -> 800223876-4 | C11: Fundación Centro de Investigación e Información en Deficiencias Auditivas - CINDA | F11: =IF(Tbla_entidades[[#This Row],[CIUU]]="","",_xlfn.XLOOKUP(Tbla_entidades[[#This Row],[CIUU]],Listas!$N:$N,Listas!$O:$O,"")) | I11: Cl. 35 #17-24, Bogotá | J11: Teusaquillo | K11: Bogotá D.C.
A12: 800232778-9 | B12: {=_xlfn.LET(_xlpm._nit,TRIM(A12&""),_xlpm._rs,TRIM(UPPER(C12&"")),_xlpm._txt,TRIM(SUBSTITUTE(SUBSTITUTE(SUBSTITUTE(SUBSTITUTE(SUBSTITUTE(SUBSTITUTE(SUBSTITUTE(_xlpm._rs,".",""),","," "),"-"," "),"/"," "),"("," "),")"," "),":"," ")),_xlpm._pal,_xlfn.TEXTSPLIT(_xlpm._txt," "),_xlpm._util,_xlfn._xlws.FILTER(_xlpm._pal,ISERROR(MATCH(_xlpm._pal,{"DE";"DEL";"LA";"LAS";"EL";"LOS";"Y";"EN";"PARA";"POR";"CON";"A";"AL";"UN";"UNA";"UNOS";"UNAS"},0))),_xlpm._cod,IFERROR(_xlfn.TEXTJOIN("_",TRUE,LEFT(INDEX(_xlpm._util,1,_xlfn.SEQUENCE(1,MIN(5,COLUMNS(_xlpm._util)))),5)),""),IF(OR(_xlpm._nit="",UPPER(_xlpm._nit)="N/A",UPPER(_xlpm._nit)="NA",UPPER(_xlpm._nit)="SIN NIT",UPPER(_xlpm._nit)="NO APLICA",_xlpm._nit="0"),_xlpm._cod,_xlpm._nit))} -> 800232778-9 | C12: Fundación Sainville | D12: CUATERNARIO | F12: =IF(Tbla_entidades[[#This Row],[CIUU]]="","",_xlfn.XLOOKUP(Tbla_entidades[[#This Row],[CIUU]],Listas!$N:$N,Listas!$O:$O,"")) | G12: funsainville@gmail.com | H12: 0 | I12: Carrera 2B # 90 - 16 sur | J12: Usme | K12: Bogotá D.C. | L12: EN EJECUCIÓN | M12: PUJ-04960-19 | N12: 44767
A13: 808004139-4 | B13: {=_xlfn.LET(_xlpm._nit,TRIM(A13&""),_xlpm._rs,TRIM(UPPER(C13&"")),_xlpm._txt,TRIM(SUBSTITUTE(SUBSTITUTE(SUBSTITUTE(SUBSTITUTE(SUBSTITUTE(SUBSTITUTE(SUBSTITUTE(_xlpm._rs,".",""),","," "),"-"," "),"/"," "),"("," "),")"," "),":"," ")),_xlpm._pal,_xlfn.TEXTSPLIT(_xlpm._txt," "),_xlpm._util,_xlfn._xlws.FILTER(_xlpm._pal,ISERROR(MATCH(_xlpm._pal,{"DE";"DEL";"LA";"LAS";"EL";"LOS";"Y";"EN";"PARA";"POR";"CON";"A";"AL";"UN";"UNA";"UNOS";"UNAS"},0))),_xlpm._cod,IFERROR(_xlfn.TEXTJOIN("_",TRUE,LEFT(INDEX(_xlpm._util,1,_xlfn.SEQUENCE(1,MIN(5,COLUMNS(_xlpm._util)))),5)),""),IF(OR(_xlpm._nit="",UPPER(_xlpm._nit)="N/A",UPPER(_xlpm._nit)="NA",UPPER(_xlpm._nit)="SIN NIT",UPPER(_xlpm._nit)="NO APLICA",_xlpm._nit="0"),_xlpm._cod,_xlpm._nit))} -> 808004139-4 | C13: Junta de Acción Comunal Vereda Las Mercedes Sector Los Robles | D13: CUATERNARIO | F13: =IF(Tbla_entidades[[#This Row],[CIUU]]="","",_xlfn.XLOOKUP(Tbla_entidades[[#This Row],[CIUU]],Listas!$N:$N,Listas!$O:$O,"")) | G13: comitezrcpartealta@gmail.com | H13: 3002783497 | I13: Parte Alta Municipio de Venecia | J13: Parte Alta Municipio de Venecia | K13: Bogotá D.C. | L13: EN EJECUCIÓN | M13: PUJ-00277-23 | N13: 44949
A14: 811004956-6 | B14: {=_xlfn.LET(_xlpm._nit,TRIM(A14&""),_xlpm._rs,TRIM(UPPER(C14&"")),_xlpm._txt,TRIM(SUBSTITUTE(SUBSTITUTE(SUBSTITUTE(SUBSTITUTE(SUBSTITUTE(SUBSTITUTE(SUBSTITUTE(_xlpm._rs,".",""),","," "),"-"," "),"/"," "),"("," "),")"," "),":"," ")),_xlpm._pal,_xlfn.TEXTSPLIT(_xlpm._txt," "),_xlpm._util,_xlfn._xlws.FILTER(_xlpm._pal,ISERROR(MATCH(_xlpm._pal,{"DE";"DEL";"LA";"LAS";"EL";"LOS";"Y";"EN";"PARA";"POR";"CON";"A";"AL";"UN";"UNA";"UNOS";"UNAS"},0))),_xlpm._cod,IFERROR(_xlfn.TEXTJOIN("_",TRUE,LEFT(INDEX(_xlpm._util,1,_xlfn.SEQUENCE(1,MIN(5,COLUMNS(_xlpm._util)))),5)),""),IF(OR(_xlpm._nit="",UPPER(_xlpm._nit)="N/A",UPPER(_xlpm._nit)="NA",UPPER(_xlpm._nit)="SIN NIT",UPPER(_xlpm._nit)="NO APLICA",_xlpm._nit="0"),_xlpm._cod,_xlpm._nit))} -> 811004956-6 | C14: Fundación La Luz - Centro Nacional para el Tratamiento de la Drogadicción | D14: CUATERNARIO | F14: =IF(Tbla_entidades[[#This Row],[CIUU]]="","",_xlfn.XLOOKUP(Tbla_entidades[[#This Row],[CIUU]],Listas!$N:$N,Listas!$O:$O,"")) | H14: 3017481056 | I14: AV CL 80 116 B 35 | J14: Engativá | K14: Bogotá D.C. | L14: EN EJECUCIÓN | M14: PUJ-07401-22 | N14: 46662
A15: 830003252-4 | B15: {=_xlfn.LET(_xlpm._nit,TRIM(A15&""),_xlpm._rs,TRIM(UPPER(C15&"")),_xlpm._txt,TRIM(SUBSTITUTE(SUBSTITUTE(SUBSTITUTE(SUBSTITUTE(SUBSTITUTE(SUBSTITUTE(SUBSTITUTE(_xlpm._rs,".",""),","," "),"-"," "),"/"," "),"("," "),")"," "),":"," ")),_xlpm._pal,_xlfn.TEXTSPLIT(_xlpm._txt," "),_xlpm._util,_xlfn._xlws.FILTER(_xlpm._pal,ISERROR(MATCH(_xlpm._pal,{"DE";"DEL";"LA";"LAS";"EL";"LOS";"Y";"EN";"PARA";"POR";"CON";"A";"AL";"UN";"UNA";"UNOS";"UNAS"},0))),_xlpm._cod,IFERROR(_xlfn.TEXTJOIN("_",TRUE,LEFT(INDEX(_xlpm._util,1,_xlfn.SEQUENCE(1,MIN(5,COLUMNS(_xlpm._util)))),5)),""),IF(OR(_xlpm._nit="",UPPER(_xlpm._nit)="N/A",UPPER(_xlpm._nit)="NA",UPPER(_xlpm._nit)="SIN NIT",UPPER(_xlpm._nit)="NO APLICA",_xlpm._nit="0"),_xlpm._cod,_xlpm._nit))} -> 830003252-4 | C15: Fundación del Quemado | D15: CUATERNARIO | F15: =IF(Tbla_entidades[[#This Row],[CIUU]]="","",_xlfn.XLOOKUP(Tbla_entidades[[#This Row],[CIUU]],Listas!$N:$N,Listas!$O:$O,"")) | G15: subdireccionpril@fundaciondelquemado.org /contacto@fundaciondelquemado.org | H15: 2531223 - 6433318 | I15: Calle 128 B No. 59B-20 | J15: Suba | K15: Bogotá D.C. | L15: EN EJECUCIÓN | M15: PUJ-04709-20 | N15: 45137
A16: 830033350-6 | B16: {=_xlfn.LET(_xlpm._nit,TRIM(A16&""),_xlpm._rs,TRIM(UPPER(C16&"")),_xlpm._txt,TRIM(SUBSTITUTE(SUBSTITUTE(SUBSTITUTE(SUBSTITUTE(SUBSTITUTE(SUBSTITUTE(SUBSTITUTE(_xlpm._rs,".",""),","," "),"-"," "),"/"," "),"("," "),")"," "),":"," ")),_xlpm._pal,_xlfn.TEXTSPLIT(_xlpm._txt," "),_xlpm._util,_xlfn._xlws.FILTER(_xlpm._pal,ISERROR(MATCH(_xlpm._pal,{"DE";"DEL";"LA";"LAS";"EL";"LOS";"Y";"EN";"PARA";"POR";"CON";"A";"AL";"UN";"UNA";"UNOS";"UNAS"},0))),_xlpm._cod,IFERROR(_xlfn.TEXTJOIN("_",TRUE,LEFT(INDEX(_xlpm._util,1,_xlfn.SEQUENCE(1,MIN(5,COLUMNS(_xlpm._util)))),5)),""),IF(OR(_xlpm._nit="",UPPER(_xlpm._nit)="N/A",UPPER(_xlpm._nit)="NA",UPPER(_xlpm._nit)="SIN NIT",UPPER(_xlpm._nit)="NO APLICA",_xlpm._nit="0"),_xlpm._cod,_xlpm._nit))} -> 830033350-6 | C16: Corporación Educativa para el Aprendizaje Ltda. / CEPA | D16: TERCIARIO | F16: =IF(Tbla_entidades[[#This Row],[CIUU]]="","",_xlfn.XLOOKUP(Tbla_entidades[[#This Row],[CIUU]],Listas!$N:$N,Listas!$O:$O,"")) | G16: claudiancepa@yahoo.com/ fundacepa@gmail.com | H16: 2267414 | I16: Carrera 65A numero 94-76 | J16: Barrios Unidos | K16: Bogotá D.C. | L16: EN EJECUCIÓN | M16: PUJ-06688-19 | N16: 44805
A17: 830041897-6 | B17: {=_xlfn.LET(_xlpm._nit,TRIM(A17&""),_xlpm._rs,TRIM(UPPER(C17&"")),_xlpm._txt,TRIM(SUBSTITUTE(SUBSTITUTE(SUBSTITUTE(SUBSTITUTE(SUBSTITUTE(SUBSTITUTE(SUBSTITUTE(_xlpm._rs,".",""),","," "),"-"," "),"/"," "),"("," "),")"," "),":"," ")),_xlpm._pal,_xlfn.TEXTSPLIT(_xlpm._txt," "),_xlpm._util,_xlfn._xlws.FILTER(_xlpm._pal,ISERROR(MATCH(_xlpm._pal,{"DE";"DEL";"LA";"LAS";"EL";"LOS";"Y";"EN";"PARA";"POR";"CON";"A";"AL";"UN";"UNA";"UNOS";"UNAS"},0))),_xlpm._cod,IFERROR(_xlfn.TEXTJOIN("_",TRUE,LEFT(INDEX(_xlpm._util,1,_xlfn.SEQUENCE(1,MIN(5,COLUMNS(_xlpm._util)))),5)),""),IF(OR(_xlpm._nit="",UPPER(_xlpm._nit)="N/A",UPPER(_xlpm._nit)="NA",UPPER(_xlpm._nit)="SIN NIT",UPPER(_xlpm._nit)="NO APLICA",_xlpm._nit="0"),_xlpm._cod,_xlpm._nit))} -> 830041897-6 | C17: Colegio Nueva Esperanza I. E. D. | D17: TERCIARIO | E17: 8521 | F17: =IF(Tbla_entidades[[#This Row],[CIUU]]="","",_xlfn.XLOOKUP(Tbla_entidades[[#This Row],[CIUU]],Listas!$N:$N,Listas!$O:$O,"")) -> Educación básica secundaria. | G17: cednvaesperanza5@educacionbogota.edu.co | H17: Sede A: (601)3654900 - Sede B: (601) 3653777 - 3653888 | I17: Carrera 14 B Este Nº 76 - 59 sur | J17: Usme | K17: Bogotá D.C. | L17: EN EJECUCIÓN | M17: PUJ-01422-23 | N17: 46821
A18: 830062520-5 | B18: {=_xlfn.LET(_xlpm._nit,TRIM(A18&""),_xlpm._rs,TRIM(UPPER(C18&"")),_xlpm._txt,TRIM(SUBSTITUTE(SUBSTITUTE(SUBSTITUTE(SUBSTITUTE(SUBSTITUTE(SUBSTITUTE(SUBSTITUTE(_xlpm._rs,".",""),","," "),"-"," "),"/"," "),"("," "),")"," "),":"," ")),_xlpm._pal,_xlfn.TEXTSPLIT(_xlpm._txt," "),_xlpm._util,_xlfn._xlws.FILTER(_xlpm._pal,ISERROR(MATCH(_xlpm._pal,{"DE";"DEL";"LA";"LAS";"EL";"LOS";"Y";"EN";"PARA";"POR";"CON";"A";"AL";"UN";"UNA";"UNOS";"UNAS"},0))),_xlpm._cod,IFERROR(_xlfn.TEXTJOIN("_",TRUE,LEFT(INDEX(_xlpm._util,1,_xlfn.SEQUENCE(1,MIN(5,COLUMNS(_xlpm._util)))),5)),""),IF(OR(_xlpm._nit="",UPPER(_xlpm._nit)="N/A",UPPER(_xlpm._nit)="NA",UPPER(_xlpm._nit)="SIN NIT",UPPER(_xlpm._nit)="NO APLICA",_xlpm._nit="0"),_xlpm._cod,_xlpm._nit))} -> 830062520-5 | C18: Junta de Acción Comunal Barrio Doña Liliana | D18: CUATERNARIO | F18: =IF(Tbla_entidades[[#This Row],[CIUU]]="","",_xlfn.XLOOKUP(Tbla_entidades[[#This Row],[CIUU]],Listas!$N:$N,Listas!$O:$O,"")) | G18: barrio.d.liliana5@gmail.com | H18: 3202008232 | I18: KR 11 D ESTE 79 B 46 SUR | J18: Usme | K18: Bogotá D.C. | L18: EN EJECUCIÓN | M18: PUJ-00990-23 | N18: 20/02/2028
A19: 830078970-6 | B19: {=_xlfn.LET(_xlpm._nit,TRIM(A19&""),_xlpm._rs,TRIM(UPPER(C19&"")),_xlpm._txt,TRIM(SUBSTITUTE(SUBSTITUTE(SUBSTITUTE(SUBSTITUTE(SUBSTITUTE(SUBSTITUTE(SUBSTITUTE(_xlpm._rs,".",""),","," "),"-"," "),"/"," "),"("," "),")"," "),":"," ")),_xlpm._pal,_xlfn.TEXTSPLIT(_xlpm._txt," "),_xlpm._util,_xlfn._xlws.FILTER(_xlpm._pal,ISERROR(MATCH(_xlpm._pal,{"DE";"DEL";"LA";"LAS";"EL";"LOS";"Y";"EN";"PARA";"POR";"CON";"A";"AL";"UN";"UNA";"UNOS";"UNAS"},0))),_xlpm._cod,IFERROR(_xlfn.TEXTJOIN("_",TRUE,LEFT(INDEX(_xlpm._util,1,_xlfn.SEQUENCE(1,MIN(5,COLUMNS(_xlpm._util)))),5)),""),IF(OR(_xlpm._nit="",UPPER(_xlpm._nit)="N/A",UPPER(_xlpm._nit)="NA",UPPER(_xlpm._nit)="SIN NIT",UPPER(_xlpm._nit)="NO APLICA",_xlpm._nit="0"),_xlpm._cod,_xlpm._nit))} -> 830078970-6 | C19: Asociación Colombiana de Personas con Esquizofrenia y sus Familias - ACPEF | D19: CUATERNARIO | E19: 9499 | F19: =IF(Tbla_entidades[[#This Row],[CIUU]]="","",_xlfn.XLOOKUP(Tbla_entidades[[#This Row],[CIUU]],Listas!$N:$N,Listas!$O:$O,"")) -> Actividades de otras asociaciones n.c.p. | G19: secretaria.acpef@gmail.com | H19: 3112783080 | I19: Calle 52A No. 27A-54 | J19: Teusaquillo | K19: Bogotá D.C. | L19: EN EJECUCIÓN | M19: PUJ-04941-19 | N19: 44767
A20: 830079131-8 | B20: {=_xlfn.LET(_xlpm._nit,TRIM(A20&""),_xlpm._rs,TRIM(UPPER(C20&"")),_xlpm._txt,TRIM(SUBSTITUTE(SUBSTITUTE(SUBSTITUTE(SUBSTITUTE(SUBSTITUTE(SUBSTITUTE(SUBSTITUTE(_xlpm._rs,".",""),","," "),"-"," "),"/"," "),"("," "),")"," "),":"," ")),_xlpm._pal,_xlfn.TEXTSPLIT(_xlpm._txt," "),_xlpm._util,_xlfn._xlws.FILTER(_xlpm._pal,ISERROR(MATCH(_xlpm._pal,{"DE";"DEL";"LA";"LAS";"EL";"LOS";"Y";"EN";"PARA";"POR";"CON";"A";"AL";"UN";"UNA";"UNOS";"UNAS"},0))),_xlpm._cod,IFERROR(_xlfn.TEXTJOIN("_",TRUE,LEFT(INDEX(_xlpm._util,1,_xlfn.SEQUENCE(1,MIN(5,COLUMNS(_xlpm._util)))),5)),""),IF(OR(_xlpm._nit="",UPPER(_xlpm._nit)="N/A",UPPER(_xlpm._nit)="NA",UPPER(_xlpm._nit)="SIN NIT",UPPER(_xlpm._nit)="NO APLICA",_xlpm._nit="0"),_xlpm._cod,_xlpm._nit))} -> 830079131-8 | C20: Colegio Instituto Técnico Distrital Julio Flórez | D20: TERCIARIO | E20: 8521 | F20: =IF(Tbla_entidades[[#This Row],[CIUU]]="","",_xlfn.XLOOKUP(Tbla_entidades[[#This Row],[CIUU]],Listas!$N:$N,Listas!$O:$O,"")) -> Educación básica secundaria. | G20: cedjulioflorez11@educacionbogota.edu.co | H20: 3057923922 | I20: Carrera 68B # 94-12 | J20: Suba | K20: Bogotá D.C. | L20: SIN CONVENIO
A21: 830086601-7 | B21: {=_xlfn.LET(_xlpm._nit,TRIM(A21&""),_xlpm._rs,TRIM(UPPER(C21&"")),_xlpm._txt,TRIM(SUBSTITUTE(SUBSTITUTE(SUBSTITUTE(SUBSTITUTE(SUBSTITUTE(SUBSTITUTE(SUBSTITUTE(_xlpm._rs,".",""),","," "),"-"," "),"/"," "),"("," "),")"," "),":"," ")),_xlpm._pal,_xlfn.TEXTSPLIT(_xlpm._txt," "),_xlpm._util,_xlfn._xlws.FILTER(_xlpm._pal,ISERROR(MATCH(_xlpm._pal,{"DE";"DEL";"LA";"LAS";"EL";"LOS";"Y";"EN";"PARA";"POR";"CON";"A";"AL";"UN";"UNA";"UNOS";"UNAS"},0))),_xlpm._cod,IFERROR(_xlfn.TEXTJOIN("_",TRUE,LEFT(INDEX(_xlpm._util,1,_xlfn.SEQUENCE(1,MIN(5,COLUMNS(_xlpm._util)))),5)),""),IF(OR(_xlpm._nit="",UPPER(_xlpm._nit)="N/A",UPPER(_xlpm._nit)="NA",UPPER(_xlpm._nit)="SIN NIT",UPPER(_xlpm._nit)="NO APLICA",_xlpm._nit="0"),_xlpm._cod,_xlpm._nit))} -> 830086601-7 | C21: Fundación Banco Arquidiocesano de Alimentos | D21: CUATERNARIO | F21: =IF(Tbla_entidades[[#This Row],[CIUU]]="","",_xlfn.XLOOKUP(Tbla_entidades[[#This Row],[CIUU]],Listas!$N:$N,Listas!$O:$O,"")) | G21: amigo@bancodealiemntos.org.co | H21: 7470828 | I21: Calle 19a # 32-50 | J21: Puente Aranda | K21: Bogotá D.C. | L21: EN EJECUCIÓN | M21: PUJ-05642-19 | N21: 44771
A22: 830098811-9 | B22: {=_xlfn.LET(_xlpm._nit,TRIM(A22&""),_xlpm._rs,TRIM(UPPER(C22&"")),_xlpm._txt,TRIM(SUBSTITUTE(SUBSTITUTE(SUBSTITUTE(SUBSTITUTE(SUBSTITUTE(SUBSTITUTE(SUBSTITUTE(_xlpm._rs,".",""),","," "),"-"," "),"/"," "),"("," "),")"," "),":"," ")),_xlpm._pal,_xlfn.TEXTSPLIT(_xlpm._txt," "),_xlpm._util,_xlfn._xlws.FILTER(_xlpm._pal,ISERROR(MATCH(_xlpm._pal,{"DE";"DEL";"LA";"LAS";"EL";"LOS";"Y";"EN";"PARA";"POR";"CON";"A";"AL";"UN";"UNA";"UNOS";"UNAS"},0))),_xlpm._cod,IFERROR(_xlfn.TEXTJOIN("_",TRUE,LEFT(INDEX(_xlpm._util,1,_xlfn.SEQUENCE(1,MIN(5,COLUMNS(_xlpm._util)))),5)),""),IF(OR(_xlpm._nit="",UPPER(_xlpm._nit)="N/A",UPPER(_xlpm._nit)="NA",UPPER(_xlpm._nit)="SIN NIT",UPPER(_xlpm._nit)="NO APLICA",_xlpm._nit="0"),_xlpm._cod,_xlpm._nit))} -> 830098811-9 | C22: Fundación Libérate | D22: CUATERNARIO | F22: =IF(Tbla_entidades[[#This Row],[CIUU]]="","",_xlfn.XLOOKUP(Tbla_entidades[[#This Row],[CIUU]],Listas!$N:$N,Listas!$O:$O,"")) | G22: info@fundacionliberate.org.co | H22: 6854670 | I22: Trv 77 N 166-40 | J22: Suba | K22: Bogotá D.C. | L22: EN EJECUCIÓN | M22: PUJ-05639-19 | N22: 44771
A23: 830099276-2 | B23: {=_xlfn.LET(_xlpm._nit,TRIM(A23&""),_xlpm._rs,TRIM(UPPER(C23&"")),_xlpm._txt,TRIM(SUBSTITUTE(SUBSTITUTE(SUBSTITUTE(SUBSTITUTE(SUBSTITUTE(SUBSTITUTE(SUBSTITUTE(_xlpm._rs,".",""),","," "),"-"," "),"/"," "),"("," "),")"," "),":"," ")),_xlpm._pal,_xlfn.TEXTSPLIT(_xlpm._txt," "),_xlpm._util,_xlfn._xlws.FILTER(_xlpm._pal,ISERROR(MATCH(_xlpm._pal,{"DE";"DEL";"LA";"LAS";"EL";"LOS";"Y";"EN";"PARA";"POR";"CON";"A";"AL";"UN";"UNA";"UNOS";"UNAS"},0))),_xlpm._cod,IFERROR(_xlfn.TEXTJOIN("_",TRUE,LEFT(INDEX(_xlpm._util,1,_xlfn.SEQUENCE(1,MIN(5,COLUMNS(_xlpm._util)))),5)),""),IF(OR(_xlpm._nit="",UPPER(_xlpm._nit)="N/A",UPPER(_xlpm._nit)="NA",UPPER(_xlpm._nit)="SIN NIT",UPPER(_xlpm._nit)="NO APLICA",_xlpm._nit="0"),_xlpm._cod,_xlpm._nit))} -> 830099276-2 | C23: Corporación Vida en Acción Social | D23: CUATERNARIO | F23: =IF(Tbla_entidades[[#This Row],[CIUU]]="","",_xlfn.XLOOKUP(Tbla_entidades[[#This Row],[CIUU]],Listas!$N:$N,Listas!$O:$O,"")) | G23: fundmisionvida@gmail.com / misionvida@pastoralsocialenaccion.org / direccion@pastoralsocialenaccion.org / misionvida@pastoralsocialenaccion.org | H23: 3514207 | I23: Cll 1F No. 31-11 | J23: Puente Aranda | K23: Bogotá D.C. | L23: EN EJECUCIÓN | M23: PUJ-04954-19 | N23: 44767
A24: 830100437-5 | B24: {=_xlfn.LET(_xlpm._nit,TRIM(A24&""),_xlpm._rs,TRIM(UPPER(C24&"")),_xlpm._txt,TRIM(SUBSTITUTE(SUBSTITUTE(SUBSTITUTE(SUBSTITUTE(SUBSTITUTE(SUBSTITUTE(SUBSTITUTE(_xlpm._rs,".",""),","," "),"-"," "),"/"," "),"("," "),")"," "),":"," ")),_xlpm._pal,_xlfn.TEXTSPLIT(_xlpm._txt," "),_xlpm._util,_xlfn._xlws.FILTER(_xlpm._pal,ISERROR(MATCH(_xlpm._pal,{"DE";"DEL";"LA";"LAS";"EL";"LOS";"Y";"EN";"PARA";"POR";"CON";"A";"AL";"UN";"UNA";"UNOS";"UNAS"},0))),_xlpm._cod,IFERROR(_xlfn.TEXTJOIN("_",TRUE,LEFT(INDEX(_xlpm._util,1,_xlfn.SEQUENCE(1,MIN(5,COLUMNS(_xlpm._util)))),5)),""),IF(OR(_xlpm._nit="",UPPER(_xlpm._nit)="N/A",UPPER(_xlpm._nit)="NA",UPPER(_xlpm._nit)="SIN NIT",UPPER(_xlpm._nit)="NO APLICA",_xlpm._nit="0"),_xlpm._cod,_xlpm._nit))} -> 830100437-5 | C24: Institución Educativa Distrital Costa Rica | D24: TERCIARIO | E24: 8521 | F24: =IF(Tbla_entidades[[#This Row],[CIUU]]="","",_xlfn.XLOOKUP(Tbla_entidades[[#This Row],[CIUU]],Listas!$N:$N,Listas!$O:$O,"")) -> Educación básica secundaria. | G24: colderepdecostaric@aducacionbogota.edu.co | H24: 4184079 | I24: Cra 101 #23-42 | J24: Fontibón | K24: Bogotá D.C. | L24: EN EJECUCIÓN | M24: PUJ-05643-19 | N24: 44771 | O24: Otro convenio: PUJ-00976-19
A25: 830110396-4 | B25: {=_xlfn.LET(_xlpm._nit,TRIM(A25&""),_xlpm._rs,TRIM(UPPER(C25&"")),_xlpm._txt,TRIM(SUBSTITUTE(SUBSTITUTE(SUBSTITUTE(SUBSTITUTE(SUBSTITUTE(SUBSTITUTE(SUBSTITUTE(_xlpm._rs,".",""),","," "),"-"," "),"/"," "),"("," "),")"," "),":"," ")),_xlpm._pal,_xlfn.TEXTSPLIT(_xlpm._txt," "),_xlpm._util,_xlfn._xlws.FILTER(_xlpm._pal,ISERROR(MATCH(_xlpm._pal,{"DE";"DEL";"LA";"LAS";"EL";"LOS";"Y";"EN";"PARA";"POR";"CON";"A";"AL";"UN";"UNA";"UNOS";"UNAS"},0))),_xlpm._cod,IFERROR(_xlfn.TEXTJOIN("_",TRUE,LEFT(INDEX(_xlpm._util,1,_xlfn.SEQUENCE(1,MIN(5,COLUMNS(_xlpm._util)))),5)),""),IF(OR(_xlpm._nit="",UPPER(_xlpm._nit)="N/A",UPPER(_xlpm._nit)="NA",UPPER(_xlpm._nit)="SIN NIT",UPPER(_xlpm._nit)="NO APLICA",_xlpm._nit="0"),_xlpm._cod,_xlpm._nit))} -> 830110396-4 | C25: Colegio Ciudad de Bogotá I. E. D. | D25: TERCIARIO | E25: 8521 | F25: =IF(Tbla_entidades[[#This Row],[CIUU]]="","",_xlfn.XLOOKUP(Tbla_entidades[[#This Row],[CIUU]],Listas!$N:$N,Listas!$O:$O,"")) -> Educación básica secundaria. | G25: coldiciudaddebog6@educacionbogota.edu.co | H25: 2389888 | I25: Cra 25 #53B-32 sur | J25: Tunjuelito | K25: Bogotá D.C. | L25: EN EJECUCIÓN | M25: PUJ-01103-18 | N25: 44249
A26: 830128181-7 | B26: {=_xlfn.LET(_xlpm._nit,TRIM(A26&""),_xlpm._rs,TRIM(UPPER(C26&"")),_xlpm._txt,TRIM(SUBSTITUTE(SUBSTITUTE(SUBSTITUTE(SUBSTITUTE(SUBSTITUTE(SUBSTITUTE(SUBSTITUTE(_xlpm._rs,".",""),","," "),"-"," "),"/"," "),"("," "),")"," "),":"," ")),_xlpm._pal,_xlfn.TEXTSPLIT(_xlpm._txt," "),_xlpm._util,_xlfn._xlws.FILTER(_xlpm._pal,ISERROR(MATCH(_xlpm._pal,{"DE";"DEL";"LA";"LAS";"EL";"LOS";"Y";"EN";"PARA";"POR";"CON";"A";"AL";"UN";"UNA";"UNOS";"UNAS"},0))),_xlpm._cod,IFERROR(_xlfn.TEXTJOIN("_",TRUE,LEFT(INDEX(_xlpm._util,1,_xlfn.SEQUENCE(1,MIN(5,COLUMNS(_xlpm._util)))),5)),""),IF(OR(_xlpm._nit="",UPPER(_xlpm._nit)="N/A",UPPER(_xlpm._nit)="NA",UPPER(_xlpm._nit)="SIN NIT",UPPER(_xlpm._nit)="NO APLICA",_xlpm._nit="0"),_xlpm._cod,_xlpm._nit))} -> 830128181-7 | C26: Fundación Buena Semilla | D26: CUATERNARIO | F26: =IF(Tbla_entidades[[#This Row],[CIUU]]="","",_xlfn.XLOOKUP(Tbla_entidades[[#This Row],[CIUU]],Listas!$N:$N,Listas!$O:$O,"")) | I26: Calle 10 #4a-22 este | J26: Santa Fé | K26: Bogotá D.C. | L26: SIN CONVENIO | M26: N/A | N26: N/A
A27: 83013076-4 | B27: {=_xlfn.LET(_xlpm._nit,TRIM(A27&""),_xlpm._rs,TRIM(UPPER(C27&"")),_xlpm._txt,TRIM(SUBSTITUTE(SUBSTITUTE(SUBSTITUTE(SUBSTITUTE(SUBSTITUTE(SUBSTITUTE(SUBSTITUTE(_xlpm._rs,".",""),","," "),"-"," "),"/"," "),"("," "),")"," "),":"," ")),_xlpm._pal,_xlfn.TEXTSPLIT(_xlpm._txt," "),_xlpm._util,_xlfn._xlws.FILTER(_xlpm._pal,ISERROR(MATCH(_xlpm._pal,{"DE";"DEL";"LA";"LAS";"EL";"LOS";"Y";"EN";"PARA";"POR";"CON";"A";"AL";"UN";"UNA";"UNOS";"UNAS"},0))),_xlpm._cod,IFERROR(_xlfn.TEXTJOIN("_",TRUE,LEFT(INDEX(_xlpm._util,1,_xlfn.SEQUENCE(1,MIN(5,COLUMNS(_xlpm._util)))),5)),""),IF(OR(_xlpm._nit="",UPPER(_xlpm._nit)="N/A",UPPER(_xlpm._nit)="NA",UPPER(_xlpm._nit)="SIN NIT",UPPER(_xlpm._nit)="NO APLICA",_xlpm._nit="0"),_xlpm._cod,_xlpm._nit))} -> 83013076-4 | C27: Prana Incubadora | D27: CUATERNARIO | F27: =IF(Tbla_entidades[[#This Row],[CIUU]]="","",_xlfn.XLOOKUP(Tbla_entidades[[#This Row],[CIUU]],Listas!$N:$N,Listas!$O:$O,"")) | G27: pranainc@gmail.com | H27: 2488081 | I27: Calle 69 # 4-97 | J27: Chapinero | K27: Bogotá D.C. | L27: EN EJECUCIÓN | M27: PUJ-04964-19 | N27: 44767
A28: 830137451-9 | B28: {=_xlfn.LET(_xlpm._nit,TRIM(A28&""),_xlpm._rs,TRIM(UPPER(C28&"")),_xlpm._txt,TRIM(SUBSTITUTE(SUBSTITUTE(SUBSTITUTE(SUBSTITUTE(SUBSTITUTE(SUBSTITUTE(SUBSTITUTE(_xlpm._rs,".",""),","," "),"-"," "),"/"," "),"("," "),")"," "),":"," ")),_xlpm._pal,_xlfn.TEXTSPLIT(_xlpm._txt," "),_xlpm._util,_xlfn._xlws.FILTER(_xlpm._pal,ISERROR(MATCH(_xlpm._pal,{"DE";"DEL";"LA";"LAS";"EL";"LOS";"Y";"EN";"PARA";"POR";"CON";"A";"AL";"UN";"UNA";"UNOS";"UNAS"},0))),_xlpm._cod,IFERROR(_xlfn.TEXTJOIN("_",TRUE,LEFT(INDEX(_xlpm._util,1,_xlfn.SEQUENCE(1,MIN(5,COLUMNS(_xlpm._util)))),5)),""),IF(OR(_xlpm._nit="",UPPER(_xlpm._nit)="N/A",UPPER(_xlpm._nit)="NA",UPPER(_xlpm._nit)="SIN NIT",UPPER(_xlpm._nit)="NO APLICA",_xlpm._nit="0"),_xlpm._cod,_xlpm._nit))} -> 830137451-9 | C28: Fundación Proyecto Unión | D28: CUATERNARIO | F28: =IF(Tbla_entidades[[#This Row],[CIUU]]="","",_xlfn.XLOOKUP(Tbla_entidades[[#This Row],[CIUU]],Listas!$N:$N,Listas!$O:$O,"")) | G28: gestionhumana@proyectounion.org | H28: 6012719841 | I28: Carrera 5 No. 67-74 | J28: Chapinero | K28: Bogotá D.C. | L28: EN EJECUCIÓN | M28: PUJ-04959-19 | N28: 44767
A29: 830145234-0 | B29: {=_xlfn.LET(_xlpm._nit,TRIM(A29&""),_xlpm._rs,TRIM(UPPER(C29&"")),_xlpm._txt,TRIM(SUBSTITUTE(SUBSTITUTE(SUBSTITUTE(SUBSTITUTE(SUBSTITUTE(SUBSTITUTE(SUBSTITUTE(_xlpm._rs,".",""),","," "),"-"," "),"/"," "),"("," "),")"," "),":"," ")),_xlpm._pal,_xlfn.TEXTSPLIT(_xlpm._txt," "),_xlpm._util,_xlfn._xlws.FILTER(_xlpm._pal,ISERROR(MATCH(_xlpm._pal,{"DE";"DEL";"LA";"LAS";"EL";"LOS";"Y";"EN";"PARA";"POR";"CON";"A";"AL";"UN";"UNA";"UNOS";"UNAS"},0))),_xlpm._cod,IFERROR(_xlfn.TEXTJOIN("_",TRUE,LEFT(INDEX(_xlpm._util,1,_xlfn.SEQUENCE(1,MIN(5,COLUMNS(_xlpm._util)))),5)),""),IF(OR(_xlpm._nit="",UPPER(_xlpm._nit)="N/A",UPPER(_xlpm._nit)="NA",UPPER(_xlpm._nit)="SIN NIT",UPPER(_xlpm._nit)="NO APLICA",_xlpm._nit="0"),_xlpm._cod,_xlpm._nit))} -> 830145234-0 | C29: Asociación de Productores Rurales de Sumapaz | D29: PRIMARIO | E29: 1040 | F29: =IF(Tbla_entidades[[#This Row],[CIUU]]="","",_xlfn.XLOOKUP(Tbla_entidades[[#This Row],[CIUU]],Listas!$N:$N,Listas!$O:$O,"")) -> Elaboración de productos lácteos. | G29: procamsu@hotmail.com | H29: 3114868733 | I29: VEREDA LAS AURAS CORREGIMIENTO DE NAZARETH | J29: Sumapaz | K29: Bogotá D.C. | L29: EN EJECUCIÓN | M29: PUJ-01132-25 | N29: 46838
A30: 860005813-4 | B30: {=_xlfn.LET(_xlpm._nit,TRIM(A30&""),_xlpm._rs,TRIM(UPPER(C30&"")),_xlpm._txt,TRIM(SUBSTITUTE(SUBSTITUTE(SUBSTITUTE(SUBSTITUTE(SUBSTITUTE(SUBSTITUTE(SUBSTITUTE(_xlpm._rs,".",""),","," "),"-"," "),"/"," "),"("," "),")"," "),":"," ")),_xlpm._pal,_xlfn.TEXTSPLIT(_xlpm._txt," "),_xlpm._util,_xlfn._xlws.FILTER(_xlpm._pal,ISERROR(MATCH(_xlpm._pal,{"DE";"DEL";"LA";"LAS";"EL";"LOS";"Y";"EN";"PARA";"POR";"CON";"A";"AL";"UN";"UNA";"UNOS";"UNAS"},0))),_xlpm._cod,IFERROR(_xlfn.TEXTJOIN("_",TRUE,LEFT(INDEX(_xlpm._util,1,_xlfn.SEQUENCE(1,MIN(5,COLUMNS(_xlpm._util)))),5)),""),IF(OR(_xlpm._nit="",UPPER(_xlpm._nit)="N/A",UPPER(_xlpm._nit)="NA",UPPER(_xlpm._nit)="SIN NIT",UPPER(_xlpm._nit)="NO APLICA",_xlpm._nit="0"),_xlpm._cod,_xlpm._nit))} -> 860005813-4 | C30: Pontificia Universidad Javeriana - Programa Vidas Móviles | D30: CUATERNARIO | F30: =IF(Tbla_entidades[[#This Row],[CIUU]]="","",_xlfn.XLOOKUP(Tbla_entidades[[#This Row],[CIUU]],Listas!$N:$N,Listas!$O:$O,"")) | G30: vidas.moviles@javeriana.edu.co | H30: 7151213 / 3152244400 | I30: Calle 78 a sur #38-31 | J30: Ciudad Bolivar | K30: Bogotá D.C. | L30: EN EJECUCIÓN | M30: N/A | N30: N/A
A31: 860006705-1 | B31: {=_xlfn.LET(_xlpm._nit,TRIM(A31&""),_xlpm._rs,TRIM(UPPER(C31&"")),_xlpm._txt,TRIM(SUBSTITUTE(SUBSTITUTE(SUBSTITUTE(SUBSTITUTE(SUBSTITUTE(SUBSTITUTE(SUBSTITUTE(_xlpm._rs,".",""),","," "),"-"," "),"/"," "),"("," "),")"," "),":"," ")),_xlpm._pal,_xlfn.TEXTSPLIT(_xlpm._txt," "),_xlpm._util,_xlfn._xlws.FILTER(_xlpm._pal,ISERROR(MATCH(_xlpm._pal,{"DE";"DEL";"LA";"LAS";"EL";"LOS";"Y";"EN";"PARA";"POR";"CON";"A";"AL";"UN";"UNA";"UNOS";"UNAS"},0))),_xlpm._cod,IFERROR(_xlfn.TEXTJOIN("_",TRUE,LEFT(INDEX(_xlpm._util,1,_xlfn.SEQUENCE(1,MIN(5,COLUMNS(_xlpm._util)))),5)),""),IF(OR(_xlpm._nit="",UPPER(_xlpm._nit)="N/A",UPPER(_xlpm._nit)="NA",UPPER(_xlpm._nit)="SIN NIT",UPPER(_xlpm._nit)="NO APLICA",_xlpm._nit="0"),_xlpm._cod,_xlpm._nit))} -> 860006705-1 | C31: Fundación Jorge Otero de Francisco y María Liévano de Otero | F31: =IF(Tbla_entidades[[#This Row],[CIUU]]="","",_xlfn.XLOOKUP(Tbla_entidades[[#This Row],[CIUU]],Listas!$N:$N,Listas!$O:$O,"")) | I31: Carrera 90 147C-32, Suba | J31: Suba | K31: Bogotá D.C. | L31: EN EJECUCIÓN
A32: 860007627-1 | B32: {=_xlfn.LET(_xlpm._nit,TRIM(A32&""),_xlpm._rs,TRIM(UPPER(C32&"")),_xlpm._txt,TRIM(SUBSTITUTE(SUBSTITUTE(SUBSTITUTE(SUBSTITUTE(SUBSTITUTE(SUBSTITUTE(SUBSTITUTE(_xlpm._rs,".",""),","," "),"-"," "),"/"," "),"("," "),")"," "),":"," ")),_xlpm._pal,_xlfn.TEXTSPLIT(_xlpm._txt," "),_xlpm._util,_xlfn._xlws.FILTER(_xlpm._pal,ISERROR(MATCH(_xlpm._pal,{"DE";"DEL";"LA";"LAS";"EL";"LOS";"Y";"EN";"PARA";"POR";"CON";"A";"AL";"UN";"UNA";"UNOS";"UNAS"},0))),_xlpm._cod,IFERROR(_xlfn.TEXTJOIN("_",TRUE,LEFT(INDEX(_xlpm._util,1,_xlfn.SEQUENCE(1,MIN(5,COLUMNS(_xlpm._util)))),5)),""),IF(OR(_xlpm._nit="",UPPER(_xlpm._nit)="N/A",UPPER(_xlpm._nit)="NA",UPPER(_xlpm._nit)="SIN NIT",UPPER(_xlpm._nit)="NO APLICA",_xlpm._nit="0"),_xlpm._cod,_xlpm._nit))} -> 860007627-1 | C32: Compañía de Jesús | D32: CUATERNARIO | F32: =IF(Tbla_entidades[[#This Row],[CIUU]]="","",_xlfn.XLOOKUP(Tbla_entidades[[#This Row],[CIUU]],Listas!$N:$N,Listas!$O:$O,"")) | G32: casapastoralaltosdelaflorida@gmail.com | I32: Cra 31 este n. 5-8 Altos de la Floria Suacha (Soacha) | J32: Altos De La Florida | K32: Bogotá D.C. | L32: SIN CONVENIO | M32: N/A | N32: N/A | O32: Casa Pastoral Altos de la Florida
A33: 860010371-0 | B33: {=_xlfn.LET(_xlpm._nit,TRIM(A33&""),_xlpm._rs,TRIM(UPPER(C33&"")),_xlpm._txt,TRIM(SUBSTITUTE(SUBSTITUTE(SUBSTITUTE(SUBSTITUTE(SUBSTITUTE(SUBSTITUTE(SUBSTITUTE(_xlpm._rs,".",""),","," "),"-"," "),"/"," "),"("," "),")"," "),":"," ")),_xlpm._pal,_xlfn.TEXTSPLIT(_xlpm._txt," "),_xlpm._util,_xlfn._xlws.FILTER(_xlpm._pal,ISERROR(MATCH(_xlpm._pal,{"DE";"DEL";"LA";"LAS";"EL";"LOS";"Y";"EN";"PARA";"POR";"CON";"A";"AL";"UN";"UNA";"UNOS";"UNAS"},0))),_xlpm._cod,IFERROR(_xlfn.TEXTJOIN("_",TRUE,LEFT(INDEX(_xlpm._util,1,_xlfn.SEQUENCE(1,MIN(5,COLUMNS(_xlpm._util)))),5)),""),IF(OR(_xlpm._nit="",UPPER(_xlpm._nit)="N/A",UPPER(_xlpm._nit)="NA",UPPER(_xlpm._nit)="SIN NIT",UPPER(_xlpm._nit)="NO APLICA",_xlpm._nit="0"),_xlpm._cod,_xlpm._nit))} -> 860010371-0 | C33: Corporación El Minuto de Dios | D33: TERCIARIO | F33: =IF(Tbla_entidades[[#This Row],[CIUU]]="","",_xlfn.XLOOKUP(Tbla_entidades[[#This Row],[CIUU]],Listas!$N:$N,Listas!$O:$O,"")) | G33: contacto@minutodedios.org. | H33: 5874441 | I33: Calle 81A Nº 73A-22 | J33: Engativa | K33: Bogotá D.C. | L33: EN EJECUCIÓN | M33: PUJ-06682-21 | N33: 46272
A34: 860013475-1 | B34: {=_xlfn.LET(_xlpm._nit,TRIM(A34&""),_xlpm._rs,TRIM(UPPER(C34&"")),_xlpm._txt,TRIM(SUBSTITUTE(SUBSTITUTE(SUBSTITUTE(SUBSTITUTE(SUBSTITUTE(SUBSTITUTE(SUBSTITUTE(_xlpm._rs,".",""),","," "),"-"," "),"/"," "),"("," "),")"," "),":"," ")),_xlpm._pal,_xlfn.TEXTSPLIT(_xlpm._txt," "),_xlpm._util,_xlfn._xlws.FILTER(_xlpm._pal,ISERROR(MATCH(_xlpm._pal,{"DE";"DEL";"LA";"LAS";"EL";"LOS";"Y";"EN";"PARA";"POR";"CON";"A";"AL";"UN";"UNA";"UNOS";"UNAS"},0))),_xlpm._cod,IFERROR(_xlfn.TEXTJOIN("_",TRUE,LEFT(INDEX(_xlpm._util,1,_xlfn.SEQUENCE(1,MIN(5,COLUMNS(_xlpm._util)))),5)),""),IF(OR(_xlpm._nit="",UPPER(_xlpm._nit)="N/A",UPPER(_xlpm._nit)="NA",UPPER(_xlpm._nit)="SIN NIT",UPPER(_xlpm._nit)="NO APLICA",_xlpm._nit="0"),_xlpm._cod,_xlpm._nit))} -> 860013475-1 | C34: Hermanas de San Juan Evangelista | D34: CUATERNARIO | F34: =IF(Tbla_entidades[[#This Row],[CIUU]]="","",_xlfn.XLOOKUP(Tbla_entidades[[#This Row],[CIUU]],Listas!$N:$N,Listas!$O:$O,"")) | G34: juanistashogarsanjose@gmail.com | I34: Tv. 22 Bis #61B- 29 | J34: Teusaquillo | K34: Bogotá D.C. | L34: EN EJECUCIÓN | M34: PUJ-01455-21 | N34: 45375
A35: 860015536-1 | B35: {=_xlfn.LET(_xlpm._nit,TRIM(A35&""),_xlpm._rs,TRIM(UPPER(C35&"")),_xlpm._txt,TRIM(SUBSTITUTE(SUBSTITUTE(SUBSTITUTE(SUBSTITUTE(SUBSTITUTE(SUBSTITUTE(SUBSTITUTE(_xlpm._rs,".",""),","," "),"-"," "),"/"," "),"("," "),")"," "),":"," ")),_xlpm._pal,_xlfn.TEXTSPLIT(_xlpm._txt," "),_xlpm._util,_xlfn._xlws.FILTER(_xlpm._pal,ISERROR(MATCH(_xlpm._pal,{"DE";"DEL";"LA";"LAS";"EL";"LOS";"Y";"EN";"PARA";"POR";"CON";"A";"AL";"UN";"UNA";"UNOS";"UNAS"},0))),_xlpm._cod,IFERROR(_xlfn.TEXTJOIN("_",TRUE,LEFT(INDEX(_xlpm._util,1,_xlfn.SEQUENCE(1,MIN(5,COLUMNS(_xlpm._util)))),5)),""),IF(OR(_xlpm._nit="",UPPER(_xlpm._nit)="N/A",UPPER(_xlpm._nit)="NA",UPPER(_xlpm._nit)="SIN NIT",UPPER(_xlpm._nit)="NO APLICA",_xlpm._nit="0"),_xlpm._cod,_xlpm._nit))} -> 860015536-1 | C35: Hospital San Ignacio | D35: CUATERNARIO | F35: =IF(Tbla_entidades[[#This Row],[CIUU]]="","",_xlfn.XLOOKUP(Tbla_entidades[[#This Row],[CIUU]],Listas!$N:$N,Listas!$O:$O,"")) | I35: Kra 7 No. 40-62 | J35: Chapinero | K35: Bogotá D.C. | L35: EN EJECUCIÓN | M35: PUJ-06062-19 | N35: 44784
A36: 860016941-6 | B36: {=_xlfn.LET(_xlpm._nit,TRIM(A36&""),_xlpm._rs,TRIM(UPPER(C36&"")),_xlpm._txt,TRIM(SUBSTITUTE(SUBSTITUTE(SUBSTITUTE(SUBSTITUTE(SUBSTITUTE(SUBSTITUTE(SUBSTITUTE(_xlpm._rs,".",""),","," "),"-"," "),"/"," "),"("," "),")"," "),":"," ")),_xlpm._pal,_xlfn.TEXTSPLIT(_xlpm._txt," "),_xlpm._util,_xlfn._xlws.FILTER(_xlpm._pal,ISERROR(MATCH(_xlpm._pal,{"DE";"DEL";"LA";"LAS";"EL";"LOS";"Y";"EN";"PARA";"POR";"CON";"A";"AL";"UN";"UNA";"UNOS";"UNAS"},0))),_xlpm._cod,IFERROR(_xlfn.TEXTJOIN("_",TRUE,LEFT(INDEX(_xlpm._util,1,_xlfn.SEQUENCE(1,MIN(5,COLUMNS(_xlpm._util)))),5)),""),IF(OR(_xlpm._nit="",UPPER(_xlpm._nit)="N/A",UPPER(_xlpm._nit)="NA",UPPER(_xlpm._nit)="SIN NIT",UPPER(_xlpm._nit)="NO APLICA",_xlpm._nit="0"),_xlpm._cod,_xlpm._nit))} -> 860016941-6 | C36: Fundación Toma un Niño de la Mano | D36: CUATERNARIO | F36: =IF(Tbla_entidades[[#This Row],[CIUU]]="","",_xlfn.XLOOKUP(Tbla_entidades[[#This Row],[CIUU]],Listas!$N:$N,Listas!$O:$O,"")) | G36: tomalodelamano@gmail.com | H36: 6824285 | I36: CARRERA 98 # 156C- 10 | J36: Suba | K36: Bogotá D.C. | L36: EN EJECUCIÓN | M36: PUJ-04711-20 | N36: 45137
A37: 860024452-1 | B37: {=_xlfn.LET(_xlpm._nit,TRIM(A37&""),_xlpm._rs,TRIM(UPPER(C37&"")),_xlpm._txt,TRIM(SUBSTITUTE(SUBSTITUTE(SUBSTITUTE(SUBSTITUTE(SUBSTITUTE(SUBSTITUTE(SUBSTITUTE(_xlpm._rs,".",""),","," "),"-"," "),"/"," "),"("," "),")"," "),":"," ")),_xlpm._pal,_xlfn.TEXTSPLIT(_xlpm._txt," "),_xlpm._util,_xlfn._xlws.FILTER(_xlpm._pal,ISERROR(MATCH(_xlpm._pal,{"DE";"DEL";"LA";"LAS";"EL";"LOS";"Y";"EN";"PARA";"POR";"CON";"A";"AL";"UN";"UNA";"UNOS";"UNAS"},0))),_xlpm._cod,IFERROR(_xlfn.TEXTJOIN("_",TRUE,LEFT(INDEX(_xlpm._util,1,_xlfn.SEQUENCE(1,MIN(5,COLUMNS(_xlpm._util)))),5)),""),IF(OR(_xlpm._nit="",UPPER(_xlpm._nit)="N/A",UPPER(_xlpm._nit)="NA",UPPER(_xlpm._nit)="SIN NIT",UPPER(_xlpm._nit)="NO APLICA",_xlpm._nit="0"),_xlpm._cod,_xlpm._nit))} -> 860024452-1 | C37: Cámara Regional de la Construcción de Bogotá D. C. y Cundinamarca | D37: CUATERNARIO | E37: 9411 | F37: =IF(Tbla_entidades[[#This Row],[CIUU]]="","",_xlfn.XLOOKUP(Tbla_entidades[[#This Row],[CIUU]],Listas!$N:$N,Listas!$O:$O,"")) -> Actividades de asociaciones empresariales y de empleadores. | G37: jnieto@camacolbyc.co | H37: 7430265 | I37: Carrera 19 No. 90-10 Edificio Camacol Piso 2 | J37: Chapinero | K37: Bogotá D.C. | L37: EN EJECUCIÓN | M37: PUJ-00391-25 | N37: 46841 | O37: Convenio anterior PUJ-07382-19
A38: 860031909-2 | B38: {=_xlfn.LET(_xlpm._nit,TRIM(A38&""),_xlpm._rs,TRIM(UPPER(C38&"")),_xlpm._txt,TRIM(SUBSTITUTE(SUBSTITUTE(SUBSTITUTE(SUBSTITUTE(SUBSTITUTE(SUBSTITUTE(SUBSTITUTE(_xlpm._rs,".",""),","," "),"-"," "),"/"," "),"("," "),")"," "),":"," ")),_xlpm._pal,_xlfn.TEXTSPLIT(_xlpm._txt," "),_xlpm._util,_xlfn._xlws.FILTER(_xlpm._pal,ISERROR(MATCH(_xlpm._pal,{"DE";"DEL";"LA";"LAS";"EL";"LOS";"Y";"EN";"PARA";"POR";"CON";"A";"AL";"UN";"UNA";"UNOS";"UNAS"},0))),_xlpm._cod,IFERROR(_xlfn.TEXTJOIN("_",TRUE,LEFT(INDEX(_xlpm._util,1,_xlfn.SEQUENCE(1,MIN(5,COLUMNS(_xlpm._util)))),5)),""),IF(OR(_xlpm._nit="",UPPER(_xlpm._nit)="N/A",UPPER(_xlpm._nit)="NA",UPPER(_xlpm._nit)="SIN NIT",UPPER(_xlpm._nit)="NO APLICA",_xlpm._nit="0"),_xlpm._cod,_xlpm._nit))} -> 860031909-2 | C38: Fe y Alegría de Colombia | D38: CUATERNARIO | F38: =IF(Tbla_entidades[[#This Row],[CIUU]]="","",_xlfn.XLOOKUP(Tbla_entidades[[#This Row],[CIUU]],Listas!$N:$N,Listas!$O:$O,"")) | G38: dirnal@feyalegria.org.co | H38: 6013209360 | I38: Calle 49d#4 99 | J38: Rafael Uribe Uribe | K38: Bogotá D.C. | L38: SIN CONVENIO | M38: N/A | N38: N/A
A39: 860033857-7 | B39: {=_xlfn.LET(_xlpm._nit,TRIM(A39&""),_xlpm._rs,TRIM(UPPER(C39&"")),_xlpm._txt,TRIM(SUBSTITUTE(SUBSTITUTE(SUBSTITUTE(SUBSTITUTE(SUBSTITUTE(SUBSTITUTE(SUBSTITUTE(_xlpm._rs,".",""),","," "),"-"," "),"/"," "),"("," "),")"," "),":"," ")),_xlpm._pal,_xlfn.TEXTSPLIT(_xlpm._txt," "),_xlpm._util,_xlfn._xlws.FILTER(_xlpm._pal,ISERROR(MATCH(_xlpm._pal,{"DE";"DEL";"LA";"LAS";"EL";"LOS";"Y";"EN";"PARA";"POR";"CON";"A";"AL";"UN";"UNA";"UNOS";"UNAS"},0))),_xlpm._cod,IFERROR(_xlfn.TEXTJOIN("_",TRUE,LEFT(INDEX(_xlpm._util,1,_xlfn.SEQUENCE(1,MIN(5,COLUMNS(_xlpm._util)))),5)),""),IF(OR(_xlpm._nit="",UPPER(_xlpm._nit)="N/A",UPPER(_xlpm._nit)="NA",UPPER(_xlpm._nit)="SIN NIT",UPPER(_xlpm._nit)="NO APLICA",_xlpm._nit="0"),_xlpm._cod,_xlpm._nit))} -> 860033857-7 | C39: Fundación Centro de Investigación y Educación Popular - CINEP | F39: =IF(Tbla_entidades[[#This Row],[CIUU]]="","",_xlfn.XLOOKUP(Tbla_entidades[[#This Row],[CIUU]],Listas!$N:$N,Listas!$O:$O,"")) | I39: Cra 5 No. 33B-02 | J39: Santa Fé | K39: Bogotá D.C.
A40: 860504924-4 | B40: {=_xlfn.LET(_xlpm._nit,TRIM(A40&""),_xlpm._rs,TRIM(UPPER(C40&"")),_xlpm._txt,TRIM(SUBSTITUTE(SUBSTITUTE(SUBSTITUTE(SUBSTITUTE(SUBSTITUTE(SUBSTITUTE(SUBSTITUTE(_xlpm._rs,".",""),","," "),"-"," "),"/"," "),"("," "),")"," "),":"," ")),_xlpm._pal,_xlfn.TEXTSPLIT(_xlpm._txt," "),_xlpm._util,_xlfn._xlws.FILTER(_xlpm._pal,ISERROR(MATCH(_xlpm._pal,{"DE";"DEL";"LA";"LAS";"EL";"LOS";"Y";"EN";"PARA";"POR";"CON";"A";"AL";"UN";"UNA";"UNOS";"UNAS"},0))),_xlpm._cod,IFERROR(_xlfn.TEXTJOIN("_",TRUE,LEFT(INDEX(_xlpm._util,1,_xlfn.SEQUENCE(1,MIN(5,COLUMNS(_xlpm._util)))),5)),""),IF(OR(_xlpm._nit="",UPPER(_xlpm._nit)="N/A",UPPER(_xlpm._nit)="NA",UPPER(_xlpm._nit)="SIN NIT",UPPER(_xlpm._nit)="NO APLICA",_xlpm._nit="0"),_xlpm._cod,_xlpm._nit))} -> 860504924-4 | C40: Fundación Voluntariado Juan Pablo II | D40: CUATERNARIO | F40: =IF(Tbla_entidades[[#This Row],[CIUU]]="","",_xlfn.XLOOKUP(Tbla_entidades[[#This Row],[CIUU]],Listas!$N:$N,Listas!$O:$O,"")) | G40: administracion@fundacionjuanpabloii.com | H40: 2404603 7033420 | I40: Carrera 28A No. 75-24 | J40: Barrios Unidos | K40: Bogotá D.C. | L40: EN EJECUCIÓN | M40: PUJ-05890-19 | N40: 44777
A41: 860514058-3 | B41: {=_xlfn.LET(_xlpm._nit,TRIM(A41&""),_xlpm._rs,TRIM(UPPER(C41&"")),_xlpm._txt,TRIM(SUBSTITUTE(SUBSTITUTE(SUBSTITUTE(SUBSTITUTE(SUBSTITUTE(SUBSTITUTE(SUBSTITUTE(_xlpm._rs,".",""),","," "),"-"," "),"/"," "),"("," "),")"," "),":"," ")),_xlpm._pal,_xlfn.TEXTSPLIT(_xlpm._txt," "),_xlpm._util,_xlfn._xlws.FILTER(_xlpm._pal,ISERROR(MATCH(_xlpm._pal,{"DE";"DEL";"LA";"LAS";"EL";"LOS";"Y";"EN";"PARA";"POR";"CON";"A";"AL";"UN";"UNA";"UNOS";"UNAS"},0))),_xlpm._cod,IFERROR(_xlfn.TEXTJOIN("_",TRUE,LEFT(INDEX(_xlpm._util,1,_xlfn.SEQUENCE(1,MIN(5,COLUMNS(_xlpm._util)))),5)),""),IF(OR(_xlpm._nit="",UPPER(_xlpm._nit)="N/A",UPPER(_xlpm._nit)="NA",UPPER(_xlpm._nit)="SIN NIT",UPPER(_xlpm._nit)="NO APLICA",_xlpm._nit="0"),_xlpm._cod,_xlpm._nit))} -> 860514058-3 | C41: Corporación Talleres de Capacitación y Desarrollo Esperanza | D41: CUATERNARIO | F41: =IF(Tbla_entidades[[#This Row],[CIUU]]="","",_xlfn.XLOOKUP(Tbla_entidades[[#This Row],[CIUU]],Listas!$N:$N,Listas!$O:$O,"")) | G41: dirección@talleresesperanza.com | H41: 6164077 / 2189756 | I41: Cra 48# 98-09 | J41: Barrios Unidos | K41: Bogotá D.C. | L41: EN EJECUCIÓN | M41: PUJ-04948-19 | N41: 44767
A42: 860521331-9 | B42: {=_xlfn.LET(_xlpm._nit,TRIM(A42&""),_xlpm._rs,TRIM(UPPER(C42&"")),_xlpm._txt,TRIM(SUBSTITUTE(SUBSTITUTE(SUBSTITUTE(SUBSTITUTE(SUBSTITUTE(SUBSTITUTE(SUBSTITUTE(_xlpm._rs,".",""),","," "),"-"," "),"/"," "),"("," "),")"," "),":"," ")),_xlpm._pal,_xlfn.TEXTSPLIT(_xlpm._txt," "),_xlpm._util,_xlfn._xlws.FILTER(_xlpm._pal,ISERROR(MATCH(_xlpm._pal,{"DE";"DEL";"LA";"LAS";"EL";"LOS";"Y";"EN";"PARA";"POR";"CON";"A";"AL";"UN";"UNA";"UNOS";"UNAS"},0))),_xlpm._cod,IFERROR(_xlfn.TEXTJOIN("_",TRUE,LEFT(INDEX(_xlpm._util,1,_xlfn.SEQUENCE(1,MIN(5,COLUMNS(_xlpm._util)))),5)),""),IF(OR(_xlpm._nit="",UPPER(_xlpm._nit)="N/A",UPPER(_xlpm._nit)="NA",UPPER(_xlpm._nit)="SIN NIT",UPPER(_xlpm._nit)="NO APLICA",_xlpm._nit="0"),_xlpm._cod,_xlpm._nit))} -> 860521331-9 | C42: Federación Asofamilias Jesuitas en Colombia | D42: CUATERNARIO | F42: =IF(Tbla_entidades[[#This Row],[CIUU]]="","",_xlfn.XLOOKUP(Tbla_entidades[[#This Row],[CIUU]],Listas!$N:$N,Listas!$O:$O,"")) | G42: presidencia@fedeasofamilias.org | H42: 3436300 | I42: Cr 5 No. 33 B 80 | J42: Santafé | K42: Bogotá D.C. | L42: EN EJECUCIÓN | M42: PUJ-01480-21 | N42: 45375
A43: 860532248-2 | B43: {=_xlfn.LET(_xlpm._nit,TRIM(A43&""),_xlpm._rs,TRIM(UPPER(C43&"")),_xlpm._txt,TRIM(SUBSTITUTE(SUBSTITUTE(SUBSTITUTE(SUBSTITUTE(SUBSTITUTE(SUBSTITUTE(SUBSTITUTE(_xlpm._rs,".",""),","," "),"-"," "),"/"," "),"("," "),")"," "),":"," ")),_xlpm._pal,_xlfn.TEXTSPLIT(_xlpm._txt," "),_xlpm._util,_xlfn._xlws.FILTER(_xlpm._pal,ISERROR(MATCH(_xlpm._pal,{"DE";"DEL";"LA";"LAS";"EL";"LOS";"Y";"EN";"PARA";"POR";"CON";"A";"AL";"UN";"UNA";"UNOS";"UNAS"},0))),_xlpm._cod,IFERROR(_xlfn.TEXTJOIN("_",TRUE,LEFT(INDEX(_xlpm._util,1,_xlfn.SEQUENCE(1,MIN(5,COLUMNS(_xlpm._util)))),5)),""),IF(OR(_xlpm._nit="",UPPER(_xlpm._nit)="N/A",UPPER(_xlpm._nit)="NA",UPPER(_xlpm._nit)="SIN NIT",UPPER(_xlpm._nit)="NO APLICA",_xlpm._nit="0"),_xlpm._cod,_xlpm._nit))} -> 860532248-2 | C43: Colegio Rodrigo Lara Bonilla | D43: TERCIARIO | E43: 8521 | F43: =IF(Tbla_entidades[[#This Row],[CIUU]]="","",_xlfn.XLOOKUP(Tbla_entidades[[#This Row],[CIUU]],Listas!$N:$N,Listas!$O:$O,"")) -> Educación básica secundaria. | G43: rectoria@colegiorodrigolarabonilla.edu.co | H43: 7181047 | I43: Cra 43A N66-51 Sur | J43: Ciudad Bolívar | K43: Bogotá D.C. | L43: EN EJECUCIÓN | M43: PUJ-05638-19 | N43: 44771
A44: 900030381-4 | B44: {=_xlfn.LET(_xlpm._nit,TRIM(A44&""),_xlpm._rs,TRIM(UPPER(C44&"")),_xlpm._txt,TRIM(SUBSTITUTE(SUBSTITUTE(SUBSTITUTE(SUBSTITUTE(SUBSTITUTE(SUBSTITUTE(SUBSTITUTE(_xlpm._rs,".",""),","," "),"-"," "),"/"," "),"("," "),")"," "),":"," ")),_xlpm._pal,_xlfn.TEXTSPLIT(_xlpm._txt," "),_xlpm._util,_xlfn._xlws.FILTER(_xlpm._pal,ISERROR(MATCH(_xlpm._pal,{"DE";"DEL";"LA";"LAS";"EL";"LOS";"Y";"EN";"PARA";"POR";"CON";"A";"AL";"UN";"UNA";"UNOS";"UNAS"},0))),_xlpm._cod,IFERROR(_xlfn.TEXTJOIN("_",TRUE,LEFT(INDEX(_xlpm._util,1,_xlfn.SEQUENCE(1,MIN(5,COLUMNS(_xlpm._util)))),5)),""),IF(OR(_xlpm._nit="",UPPER(_xlpm._nit)="N/A",UPPER(_xlpm._nit)="NA",UPPER(_xlpm._nit)="SIN NIT",UPPER(_xlpm._nit)="NO APLICA",_xlpm._nit="0"),_xlpm._cod,_xlpm._nit))} -> 900030381-4 | C44: Colegio San Gregorio Hernández | D44: TERCIARIO | E44: 8521 | F44: =IF(Tbla_entidades[[#This Row],[CIUU]]="","",_xlfn.XLOOKUP(Tbla_entidades[[#This Row],[CIUU]],Listas!$N:$N,Listas!$O:$O,"")) -> Educación básica secundaria. | G44: colsgh@gmail.com | H44: 7613806 | I44: K 12#76-27 SUR | J44: Usme | K44: Bogotá D.C. | L44: EN EJECUCIÓN | M44: PUJ-04707-20 | N44: 45137
